Workbook

Sheet DisruptRadar Business Plan · Ma
A1: DisruptRadar Business Plan · Matriz de cenários DisruptRadar
A2: Financial model (2 pages) · Base
A4: Variable / dimension | B4: Value | C4: Value > Pessimista | D4: Value > Otimista
A5: Subscritores (fim de ano) | B5: =40 -> 40 | C5: =12 -> 12 | D5: =100 -> 100
A6: Receita anual realizada (EUR) | B6: =30096 -> 30096 | C6: =8000 -> 8000 | D6: =80000 -> 80000
A7: Custos anuais (EUR) | B7: =15120 -> 15120 | C7: =6000 -> 6000 | D7: =24000 -> 24000
A8: EBITDA (EUR) | B8: ='DisruptRadar Business Plan · Ma'!B6-'DisruptRadar Business Plan · Ma'!B7 -> 14976 | C8: ='DisruptRadar Business Plan · Ma'!C6-'DisruptRadar Business Plan · Ma'!C7 -> 2000 | D8: ='DisruptRadar Business Plan · Ma'!D6-'DisruptRadar Business Plan · Ma'!D7 -> 56000
A9: Margem bruta | B9: =0.8 -> 0.8 | C9: =0.75 -> 0.75 | D9: =0.85 -> 0.85
A10: Cobertura de caixa com receita zero (meses) | B10: =IFERROR('DisruptRadar Business Plan · Pr'!B7/'DisruptRadar Business Plan · Ma'!B7*12,"") -> 15.873016 | C10: =IFERROR('Model inputs'!Z13/'DisruptRadar Business Plan · Ma'!C7*12,"") -> 40 | D10: =IFERROR('Model inputs'!Z14/'DisruptRadar Business Plan · Ma'!D7*12,"") -> 10

Sheet DisruptRadar Business Plan · Pr
A1: DisruptRadar Business Plan · Premissas DisruptRadar — Ano 1
A2: Financial model (2 pages) · Base
A4: Variable / dimension | B4: Value
A5: Preço mensal Pro (EUR) | B5: =99 -> 99
A6: Preço mensal Enterprise proposto (EUR) | B6: =499 -> 499
A7: Caixa inicial (EUR) | B7: =20000 -> 20000
A8: Custo fixo mensal (EUR) | B8: =500 -> 500
A9: Mercado endereçável mínimo (contas) | B9: =500 -> 500
A10: Mercado endereçável máximo (contas) | B10: =1000 -> 1000
A11: Custo variável por domínio por mês — estimativa (EUR) | B11: =3 -> 3
A12: Margem Pro após custo variável — um domínio por subscritor | B12: =IFERROR(1-'DisruptRadar Business Plan · Pr'!B11/'DisruptRadar Business Plan · Pr'!B5,"") -> 0.96969697
A13: Domínios incluídos no plano Pro | B13: =10 -> 10
A14: Domínios médios por cliente Pro — hipótese | B14: =10 -> 10
A15: Custo mensal de entrega por cliente Pro (EUR) | B15: ='DisruptRadar Business Plan · Pr'!B14*'DisruptRadar Business Plan · Pr'!B11 -> 30
A16: Margem de contribuição Pro — utilização média | B16: =IFERROR(('DisruptRadar Business Plan · Pr'!B5-'DisruptRadar Business Plan · Pr'!B15)/'DisruptRadar Business Plan · Pr'!B5,"") -> 0.6969697

Sheet DisruptRadar Business Plan · Cu
A1: DisruptRadar Business Plan · Custo de entrega ligado à utilização — referência Pro
A2: Financial model (2 pages) · Base
A4: Variable / dimension | B4: Value | C4: Value > Pessimista | D4: Value > Otimista
A5: Subscritores (fim de ano) | B5: =40 -> 40 | C5: ='DisruptRadar Business Plan · Ma'!C5 -> 12 | D5: ='DisruptRadar Business Plan · Ma'!D5 -> 100
A6: Domínios monitorizados ao fim do ano — referência Pro | B6: ='DisruptRadar Business Plan · Pr'!B14*'DisruptRadar Business Plan · Cu'!B5 -> 400 | C6: ='Model inputs'!Z38*'DisruptRadar Business Plan · Cu'!C5 -> 120 | D6: ='Model inputs'!Z39*'DisruptRadar Business Plan · Cu'!D5 -> 1000
A7: Custo mensal de entrega ao fim do ano — referência Pro (EUR) | B7: ='DisruptRadar Business Plan · Pr'!B14*'DisruptRadar Business Plan · Pr'!B11*'DisruptRadar Business Plan · Cu'!B5 -> 1200 | C7: ='Model inputs'!Z38*'Model inputs'!Z28*'DisruptRadar Business Plan · Cu'!C5 -> 360 | D7: ='Model inputs'!Z39*'Model inputs'!Z29*'DisruptRadar Business Plan · Cu'!D5 -> 3000

Sheet DisruptRadar — Projeção mensal
A1: DisruptRadar — Projeção mensal · Controlos da projeção Base
A2: Financial model (2 pages) · Base
A4: Variable / dimension | B4: Value
A5: Fixos anuais da projeção Base (EUR) | B5: =6000 -> 6000
A6: Início da projeção Base | B6: =DATE(2027,1,1) -> 46388
A7: Preço mensal Pro (EUR) | B7: =99 -> 99
A8: Domínios médios por cliente Pro — hipótese | B8: =10 -> 10
A9: Custo variável por domínio por mês — estimativa (EUR) | B9: =3 -> 3
A10: Caixa inicial (EUR) | B10: =20000 -> 20000

Sheet DisruptRadar — Projeção men (2)
A1: DisruptRadar — Projeção mensal · Projeção mensal Base — clientes, resultado e caixa
A2: Financial model (2 pages) · Base
A4: Variable / dimension | B4: 2027-01 | C4: 2027-02 | D4: 2027-03 | E4: 2027-04 | F4: 2027-05 | G4: 2027-06 | H4: 2027-07 | I4: 2027-08 | J4: 2027-09 | K4: 2027-10 | L4: 2027-11 | M4: 2027-12
A5: Clientes no fim do mês — projeção Base | B5: =1 -> 1 | C5: =4 -> 4 | D5: =9 -> 9 | E5: =14 -> 14 | F5: =20 -> 20 | G5: =26 -> 26 | H5: =32 -> 32 | I5: =38 -> 38 | J5: =40 -> 40 | K5: =40 -> 40 | L5: =40 -> 40 | M5: =40 -> 40
A6: Receita mensal — projeção Base (EUR) | B6: ='DisruptRadar — Projeção men (2)'!B5*'DisruptRadar Business Plan · Pr'!B5 -> 99 | C6: ='DisruptRadar — Projeção men (2)'!C5*'DisruptRadar Business Plan · Pr'!B5 -> 396 | D6: ='DisruptRadar — Projeção men (2)'!D5*'DisruptRadar Business Plan · Pr'!B5 -> 891 | E6: ='DisruptRadar — Projeção men (2)'!E5*'DisruptRadar Business Plan · Pr'!B5 -> 1386 | F6: ='DisruptRadar — Projeção men (2)'!F5*'DisruptRadar Business Plan · Pr'!B5 -> 1980 | G6: ='DisruptRadar — Projeção men (2)'!G5*'DisruptRadar Business Plan · Pr'!B5 -> 2574 | H6: ='DisruptRadar — Projeção men (2)'!H5*'DisruptRadar Business Plan · Pr'!B5 -> 3168 | I6: ='DisruptRadar — Projeção men (2)'!I5*'DisruptRadar Business Plan · Pr'!B5 -> 3762 | J6: ='DisruptRadar — Projeção men (2)'!J5*'DisruptRadar Business Plan · Pr'!B5 -> 3960 | K6: ='DisruptRadar — Projeção men (2)'!K5*'DisruptRadar Business Plan · Pr'!B5 -> 3960 | L6: ='DisruptRadar — Projeção men (2)'!L5*'DisruptRadar Business Plan · Pr'!B5 -> 3960 | M6: ='DisruptRadar — Projeção men (2)'!M5*'DisruptRadar Business Plan · Pr'!B5 -> 3960
A7: Entrega mensal — projeção Base (EUR) | B7: ='DisruptRadar — Projeção men (2)'!B5*'DisruptRadar Business Plan · Pr'!B14*'DisruptRadar Business Plan · Pr'!B11 -> 30 | C7: ='DisruptRadar — Projeção men (2)'!C5*'DisruptRadar Business Plan · Pr'!B14*'DisruptRadar Business Plan · Pr'!B11 -> 120 | D7: ='DisruptRadar — Projeção men (2)'!D5*'DisruptRadar Business Plan · Pr'!B14*'DisruptRadar Business Plan · Pr'!B11 -> 270 | E7: ='DisruptRadar — Projeção men (2)'!E5*'DisruptRadar Business Plan · Pr'!B14*'DisruptRadar Business Plan · Pr'!B11 -> 420 | F7: ='DisruptRadar — Projeção men (2)'!F5*'DisruptRadar Business Plan · Pr'!B14*'DisruptRadar Business Plan · Pr'!B11 -> 600 | G7: ='DisruptRadar — Projeção men (2)'!G5*'DisruptRadar Business Plan · Pr'!B14*'DisruptRadar Business Plan · Pr'!B11 -> 780 | H7: ='DisruptRadar — Projeção men (2)'!H5*'DisruptRadar Business Plan · Pr'!B14*'DisruptRadar Business Plan · Pr'!B11 -> 960 | I7: ='DisruptRadar — Projeção men (2)'!I5*'DisruptRadar Business Plan · Pr'!B14*'DisruptRadar Business Plan · Pr'!B11 -> 1140 | J7: ='DisruptRadar — Projeção men (2)'!J5*'DisruptRadar Business Plan · Pr'!B14*'DisruptRadar Business Plan · Pr'!B11 -> 1200 | K7: ='DisruptRadar — Projeção men (2)'!K5*'DisruptRadar Business Plan · Pr'!B14*'DisruptRadar Business Plan · Pr'!B11 -> 1200 | L7: ='DisruptRadar — Projeção men (2)'!L5*'DisruptRadar Business Plan · Pr'!B14*'DisruptRadar Business Plan · Pr'!B11 -> 1200 | M7: ='DisruptRadar — Projeção men (2)'!M5*'DisruptRadar Business Plan · Pr'!B14*'DisruptRadar Business Plan · Pr'!B11 -> 1200
A8: Fixos mensais — projeção Base (EUR) | B8: ='DisruptRadar — Projeção mensal'!B5/12 -> 500 | C8: ='DisruptRadar — Projeção mensal'!B5/12 -> 500 | D8: ='DisruptRadar — Projeção mensal'!B5/12 -> 500 | E8: ='DisruptRadar — Projeção mensal'!B5/12 -> 500 | F8: ='DisruptRadar — Projeção mensal'!B5/12 -> 500 | G8: ='DisruptRadar — Projeção mensal'!B5/12 -> 500 | H8: ='DisruptRadar — Projeção mensal'!B5/12 -> 500 | I8: ='DisruptRadar — Projeção mensal'!B5/12 -> 500 | J8: ='DisruptRadar — Projeção mensal'!B5/12 -> 500 | K8: ='DisruptRadar — Projeção mensal'!B5/12 -> 500 | L8: ='DisruptRadar — Projeção mensal'!B5/12 -> 500 | M8: ='DisruptRadar — Projeção mensal'!B5/12 -> 500
A9: Custos totais mensais — projeção Base (EUR) | B9: ='DisruptRadar — Projeção men (2)'!B7+'DisruptRadar — Projeção men (2)'!B8 -> 530 | C9: ='DisruptRadar — Projeção men (2)'!C7+'DisruptRadar — Projeção men (2)'!C8 -> 620 | D9: ='DisruptRadar — Projeção men (2)'!D7+'DisruptRadar — Projeção men (2)'!D8 -> 770 | E9: ='DisruptRadar — Projeção men (2)'!E7+'DisruptRadar — Projeção men (2)'!E8 -> 920 | F9: ='DisruptRadar — Projeção men (2)'!F7+'DisruptRadar — Projeção men (2)'!F8 -> 1100 | G9: ='DisruptRadar — Projeção men (2)'!G7+'DisruptRadar — Projeção men (2)'!G8 -> 1280 | H9: ='DisruptRadar — Projeção men (2)'!H7+'DisruptRadar — Projeção men (2)'!H8 -> 1460 | I9: ='DisruptRadar — Projeção men (2)'!I7+'DisruptRadar — Projeção men (2)'!I8 -> 1640 | ... M9: ='DisruptRadar — Projeção men (2)'!M7+'DisruptRadar — Projeção men (2)'!M8 -> 1700
A10: EBITDA mensal — projeção Base (EUR) | B10: ='DisruptRadar — Projeção men (2)'!B6-'DisruptRadar — Projeção men (2)'!B9 -> -431 | C10: ='DisruptRadar — Projeção men (2)'!C6-'DisruptRadar — Projeção men (2)'!C9 -> -224 | D10: ='DisruptRadar — Projeção men (2)'!D6-'DisruptRadar — Projeção men (2)'!D9 -> 121 | E10: ='DisruptRadar — Projeção men (2)'!E6-'DisruptRadar — Projeção men (2)'!E9 -> 466 | F10: ='DisruptRadar — Projeção men (2)'!F6-'DisruptRadar — Projeção men (2)'!F9 -> 880 | G10: ='DisruptRadar — Projeção men (2)'!G6-'DisruptRadar — Projeção men (2)'!G9 -> 1294 | H10: ='DisruptRadar — Projeção men (2)'!H6-'DisruptRadar — Projeção men (2)'!H9 -> 1708 | I10: ='DisruptRadar — Projeção men (2)'!I6-'DisruptRadar — Projeção men (2)'!I9 -> 2122 | ... M10: ='DisruptRadar — Projeção men (2)'!M6-'DisruptRadar — Projeção men (2)'!M9 -> 2260
A11: Caixa inicial do mês — projeção Base (EUR) | B11: =IF(IF(IF(ISERROR(DATE(2027,1,1)=DATE(YEAR('DisruptRadar — Projeção mensal'!B6),MONTH('DisruptRadar — Projeção mensal'!B6),1)),DATE(2027,1,1)=DATE(YEAR('DisruptRadar — Projeção mensal'!B6),MONTH('DisruptRadar — Projeção mensal'!B6),1),IF(DATE(YEAR('DisruptRadar — Projeção mensal'!B6),MONTH('DisruptRadar — Projeção mensal'!B6),1)="","",DATE(2027,1,1)=DATE(YEAR('DisruptRadar — Projeção mensal'!B6),MONTH('DisruptRadar — Projeção mensal'!B6),1)))="",FALSE,IF(ISERROR(DATE(2027,1,1)=DATE(YEAR('DisruptRadar — Projeção mensal'!B6),MONTH('DisruptRadar — Projeção mensal'!B6),1)),DATE(2027,1,1)=DATE(YEAR('DisruptRadar — Projeção mensal'!B6),MONTH('DisruptRadar — Projeção mensal'!B6),1),IF(DATE(YEAR('DisruptRadar — Projeção mensal'!B6),MONTH('DisruptRadar — Projeção mensal'!B6),1)="","",DATE(2027,1,1)=DATE(YEAR('DisruptRadar — Projeção mensal'!B6),MONTH('DisruptRadar — Projeção mensal'!B6),1)))),IF('DisruptRadar Business Plan · Pr'!B7="","",'DisruptRadar Business Plan · Pr'!B7),IF('Model inputs'!B6="","",'Model inputs'!B6)) -> 20000 | C11: =IF(IF(IF(ISERROR(DATE(2027,2,1)=DATE(YEAR('DisruptRadar — Projeção mensal'!B6),MONTH('DisruptRadar — Projeção mensal'!B6),1)),DATE(2027,2,1)=DATE(YEAR('DisruptRadar — Projeção mensal'!B6),MONTH('DisruptRadar — Projeção mensal'!B6),1),IF(DATE(YEAR('DisruptRadar — Projeção mensal'!B6),MONTH('DisruptRadar — Projeção mensal'!B6),1)="","",DATE(2027,2,1)=DATE(YEAR('DisruptRadar — Projeção mensal'!B6),MONTH('DisruptRadar — Projeção mensal'!B6),1)))="",FALSE,IF(ISERROR(DATE(2027,2,1)=DATE(YEAR('DisruptRadar — Projeção mensal'!B6),MONTH('DisruptRadar — Projeção mensal'!B6),1)),DATE(2027,2,1)=DATE(YEAR('DisruptRadar — Projeção mensal'!B6),MONTH('DisruptRadar — Projeção mensal'!B6),1),IF(DATE(YEAR('DisruptRadar — Projeção mensal'!B6),MONTH('DisruptRadar — Projeção mensal'!B6),1)="","",DATE(2027,2,1)=DATE(YEAR('DisruptRadar — Projeção mensal'!B6),MONTH('DisruptRadar — Projeção mensal'!B6),1)))),IF('DisruptRadar Business Plan · Pr'!B7="","",'DisruptRadar Business Plan · Pr'!B7),IF('DisruptRadar — Projeção men (2)'!B12="","",'DisruptRadar — Projeção men (2)'!B12)) -> 19569 | D11: =IF(IF(IF(ISERROR(DATE(2027,3,1)=DATE(YEAR('DisruptRadar — Projeção mensal'!B6),MONTH('DisruptRadar — Projeção mensal'!B6),1)),DATE(2027,3,1)=DATE(YEAR('DisruptRadar — Projeção mensal'!B6),MONTH('DisruptRadar — Projeção mensal'!B6),1),IF(DATE(YEAR('DisruptRadar — Projeção mensal'!B6),MONTH('DisruptRadar — Projeção mensal'!B6),1)="","",DATE(2027,3,1)=DATE(YEAR('DisruptRadar — Projeção mensal'!B6),MONTH('DisruptRadar — Projeção mensal'!B6),1)))="",FALSE,IF(ISERROR(DATE(2027,3,1)=DATE(YEAR('DisruptRadar — Projeção mensal'!B6),MONTH('DisruptRadar — Projeção mensal'!B6),1)),DATE(2027,3,1)=DATE(YEAR('DisruptRadar — Projeção mensal'!B6),MONTH('DisruptRadar — Projeção mensal'!B6),1),IF(DATE(YEAR('DisruptRadar — Projeção mensal'!B6),MONTH('DisruptRadar — Projeção mensal'!B6),1)="","",DATE(2027,3,1)=DATE(YEAR('DisruptRadar — Projeção mensal'!B6),MONTH('DisruptRadar — Projeção mensal'!B6),1)))),IF('DisruptRadar Business Plan · Pr'!B7="","",'DisruptRadar Business Plan · Pr'!B7),IF('DisruptRadar — Projeção men (2)'!C12="","",'DisruptRadar — Projeção men (2)'!C12)) -> 19345 | E11: =IF(IF(IF(ISERROR(DATE(2027,4,1)=DATE(YEAR('DisruptRadar — Projeção mensal'!B6),MONTH('DisruptRadar — Projeção mensal'!B6),1)),DATE(2027,4,1)=DATE(YEAR('DisruptRadar — Projeção mensal'!B6),MONTH('DisruptRadar — Projeção mensal'!B6),1),IF(DATE(YEAR('DisruptRadar — Projeção mensal'!B6),MONTH('DisruptRadar — Projeção mensal'!B6),1)="","",DATE(2027,4,1)=DATE(YEAR('DisruptRadar — Projeção mensal'!B6),MONTH('DisruptRadar — Projeção mensal'!B6),1)))="",FALSE,IF(ISERROR(DATE(2027,4,1)=DATE(YEAR('DisruptRadar — Projeção mensal'!B6),MONTH('DisruptRadar — Projeção mensal'!B6),1)),DATE(2027,4,1)=DATE(YEAR('DisruptRadar — Projeção mensal'!B6),MONTH('DisruptRadar — Projeção mensal'!B6),1),IF(DATE(YEAR('DisruptRadar — Projeção mensal'!B6),MONTH('DisruptRadar — Projeção mensal'!B6),1)="","",DATE(2027,4,1)=DATE(YEAR('DisruptRadar — Projeção mensal'!B6),MONTH('DisruptRadar — Projeção mensal'!B6),1)))),IF('DisruptRadar Business Plan · Pr'!B7="","",'DisruptRadar Business Plan · Pr'!B7),IF('DisruptRadar — Projeção men (2)'!D12="","",'DisruptRadar — Projeção men (2)'!D12)) -> 19466 | F11: =IF(IF(IF(ISERROR(DATE(2027,5,1)=DATE(YEAR('DisruptRadar — Projeção mensal'!B6),MONTH('DisruptRadar — Projeção mensal'!B6),1)),DATE(2027,5,1)=DATE(YEAR('DisruptRadar — Projeção mensal'!B6),MONTH('DisruptRadar — Projeção mensal'!B6),1),IF(DATE(YEAR('DisruptRadar — Projeção mensal'!B6),MONTH('DisruptRadar — Projeção mensal'!B6),1)="","",DATE(2027,5,1)=DATE(YEAR('DisruptRadar — Projeção mensal'!B6),MONTH('DisruptRadar — Projeção mensal'!B6),1)))="",FALSE,IF(ISERROR(DATE(2027,5,1)=DATE(YEAR('DisruptRadar — Projeção mensal'!B6),MONTH('DisruptRadar — Projeção mensal'!B6),1)),DATE(2027,5,1)=DATE(YEAR('DisruptRadar — Projeção mensal'!B6),MONTH('DisruptRadar — Projeção mensal'!B6),1),IF(DATE(YEAR('DisruptRadar — Projeção mensal'!B6),MONTH('DisruptRadar — Projeção mensal'!B6),1)="","",DATE(2027,5,1)=DATE(YEAR('DisruptRadar — Projeção mensal'!B6),MONTH('DisruptRadar — Projeção mensal'!B6),1)))),IF('DisruptRadar Business Plan · Pr'!B7="","",'DisruptRadar Business Plan · Pr'!B7),IF('DisruptRadar — Projeção men (2)'!E12="","",'DisruptRadar — Projeção men (2)'!E12)) -> 19932 | G11: =IF(IF(IF(ISERROR(DATE(2027,6,1)=DATE(YEAR('DisruptRadar — Projeção mensal'!B6),MONTH('DisruptRadar — Projeção mensal'!B6),1)),DATE(2027,6,1)=DATE(YEAR('DisruptRadar — Projeção mensal'!B6),MONTH('DisruptRadar — Projeção mensal'!B6),1),IF(DATE(YEAR('DisruptRadar — Projeção mensal'!B6),MONTH('DisruptRadar — Projeção mensal'!B6),1)="","",DATE(2027,6,1)=DATE(YEAR('DisruptRadar — Projeção mensal'!B6),MONTH('DisruptRadar — Projeção mensal'!B6),1)))="",FALSE,IF(ISERROR(DATE(2027,6,1)=DATE(YEAR('DisruptRadar — Projeção mensal'!B6),MONTH('DisruptRadar — Projeção mensal'!B6),1)),DATE(2027,6,1)=DATE(YEAR('DisruptRadar — Projeção mensal'!B6),MONTH('DisruptRadar — Projeção mensal'!B6),1),IF(DATE(YEAR('DisruptRadar — Projeção mensal'!B6),MONTH('DisruptRadar — Projeção mensal'!B6),1)="","",DATE(2027,6,1)=DATE(YEAR('DisruptRadar — Projeção mensal'!B6),MONTH('DisruptRadar — Projeção mensal'!B6),1)))),IF('DisruptRadar Business Plan · Pr'!B7="","",'DisruptRadar Business Plan · Pr'!B7),IF('DisruptRadar — Projeção men (2)'!F12="","",'DisruptRadar — Projeção men (2)'!F12)) -> 20812 | H11: =IF(IF(IF(ISERROR(DATE(2027,7,1)=DATE(YEAR('DisruptRadar — Projeção mensal'!B6),MONTH('DisruptRadar — Projeção mensal'!B6),1)),DATE(2027,7,1)=DATE(YEAR('DisruptRadar — Projeção mensal'!B6),MONTH('DisruptRadar — Projeção mensal'!B6),1),IF(DATE(YEAR('DisruptRadar — Projeção mensal'!B6),MONTH('DisruptRadar — Projeção mensal'!B6),1)="","",DATE(2027,7,1)=DATE(YEAR('DisruptRadar — Projeção mensal'!B6),MONTH('DisruptRadar — Projeção mensal'!B6),1)))="",FALSE,IF(ISERROR(DATE(2027,7,1)=DATE(YEAR('DisruptRadar — Projeção mensal'!B6),MONTH('DisruptRadar — Projeção mensal'!B6),1)),DATE(2027,7,1)=DATE(YEAR('DisruptRadar — Projeção mensal'!B6),MONTH('DisruptRadar — Projeção mensal'!B6),1),IF(DATE(YEAR('DisruptRadar — Projeção mensal'!B6),MONTH('DisruptRadar — Projeção mensal'!B6),1)="","",DATE(2027,7,1)=DATE(YEAR('DisruptRadar — Projeção mensal'!B6),MONTH('DisruptRadar — Projeção mensal'!B6),1)))),IF('DisruptRadar Business Plan · Pr'!B7="","",'DisruptRadar Business Plan · Pr'!B7),IF('DisruptRadar — Projeção men (2)'!G12="","",'DisruptRadar — Projeção men (2)'!G12)) -> 22106 | I11: =IF(IF(IF(ISERROR(DATE(2027,8,1)=DATE(YEAR('DisruptRadar — Projeção mensal'!B6),MONTH('DisruptRadar — Projeção mensal'!B6),1)),DATE(2027,8,1)=DATE(YEAR('DisruptRadar — Projeção mensal'!B6),MONTH('DisruptRadar — Projeção mensal'!B6),1),IF(DATE(YEAR('DisruptRadar — Projeção mensal'!B6),MONTH('DisruptRadar — Projeção mensal'!B6),1)="","",DATE(2027,8,1)=DATE(YEAR('DisruptRadar — Projeção mensal'!B6),MONTH('DisruptRadar — Projeção mensal'!B6),1)))="",FALSE,IF(ISERROR(DATE(2027,8,1)=DATE(YEAR('DisruptRadar — Projeção mensal'!B6),MONTH('DisruptRadar — Projeção mensal'!B6),1)),DATE(2027,8,1)=DATE(YEAR('DisruptRadar — Projeção mensal'!B6),MONTH('DisruptRadar — Projeção mensal'!B6),1),IF(DATE(YEAR('DisruptRadar — Projeção mensal'!B6),MONTH('DisruptRadar — Projeção mensal'!B6),1)="","",DATE(2027,8,1)=DATE(YEAR('DisruptRadar — Projeção mensal'!B6),MONTH('DisruptRadar — Projeção mensal'!B6),1)))),IF('DisruptRadar Business Plan · Pr'!B7="","",'DisruptRadar Business Plan · Pr'!B7),IF('DisruptRadar — Projeção men (2)'!H12="","",'DisruptRadar — Projeção men (2)'!H12)) -> 23814 | J11: =IF(IF(IF(ISERROR(DATE(2027,9,1)=DATE(YEAR('DisruptRadar — Projeção mensal'!B6),MONTH('DisruptRadar — Projeção mensal'!B6),1)),DATE(2027,9,1)=DATE(YEAR('DisruptRadar — Projeção mensal'!B6),MONTH('DisruptRadar — Projeção mensal'!B6),1),IF(DATE(YEAR('DisruptRadar — Projeção mensal'!B6),MONTH('DisruptRadar — Projeção mensal'!B6),1)="","",DATE(2027,9,1)=DATE(YEAR('DisruptRadar — Projeção mensal'!B6),MONTH('DisruptRadar — Projeção mensal'!B6),1)))="",FALSE,IF(ISERROR(DATE(2027,9,1)=DATE(YEAR('DisruptRadar — Projeção mensal'!B6),MONTH('DisruptRadar — Projeção mensal'!B6),1)),DATE(2027,9,1)=DATE(YEAR('DisruptRadar — Projeção mensal'!B6),MONTH('DisruptRadar — Projeção mensal'!B6),1),IF(DATE(YEAR('DisruptRadar — Projeção mensal'!B6),MONTH('DisruptRadar — Projeção mensal'!B6),1)="","",DATE(2027,9,1)=DATE(YEAR('DisruptRadar — Projeção mensal'!B6),MONTH('DisruptRadar — Projeção mensal'!B6),1)))),IF('DisruptRadar Business Plan · Pr'!B7="","",'DisruptRadar Business Plan · Pr'!B7),IF('DisruptRadar — Projeção men (2)'!I12="","",'DisruptRadar — Projeção men (2)'!I12)) -> 25936 | K11: =IF(IF(IF(ISERROR(DATE(2027,10,1)=DATE(YEAR('DisruptRadar — Projeção mensal'!B6),MONTH('DisruptRadar — Projeção mensal'!B6),1)),DATE(2027,10,1)=DATE(YEAR('DisruptRadar — Projeção mensal'!B6),MONTH('DisruptRadar — Projeção mensal'!B6),1),IF(DATE(YEAR('DisruptRadar — Projeção mensal'!B6),MONTH('DisruptRadar — Projeção mensal'!B6),1)="","",DATE(2027,10,1)=DATE(YEAR('DisruptRadar — Projeção mensal'!B6),MONTH('DisruptRadar — Projeção mensal'!B6),1)))="",FALSE,IF(ISERROR(DATE(2027,10,1)=DATE(YEAR('DisruptRadar — Projeção mensal'!B6),MONTH('DisruptRadar — Projeção mensal'!B6),1)),DATE(2027,10,1)=DATE(YEAR('DisruptRadar — Projeção mensal'!B6),MONTH('DisruptRadar — Projeção mensal'!B6),1),IF(DATE(YEAR('DisruptRadar — Projeção mensal'!B6),MONTH('DisruptRadar — Projeção mensal'!B6),1)="","",DATE(2027,10,1)=DATE(YEAR('DisruptRadar — Projeção mensal'!B6),MONTH('DisruptRadar — Projeção mensal'!B6),1)))),IF('DisruptRadar Business Plan · Pr'!B7="","",'DisruptRadar Business Plan · Pr'!B7),IF('DisruptRadar — Projeção men (2)'!J12="","",'DisruptRadar — Projeção men (2)'!J12)) -> 28196 | L11: =IF(IF(IF(ISERROR(DATE(2027,11,1)=DATE(YEAR('DisruptRadar — Projeção mensal'!B6),MONTH('DisruptRadar — Projeção mensal'!B6),1)),DATE(2027,11,1)=DATE(YEAR('DisruptRadar — Projeção mensal'!B6),MONTH('DisruptRadar — Projeção mensal'!B6),1),IF(DATE(YEAR('DisruptRadar — Projeção mensal'!B6),MONTH('DisruptRadar — Projeção mensal'!B6),1)="","",DATE(2027,11,1)=DATE(YEAR('DisruptRadar — Projeção mensal'!B6),MONTH('DisruptRadar — Projeção mensal'!B6),1)))="",FALSE,IF(ISERROR(DATE(2027,11,1)=DATE(YEAR('DisruptRadar — Projeção mensal'!B6),MONTH('DisruptRadar — Projeção mensal'!B6),1)),DATE(2027,11,1)=DATE(YEAR('DisruptRadar — Projeção mensal'!B6),MONTH('DisruptRadar — Projeção mensal'!B6),1),IF(DATE(YEAR('DisruptRadar — Projeção mensal'!B6),MONTH('DisruptRadar — Projeção mensal'!B6),1)="","",DATE(2027,11,1)=DATE(YEAR('DisruptRadar — Projeção mensal'!B6),MONTH('DisruptRadar — Projeção mensal'!B6),1)))),IF('DisruptRadar Business Plan · Pr'!B7="","",'DisruptRadar Business Plan · Pr'!B7),IF('DisruptRadar — Projeção men (2)'!K12="","",'DisruptRadar — Projeção men (2)'!K12)) -> 30456 | M11: =IF(IF(IF(ISERROR(DATE(2027,12,1)=DATE(YEAR('DisruptRadar — Projeção mensal'!B6),MONTH('DisruptRadar — Projeção mensal'!B6),1)),DATE(2027,12,1)=DATE(YEAR('DisruptRadar — Projeção mensal'!B6),MONTH('DisruptRadar — Projeção mensal'!B6),1),IF(DATE(YEAR('DisruptRadar — Projeção mensal'!B6),MONTH('DisruptRadar — Projeção mensal'!B6),1)="","",DATE(2027,12,1)=DATE(YEAR('DisruptRadar — Projeção mensal'!B6),MONTH('DisruptRadar — Projeção mensal'!B6),1)))="",FALSE,IF(ISERROR(DATE(2027,12,1)=DATE(YEAR('DisruptRadar — Projeção mensal'!B6),MONTH('DisruptRadar — Projeção mensal'!B6),1)),DATE(2027,12,1)=DATE(YEAR('DisruptRadar — Projeção mensal'!B6),MONTH('DisruptRadar — Projeção mensal'!B6),1),IF(DATE(YEAR('DisruptRadar — Projeção mensal'!B6),MONTH('DisruptRadar — Projeção mensal'!B6),1)="","",DATE(2027,12,1)=DATE(YEAR('DisruptRadar — Projeção mensal'!B6),MONTH('DisruptRadar — Projeção mensal'!B6),1)))),IF('DisruptRadar Business Plan · Pr'!B7="","",'DisruptRadar Business Plan · Pr'!B7),IF('DisruptRadar — Projeção men (2)'!L12="","",'DisruptRadar — Projeção men (2)'!L12)) -> 32716
A12: Caixa final — projeção Base (EUR) | B12: ='DisruptRadar — Projeção men (2)'!B11+'DisruptRadar — Projeção men (2)'!B10 -> 19569 | C12: ='DisruptRadar — Projeção men (2)'!C11+'DisruptRadar — Projeção men (2)'!C10 -> 19345 | D12: ='DisruptRadar — Projeção men (2)'!D11+'DisruptRadar — Projeção men (2)'!D10 -> 19466 | E12: ='DisruptRadar — Projeção men (2)'!E11+'DisruptRadar — Projeção men (2)'!E10 -> 19932 | F12: ='DisruptRadar — Projeção men (2)'!F11+'DisruptRadar — Projeção men (2)'!F10 -> 20812 | G12: ='DisruptRadar — Projeção men (2)'!G11+'DisruptRadar — Projeção men (2)'!G10 -> 22106 | H12: ='DisruptRadar — Projeção men (2)'!H11+'DisruptRadar — Projeção men (2)'!H10 -> 23814 | I12: ='DisruptRadar — Projeção men (2)'!I11+'DisruptRadar — Projeção men (2)'!I10 -> 25936 | ... M12: ='DisruptRadar — Projeção men (2)'!M11+'DisruptRadar — Projeção men (2)'!M10 -> 34976
A13: Movimento de caixa acumulado — projeção Base (EUR) | B13: =IF(IF(IF(IF(ISERROR(DATE(2027,1,1)=DATE(YEAR('DisruptRadar — Projeção mensal'!B6),MONTH('DisruptRadar — Projeção mensal'!B6),1)),DATE(2027,1,1)=DATE(YEAR('DisruptRadar — Projeção mensal'!B6),MONTH('DisruptRadar — Projeção mensal'!B6),1),IF(DATE(YEAR('DisruptRadar — Projeção mensal'!B6),MONTH('DisruptRadar — Projeção mensal'!B6),1)="","",DATE(2027,1,1)=DATE(YEAR('DisruptRadar — Projeção mensal'!B6),MONTH('DisruptRadar — Projeção mensal'!B6),1)))="",FALSE,IF(ISERROR(DATE(2027,1,1)=DATE(YEAR('DisruptRadar — Projeção mensal'!B6),MONTH('DisruptRadar — Projeção mensal'!B6),1)),DATE(2027,1,1)=DATE(YEAR('DisruptRadar — Projeção mensal'!B6),MONTH('DisruptRadar — Projeção mensal'!B6),1),IF(DATE(YEAR('DisruptRadar — Projeção mensal'!B6),MONTH('DisruptRadar — Projeção mensal'!B6),1)="","",DATE(2027,1,1)=DATE(YEAR('DisruptRadar — Projeção mensal'!B6),MONTH('DisruptRadar — Projeção mensal'!B6),1)))),0,IF('Model inputs'!B64="","",'Model inputs'!B64))="",0,IF(IF(IF(ISERROR(DATE(2027,1,1)=DATE(YEAR('DisruptRadar — Projeção mensal'!B6),MONTH('DisruptRadar — Projeção mensal'!B6),1)),DATE(2027,1,1)=DATE(YEAR('DisruptRadar — Projeção mensal'!B6),MONTH('DisruptRadar — Projeção mensal'!B6),1),IF(DATE(YEAR('DisruptRadar — Projeção mensal'!B6),MONTH('DisruptRadar — Projeção mensal'!B6),1)="","",DATE(2027,1,1)=DATE(YEAR('DisruptRadar — Projeção mensal'!B6),MONTH('DisruptRadar — Projeção mensal'!B6),1)))="",FALSE,IF(ISERROR(DATE(2027,1,1)=DATE(YEAR('DisruptRadar — Projeção mensal'!B6),MONTH('DisruptRadar — Projeção mensal'!B6),1)),DATE(2027,1,1)=DATE(YEAR('DisruptRadar — Projeção mensal'!B6),MONTH('DisruptRadar — Projeção mensal'!B6),1),IF(DATE(YEAR('DisruptRadar — Projeção mensal'!B6),MONTH('DisruptRadar — Projeção mensal'!B6),1)="","",DATE(2027,1,1)=DATE(YEAR('DisruptRadar — Projeção mensal'!B6),MONTH('DisruptRadar — Projeção mensal'!B6),1)))),0,IF('Model inputs'!B64="","",'Model inputs'!B64)))+'DisruptRadar — Projeção men (2)'!B10 -> -431 | C13: =IF(IF(IF(IF(ISERROR(DATE(2027,2,1)=DATE(YEAR('DisruptRadar — Projeção mensal'!B6),MONTH('DisruptRadar — Projeção mensal'!B6),1)),DATE(2027,2,1)=DATE(YEAR('DisruptRadar — Projeção mensal'!B6),MONTH('DisruptRadar — Projeção mensal'!B6),1),IF(DATE(YEAR('DisruptRadar — Projeção mensal'!B6),MONTH('DisruptRadar — Projeção mensal'!B6),1)="","",DATE(2027,2,1)=DATE(YEAR('DisruptRadar — Projeção mensal'!B6),MONTH('DisruptRadar — Projeção mensal'!B6),1)))="",FALSE,IF(ISERROR(DATE(2027,2,1)=DATE(YEAR('DisruptRadar — Projeção mensal'!B6),MONTH('DisruptRadar — Projeção mensal'!B6),1)),DATE(2027,2,1)=DATE(YEAR('DisruptRadar — Projeção mensal'!B6),MONTH('DisruptRadar — Projeção mensal'!B6),1),IF(DATE(YEAR('DisruptRadar — Projeção mensal'!B6),MONTH('DisruptRadar — Projeção mensal'!B6),1)="","",DATE(2027,2,1)=DATE(YEAR('DisruptRadar — Projeção mensal'!B6),MONTH('DisruptRadar — Projeção mensal'!B6),1)))),0,IF('DisruptRadar — Projeção men (2)'!B13="","",'DisruptRadar — Projeção men (2)'!B13))="",0,IF(IF(IF(ISERROR(DATE(2027,2,1)=DATE(YEAR('DisruptRadar — Projeção mensal'!B6),MONTH('DisruptRadar — Projeção mensal'!B6),1)),DATE(2027,2,1)=DATE(YEAR('DisruptRadar — Projeção mensal'!B6),MONTH('DisruptRadar — Projeção mensal'!B6),1),IF(DATE(YEAR('DisruptRadar — Projeção mensal'!B6),MONTH('DisruptRadar — Projeção mensal'!B6),1)="","",DATE(2027,2,1)=DATE(YEAR('DisruptRadar — Projeção mensal'!B6),MONTH('DisruptRadar — Projeção mensal'!B6),1)))="",FALSE,IF(ISERROR(DATE(2027,2,1)=DATE(YEAR('DisruptRadar — Projeção mensal'!B6),MONTH('DisruptRadar — Projeção mensal'!B6),1)),DATE(2027,2,1)=DATE(YEAR('DisruptRadar — Projeção mensal'!B6),MONTH('DisruptRadar — Projeção mensal'!B6),1),IF(DATE(YEAR('DisruptRadar — Projeção mensal'!B6),MONTH('DisruptRadar — Projeção mensal'!B6),1)="","",DATE(2027,2,1)=DATE(YEAR('DisruptRadar — Projeção mensal'!B6),MONTH('DisruptRadar — Projeção mensal'!B6),1)))),0,IF('DisruptRadar — Projeção men (2)'!B13="","",'DisruptRadar — Projeção men (2)'!B13)))+'DisruptRadar — Projeção men (2)'!C10 -> -655 | D13: =IF(IF(IF(IF(ISERROR(DATE(2027,3,1)=DATE(YEAR('DisruptRadar — Projeção mensal'!B6),MONTH('DisruptRadar — Projeção mensal'!B6),1)),DATE(2027,3,1)=DATE(YEAR('DisruptRadar — Projeção mensal'!B6),MONTH('DisruptRadar — Projeção mensal'!B6),1),IF(DATE(YEAR('DisruptRadar — Projeção mensal'!B6),MONTH('DisruptRadar — Projeção mensal'!B6),1)="","",DATE(2027,3,1)=DATE(YEAR('DisruptRadar — Projeção mensal'!B6),MONTH('DisruptRadar — Projeção mensal'!B6),1)))="",FALSE,IF(ISERROR(DATE(2027,3,1)=DATE(YEAR('DisruptRadar — Projeção mensal'!B6),MONTH('DisruptRadar — Projeção mensal'!B6),1)),DATE(2027,3,1)=DATE(YEAR('DisruptRadar — Projeção mensal'!B6),MONTH('DisruptRadar — Projeção mensal'!B6),1),IF(DATE(YEAR('DisruptRadar — Projeção mensal'!B6),MONTH('DisruptRadar — Projeção mensal'!B6),1)="","",DATE(2027,3,1)=DATE(YEAR('DisruptRadar — Projeção mensal'!B6),MONTH('DisruptRadar — Projeção mensal'!B6),1)))),0,IF('DisruptRadar — Projeção men (2)'!C13="","",'DisruptRadar — Projeção men (2)'!C13))="",0,IF(IF(IF(ISERROR(DATE(2027,3,1)=DATE(YEAR('DisruptRadar — Projeção mensal'!B6),MONTH('DisruptRadar — Projeção mensal'!B6),1)),DATE(2027,3,1)=DATE(YEAR('DisruptRadar — Projeção mensal'!B6),MONTH('DisruptRadar — Projeção mensal'!B6),1),IF(DATE(YEAR('DisruptRadar — Projeção mensal'!B6),MONTH('DisruptRadar — Projeção mensal'!B6),1)="","",DATE(2027,3,1)=DATE(YEAR('DisruptRadar — Projeção mensal'!B6),MONTH('DisruptRadar — Projeção mensal'!B6),1)))="",FALSE,IF(ISERROR(DATE(2027,3,1)=DATE(YEAR('DisruptRadar — Projeção mensal'!B6),MONTH('DisruptRadar — Projeção mensal'!B6),1)),DATE(2027,3,1)=DATE(YEAR('DisruptRadar — Projeção mensal'!B6),MONTH('DisruptRadar — Projeção mensal'!B6),1),IF(DATE(YEAR('DisruptRadar — Projeção mensal'!B6),MONTH('DisruptRadar — Projeção mensal'!B6),1)="","",DATE(2027,3,1)=DATE(YEAR('DisruptRadar — Projeção mensal'!B6),MONTH('DisruptRadar — Projeção mensal'!B6),1)))),0,IF('DisruptRadar — Projeção men (2)'!C13="","",'DisruptRadar — Projeção men (2)'!C13)))+'DisruptRadar — Projeção men (2)'!D10 -> -534 | E13: =IF(IF(IF(IF(ISERROR(DATE(2027,4,1)=DATE(YEAR('DisruptRadar — Projeção mensal'!B6),MONTH('DisruptRadar — Projeção mensal'!B6),1)),DATE(2027,4,1)=DATE(YEAR('DisruptRadar — Projeção mensal'!B6),MONTH('DisruptRadar — Projeção mensal'!B6),1),IF(DATE(YEAR('DisruptRadar — Projeção mensal'!B6),MONTH('DisruptRadar — Projeção mensal'!B6),1)="","",DATE(2027,4,1)=DATE(YEAR('DisruptRadar — Projeção mensal'!B6),MONTH('DisruptRadar — Projeção mensal'!B6),1)))="",FALSE,IF(ISERROR(DATE(2027,4,1)=DATE(YEAR('DisruptRadar — Projeção mensal'!B6),MONTH('DisruptRadar — Projeção mensal'!B6),1)),DATE(2027,4,1)=DATE(YEAR('DisruptRadar — Projeção mensal'!B6),MONTH('DisruptRadar — Projeção mensal'!B6),1),IF(DATE(YEAR('DisruptRadar — Projeção mensal'!B6),MONTH('DisruptRadar — Projeção mensal'!B6),1)="","",DATE(2027,4,1)=DATE(YEAR('DisruptRadar — Projeção mensal'!B6),MONTH('DisruptRadar — Projeção mensal'!B6),1)))),0,IF('DisruptRadar — Projeção men (2)'!D13="","",'DisruptRadar — Projeção men (2)'!D13))="",0,IF(IF(IF(ISERROR(DATE(2027,4,1)=DATE(YEAR('DisruptRadar — Projeção mensal'!B6),MONTH('DisruptRadar — Projeção mensal'!B6),1)),DATE(2027,4,1)=DATE(YEAR('DisruptRadar — Projeção mensal'!B6),MONTH('DisruptRadar — Projeção mensal'!B6),1),IF(DATE(YEAR('DisruptRadar — Projeção mensal'!B6),MONTH('DisruptRadar — Projeção mensal'!B6),1)="","",DATE(2027,4,1)=DATE(YEAR('DisruptRadar — Projeção mensal'!B6),MONTH('DisruptRadar — Projeção mensal'!B6),1)))="",FALSE,IF(ISERROR(DATE(2027,4,1)=DATE(YEAR('DisruptRadar — Projeção mensal'!B6),MONTH('DisruptRadar — Projeção mensal'!B6),1)),DATE(2027,4,1)=DATE(YEAR('DisruptRadar — Projeção mensal'!B6),MONTH('DisruptRadar — Projeção mensal'!B6),1),IF(DATE(YEAR('DisruptRadar — Projeção mensal'!B6),MONTH('DisruptRadar — Projeção mensal'!B6),1)="","",DATE(2027,4,1)=DATE(YEAR('DisruptRadar — Projeção mensal'!B6),MONTH('DisruptRadar — Projeção mensal'!B6),1)))),0,IF('DisruptRadar — Projeção men (2)'!D13="","",'DisruptRadar — Projeção men (2)'!D13)))+'DisruptRadar — Projeção men (2)'!E10 -> -68 | F13: =IF(IF(IF(IF(ISERROR(DATE(2027,5,1)=DATE(YEAR('DisruptRadar — Projeção mensal'!B6),MONTH('DisruptRadar — Projeção mensal'!B6),1)),DATE(2027,5,1)=DATE(YEAR('DisruptRadar — Projeção mensal'!B6),MONTH('DisruptRadar — Projeção mensal'!B6),1),IF(DATE(YEAR('DisruptRadar — Projeção mensal'!B6),MONTH('DisruptRadar — Projeção mensal'!B6),1)="","",DATE(2027,5,1)=DATE(YEAR('DisruptRadar — Projeção mensal'!B6),MONTH('DisruptRadar — Projeção mensal'!B6),1)))="",FALSE,IF(ISERROR(DATE(2027,5,1)=DATE(YEAR('DisruptRadar — Projeção mensal'!B6),MONTH('DisruptRadar — Projeção mensal'!B6),1)),DATE(2027,5,1)=DATE(YEAR('DisruptRadar — Projeção mensal'!B6),MONTH('DisruptRadar — Projeção mensal'!B6),1),IF(DATE(YEAR('DisruptRadar — Projeção mensal'!B6),MONTH('DisruptRadar — Projeção mensal'!B6),1)="","",DATE(2027,5,1)=DATE(YEAR('DisruptRadar — Projeção mensal'!B6),MONTH('DisruptRadar — Projeção mensal'!B6),1)))),0,IF('DisruptRadar — Projeção men (2)'!E13="","",'DisruptRadar — Projeção men (2)'!E13))="",0,IF(IF(IF(ISERROR(DATE(2027,5,1)=DATE(YEAR('DisruptRadar — Projeção mensal'!B6),MONTH('DisruptRadar — Projeção mensal'!B6),1)),DATE(2027,5,1)=DATE(YEAR('DisruptRadar — Projeção mensal'!B6),MONTH('DisruptRadar — Projeção mensal'!B6),1),IF(DATE(YEAR('DisruptRadar — Projeção mensal'!B6),MONTH('DisruptRadar — Projeção mensal'!B6),1)="","",DATE(2027,5,1)=DATE(YEAR('DisruptRadar — Projeção mensal'!B6),MONTH('DisruptRadar — Projeção mensal'!B6),1)))="",FALSE,IF(ISERROR(DATE(2027,5,1)=DATE(YEAR('DisruptRadar — Projeção mensal'!B6),MONTH('DisruptRadar — Projeção mensal'!B6),1)),DATE(2027,5,1)=DATE(YEAR('DisruptRadar — Projeção mensal'!B6),MONTH('DisruptRadar — Projeção mensal'!B6),1),IF(DATE(YEAR('DisruptRadar — Projeção mensal'!B6),MONTH('DisruptRadar — Projeção mensal'!B6),1)="","",DATE(2027,5,1)=DATE(YEAR('DisruptRadar — Projeção mensal'!B6),MONTH('DisruptRadar — Projeção mensal'!B6),1)))),0,IF('DisruptRadar — Projeção men (2)'!E13="","",'DisruptRadar — Projeção men (2)'!E13)))+'DisruptRadar — Projeção men (2)'!F10 -> 812 | G13: =IF(IF(IF(IF(ISERROR(DATE(2027,6,1)=DATE(YEAR('DisruptRadar — Projeção mensal'!B6),MONTH('DisruptRadar — Projeção mensal'!B6),1)),DATE(2027,6,1)=DATE(YEAR('DisruptRadar — Projeção mensal'!B6),MONTH('DisruptRadar — Projeção mensal'!B6),1),IF(DATE(YEAR('DisruptRadar — Projeção mensal'!B6),MONTH('DisruptRadar — Projeção mensal'!B6),1)="","",DATE(2027,6,1)=DATE(YEAR('DisruptRadar — Projeção mensal'!B6),MONTH('DisruptRadar — Projeção mensal'!B6),1)))="",FALSE,IF(ISERROR(DATE(2027,6,1)=DATE(YEAR('DisruptRadar — Projeção mensal'!B6),MONTH('DisruptRadar — Projeção mensal'!B6),1)),DATE(2027,6,1)=DATE(YEAR('DisruptRadar — Projeção mensal'!B6),MONTH('DisruptRadar — Projeção mensal'!B6),1),IF(DATE(YEAR('DisruptRadar — Projeção mensal'!B6),MONTH('DisruptRadar — Projeção mensal'!B6),1)="","",DATE(2027,6,1)=DATE(YEAR('DisruptRadar — Projeção mensal'!B6),MONTH('DisruptRadar — Projeção mensal'!B6),1)))),0,IF('DisruptRadar — Projeção men (2)'!F13="","",'DisruptRadar — Projeção men (2)'!F13))="",0,IF(IF(IF(ISERROR(DATE(2027,6,1)=DATE(YEAR('DisruptRadar — Projeção mensal'!B6),MONTH('DisruptRadar — Projeção mensal'!B6),1)),DATE(2027,6,1)=DATE(YEAR('DisruptRadar — Projeção mensal'!B6),MONTH('DisruptRadar — Projeção mensal'!B6),1),IF(DATE(YEAR('DisruptRadar — Projeção mensal'!B6),MONTH('DisruptRadar — Projeção mensal'!B6),1)="","",DATE(2027,6,1)=DATE(YEAR('DisruptRadar — Projeção mensal'!B6),MONTH('DisruptRadar — Projeção mensal'!B6),1)))="",FALSE,IF(ISERROR(DATE(2027,6,1)=DATE(YEAR('DisruptRadar — Projeção mensal'!B6),MONTH('DisruptRadar — Projeção mensal'!B6),1)),DATE(2027,6,1)=DATE(YEAR('DisruptRadar — Projeção mensal'!B6),MONTH('DisruptRadar — Projeção mensal'!B6),1),IF(DATE(YEAR('DisruptRadar — Projeção mensal'!B6),MONTH('DisruptRadar — Projeção mensal'!B6),1)="","",DATE(2027,6,1)=DATE(YEAR('DisruptRadar — Projeção mensal'!B6),MONTH('DisruptRadar — Projeção mensal'!B6),1)))),0,IF('DisruptRadar — Projeção men (2)'!F13="","",'DisruptRadar — Projeção men (2)'!F13)))+'DisruptRadar — Projeção men (2)'!G10 -> 2106 | H13: =IF(IF(IF(IF(ISERROR(DATE(2027,7,1)=DATE(YEAR('DisruptRadar — Projeção mensal'!B6),MONTH('DisruptRadar — Projeção mensal'!B6),1)),DATE(2027,7,1)=DATE(YEAR('DisruptRadar — Projeção mensal'!B6),MONTH('DisruptRadar — Projeção mensal'!B6),1),IF(DATE(YEAR('DisruptRadar — Projeção mensal'!B6),MONTH('DisruptRadar — Projeção mensal'!B6),1)="","",DATE(2027,7,1)=DATE(YEAR('DisruptRadar — Projeção mensal'!B6),MONTH('DisruptRadar — Projeção mensal'!B6),1)))="",FALSE,IF(ISERROR(DATE(2027,7,1)=DATE(YEAR('DisruptRadar — Projeção mensal'!B6),MONTH('DisruptRadar — Projeção mensal'!B6),1)),DATE(2027,7,1)=DATE(YEAR('DisruptRadar — Projeção mensal'!B6),MONTH('DisruptRadar — Projeção mensal'!B6),1),IF(DATE(YEAR('DisruptRadar — Projeção mensal'!B6),MONTH('DisruptRadar — Projeção mensal'!B6),1)="","",DATE(2027,7,1)=DATE(YEAR('DisruptRadar — Projeção mensal'!B6),MONTH('DisruptRadar — Projeção mensal'!B6),1)))),0,IF('DisruptRadar — Projeção men (2)'!G13="","",'DisruptRadar — Projeção men (2)'!G13))="",0,IF(IF(IF(ISERROR(DATE(2027,7,1)=DATE(YEAR('DisruptRadar — Projeção mensal'!B6),MONTH('DisruptRadar — Projeção mensal'!B6),1)),DATE(2027,7,1)=DATE(YEAR('DisruptRadar — Projeção mensal'!B6),MONTH('DisruptRadar — Projeção mensal'!B6),1),IF(DATE(YEAR('DisruptRadar — Projeção mensal'!B6),MONTH('DisruptRadar — Projeção mensal'!B6),1)="","",DATE(2027,7,1)=DATE(YEAR('DisruptRadar — Projeção mensal'!B6),MONTH('DisruptRadar — Projeção mensal'!B6),1)))="",FALSE,IF(ISERROR(DATE(2027,7,1)=DATE(YEAR('DisruptRadar — Projeção mensal'!B6),MONTH('DisruptRadar — Projeção mensal'!B6),1)),DATE(2027,7,1)=DATE(YEAR('DisruptRadar — Projeção mensal'!B6),MONTH('DisruptRadar — Projeção mensal'!B6),1),IF(DATE(YEAR('DisruptRadar — Projeção mensal'!B6),MONTH('DisruptRadar — Projeção mensal'!B6),1)="","",DATE(2027,7,1)=DATE(YEAR('DisruptRadar — Projeção mensal'!B6),MONTH('DisruptRadar — Projeção mensal'!B6),1)))),0,IF('DisruptRadar — Projeção men (2)'!G13="","",'DisruptRadar — Projeção men (2)'!G13)))+'DisruptRadar — Projeção men (2)'!H10 -> 3814 | I13: =IF(IF(IF(IF(ISERROR(DATE(2027,8,1)=DATE(YEAR('DisruptRadar — Projeção mensal'!B6),MONTH('DisruptRadar — Projeção mensal'!B6),1)),DATE(2027,8,1)=DATE(YEAR('DisruptRadar — Projeção mensal'!B6),MONTH('DisruptRadar — Projeção mensal'!B6),1),IF(DATE(YEAR('DisruptRadar — Projeção mensal'!B6),MONTH('DisruptRadar — Projeção mensal'!B6),1)="","",DATE(2027,8,1)=DATE(YEAR('DisruptRadar — Projeção mensal'!B6),MONTH('DisruptRadar — Projeção mensal'!B6),1)))="",FALSE,IF(ISERROR(DATE(2027,8,1)=DATE(YEAR('DisruptRadar — Projeção mensal'!B6),MONTH('DisruptRadar — Projeção mensal'!B6),1)),DATE(2027,8,1)=DATE(YEAR('DisruptRadar — Projeção mensal'!B6),MONTH('DisruptRadar — Projeção mensal'!B6),1),IF(DATE(YEAR('DisruptRadar — Projeção mensal'!B6),MONTH('DisruptRadar — Projeção mensal'!B6),1)="","",DATE(2027,8,1)=DATE(YEAR('DisruptRadar — Projeção mensal'!B6),MONTH('DisruptRadar — Projeção mensal'!B6),1)))),0,IF('DisruptRadar — Projeção men (2)'!H13="","",'DisruptRadar — Projeção men (2)'!H13))="",0,IF(IF(IF(ISERROR(DATE(2027,8,1)=DATE(YEAR('DisruptRadar — Projeção mensal'!B6),MONTH('DisruptRadar — Projeção mensal'!B6),1)),DATE(2027,8,1)=DATE(YEAR('DisruptRadar — Projeção mensal'!B6),MONTH('DisruptRadar — Projeção mensal'!B6),1),IF(DATE(YEAR('DisruptRadar — Projeção mensal'!B6),MONTH('DisruptRadar — Projeção mensal'!B6),1)="","",DATE(2027,8,1)=DATE(YEAR('DisruptRadar — Projeção mensal'!B6),MONTH('DisruptRadar — Projeção mensal'!B6),1)))="",FALSE,IF(ISERROR(DATE(2027,8,1)=DATE(YEAR('DisruptRadar — Projeção mensal'!B6),MONTH('DisruptRadar — Projeção mensal'!B6),1)),DATE(2027,8,1)=DATE(YEAR('DisruptRadar — Projeção mensal'!B6),MONTH('DisruptRadar — Projeção mensal'!B6),1),IF(DATE(YEAR('DisruptRadar — Projeção mensal'!B6),MONTH('DisruptRadar — Projeção mensal'!B6),1)="","",DATE(2027,8,1)=DATE(YEAR('DisruptRadar — Projeção mensal'!B6),MONTH('DisruptRadar — Projeção mensal'!B6),1)))),0,IF('DisruptRadar — Projeção men (2)'!H13="","",'DisruptRadar — Projeção men (2)'!H13)))+'DisruptRadar — Projeção men (2)'!I10 -> 5936 | J13: =IF(IF(IF(IF(ISERROR(DATE(2027,9,1)=DATE(YEAR('DisruptRadar — Projeção mensal'!B6),MONTH('DisruptRadar — Projeção mensal'!B6),1)),DATE(2027,9,1)=DATE(YEAR('DisruptRadar — Projeção mensal'!B6),MONTH('DisruptRadar — Projeção mensal'!B6),1),IF(DATE(YEAR('DisruptRadar — Projeção mensal'!B6),MONTH('DisruptRadar — Projeção mensal'!B6),1)="","",DATE(2027,9,1)=DATE(YEAR('DisruptRadar — Projeção mensal'!B6),MONTH('DisruptRadar — Projeção mensal'!B6),1)))="",FALSE,IF(ISERROR(DATE(2027,9,1)=DATE(YEAR('DisruptRadar — Projeção mensal'!B6),MONTH('DisruptRadar — Projeção mensal'!B6),1)),DATE(2027,9,1)=DATE(YEAR('DisruptRadar — Projeção mensal'!B6),MONTH('DisruptRadar — Projeção mensal'!B6),1),IF(DATE(YEAR('DisruptRadar — Projeção mensal'!B6),MONTH('DisruptRadar — Projeção mensal'!B6),1)="","",DATE(2027,9,1)=DATE(YEAR('DisruptRadar — Projeção mensal'!B6),MONTH('DisruptRadar — Projeção mensal'!B6),1)))),0,IF('DisruptRadar — Projeção men (2)'!I13="","",'DisruptRadar — Projeção men (2)'!I13))="",0,IF(IF(IF(ISERROR(DATE(2027,9,1)=DATE(YEAR('DisruptRadar — Projeção mensal'!B6),MONTH('DisruptRadar — Projeção mensal'!B6),1)),DATE(2027,9,1)=DATE(YEAR('DisruptRadar — Projeção mensal'!B6),MONTH('DisruptRadar — Projeção mensal'!B6),1),IF(DATE(YEAR('DisruptRadar — Projeção mensal'!B6),MONTH('DisruptRadar — Projeção mensal'!B6),1)="","",DATE(2027,9,1)=DATE(YEAR('DisruptRadar — Projeção mensal'!B6),MONTH('DisruptRadar — Projeção mensal'!B6),1)))="",FALSE,IF(ISERROR(DATE(2027,9,1)=DATE(YEAR('DisruptRadar — Projeção mensal'!B6),MONTH('DisruptRadar — Projeção mensal'!B6),1)),DATE(2027,9,1)=DATE(YEAR('DisruptRadar — Projeção mensal'!B6),MONTH('DisruptRadar — Projeção mensal'!B6),1),IF(DATE(YEAR('DisruptRadar — Projeção mensal'!B6),MONTH('DisruptRadar — Projeção mensal'!B6),1)="","",DATE(2027,9,1)=DATE(YEAR('DisruptRadar — Projeção mensal'!B6),MONTH('DisruptRadar — Projeção mensal'!B6),1)))),0,IF('DisruptRadar — Projeção men (2)'!I13="","",'DisruptRadar — Projeção men (2)'!I13)))+'DisruptRadar — Projeção men (2)'!J10 -> 8196 | K13: =IF(IF(IF(IF(ISERROR(DATE(2027,10,1)=DATE(YEAR('DisruptRadar — Projeção mensal'!B6),MONTH('DisruptRadar — Projeção mensal'!B6),1)),DATE(2027,10,1)=DATE(YEAR('DisruptRadar — Projeção mensal'!B6),MONTH('DisruptRadar — Projeção mensal'!B6),1),IF(DATE(YEAR('DisruptRadar — Projeção mensal'!B6),MONTH('DisruptRadar — Projeção mensal'!B6),1)="","",DATE(2027,10,1)=DATE(YEAR('DisruptRadar — Projeção mensal'!B6),MONTH('DisruptRadar — Projeção mensal'!B6),1)))="",FALSE,IF(ISERROR(DATE(2027,10,1)=DATE(YEAR('DisruptRadar — Projeção mensal'!B6),MONTH('DisruptRadar — Projeção mensal'!B6),1)),DATE(2027,10,1)=DATE(YEAR('DisruptRadar — Projeção mensal'!B6),MONTH('DisruptRadar — Projeção mensal'!B6),1),IF(DATE(YEAR('DisruptRadar — Projeção mensal'!B6),MONTH('DisruptRadar — Projeção mensal'!B6),1)="","",DATE(2027,10,1)=DATE(YEAR('DisruptRadar — Projeção mensal'!B6),MONTH('DisruptRadar — Projeção mensal'!B6),1)))),0,IF('DisruptRadar — Projeção men (2)'!J13="","",'DisruptRadar — Projeção men (2)'!J13))="",0,IF(IF(IF(ISERROR(DATE(2027,10,1)=DATE(YEAR('DisruptRadar — Projeção mensal'!B6),MONTH('DisruptRadar — Projeção mensal'!B6),1)),DATE(2027,10,1)=DATE(YEAR('DisruptRadar — Projeção mensal'!B6),MONTH('DisruptRadar — Projeção mensal'!B6),1),IF(DATE(YEAR('DisruptRadar — Projeção mensal'!B6),MONTH('DisruptRadar — Projeção mensal'!B6),1)="","",DATE(2027,10,1)=DATE(YEAR('DisruptRadar — Projeção mensal'!B6),MONTH('DisruptRadar — Projeção mensal'!B6),1)))="",FALSE,IF(ISERROR(DATE(2027,10,1)=DATE(YEAR('DisruptRadar — Projeção mensal'!B6),MONTH('DisruptRadar — Projeção mensal'!B6),1)),DATE(2027,10,1)=DATE(YEAR('DisruptRadar — Projeção mensal'!B6),MONTH('DisruptRadar — Projeção mensal'!B6),1),IF(DATE(YEAR('DisruptRadar — Projeção mensal'!B6),MONTH('DisruptRadar — Projeção mensal'!B6),1)="","",DATE(2027,10,1)=DATE(YEAR('DisruptRadar — Projeção mensal'!B6),MONTH('DisruptRadar — Projeção mensal'!B6),1)))),0,IF('DisruptRadar — Projeção men (2)'!J13="","",'DisruptRadar — Projeção men (2)'!J13)))+'DisruptRadar — Projeção men (2)'!K10 -> 10456 | L13: =IF(IF(IF(IF(ISERROR(DATE(2027,11,1)=DATE(YEAR('DisruptRadar — Projeção mensal'!B6),MONTH('DisruptRadar — Projeção mensal'!B6),1)),DATE(2027,11,1)=DATE(YEAR('DisruptRadar — Projeção mensal'!B6),MONTH('DisruptRadar — Projeção mensal'!B6),1),IF(DATE(YEAR('DisruptRadar — Projeção mensal'!B6),MONTH('DisruptRadar — Projeção mensal'!B6),1)="","",DATE(2027,11,1)=DATE(YEAR('DisruptRadar — Projeção mensal'!B6),MONTH('DisruptRadar — Projeção mensal'!B6),1)))="",FALSE,IF(ISERROR(DATE(2027,11,1)=DATE(YEAR('DisruptRadar — Projeção mensal'!B6),MONTH('DisruptRadar — Projeção mensal'!B6),1)),DATE(2027,11,1)=DATE(YEAR('DisruptRadar — Projeção mensal'!B6),MONTH('DisruptRadar — Projeção mensal'!B6),1),IF(DATE(YEAR('DisruptRadar — Projeção mensal'!B6),MONTH('DisruptRadar — Projeção mensal'!B6),1)="","",DATE(2027,11,1)=DATE(YEAR('DisruptRadar — Projeção mensal'!B6),MONTH('DisruptRadar — Projeção mensal'!B6),1)))),0,IF('DisruptRadar — Projeção men (2)'!K13="","",'DisruptRadar — Projeção men (2)'!K13))="",0,IF(IF(IF(ISERROR(DATE(2027,11,1)=DATE(YEAR('DisruptRadar — Projeção mensal'!B6),MONTH('DisruptRadar — Projeção mensal'!B6),1)),DATE(2027,11,1)=DATE(YEAR('DisruptRadar — Projeção mensal'!B6),MONTH('DisruptRadar — Projeção mensal'!B6),1),IF(DATE(YEAR('DisruptRadar — Projeção mensal'!B6),MONTH('DisruptRadar — Projeção mensal'!B6),1)="","",DATE(2027,11,1)=DATE(YEAR('DisruptRadar — Projeção mensal'!B6),MONTH('DisruptRadar — Projeção mensal'!B6),1)))="",FALSE,IF(ISERROR(DATE(2027,11,1)=DATE(YEAR('DisruptRadar — Projeção mensal'!B6),MONTH('DisruptRadar — Projeção mensal'!B6),1)),DATE(2027,11,1)=DATE(YEAR('DisruptRadar — Projeção mensal'!B6),MONTH('DisruptRadar — Projeção mensal'!B6),1),IF(DATE(YEAR('DisruptRadar — Projeção mensal'!B6),MONTH('DisruptRadar — Projeção mensal'!B6),1)="","",DATE(2027,11,1)=DATE(YEAR('DisruptRadar — Projeção mensal'!B6),MONTH('DisruptRadar — Projeção mensal'!B6),1)))),0,IF('DisruptRadar — Projeção men (2)'!K13="","",'DisruptRadar — Projeção men (2)'!K13)))+'DisruptRadar — Projeção men (2)'!L10 -> 12716 | M13: =IF(IF(IF(IF(ISERROR(DATE(2027,12,1)=DATE(YEAR('DisruptRadar — Projeção mensal'!B6),MONTH('DisruptRadar — Projeção mensal'!B6),1)),DATE(2027,12,1)=DATE(YEAR('DisruptRadar — Projeção mensal'!B6),MONTH('DisruptRadar — Projeção mensal'!B6),1),IF(DATE(YEAR('DisruptRadar — Projeção mensal'!B6),MONTH('DisruptRadar — Projeção mensal'!B6),1)="","",DATE(2027,12,1)=DATE(YEAR('DisruptRadar — Projeção mensal'!B6),MONTH('DisruptRadar — Projeção mensal'!B6),1)))="",FALSE,IF(ISERROR(DATE(2027,12,1)=DATE(YEAR('DisruptRadar — Projeção mensal'!B6),MONTH('DisruptRadar — Projeção mensal'!B6),1)),DATE(2027,12,1)=DATE(YEAR('DisruptRadar — Projeção mensal'!B6),MONTH('DisruptRadar — Projeção mensal'!B6),1),IF(DATE(YEAR('DisruptRadar — Projeção mensal'!B6),MONTH('DisruptRadar — Projeção mensal'!B6),1)="","",DATE(2027,12,1)=DATE(YEAR('DisruptRadar — Projeção mensal'!B6),MONTH('DisruptRadar — Projeção mensal'!B6),1)))),0,IF('DisruptRadar — Projeção men (2)'!L13="","",'DisruptRadar — Projeção men (2)'!L13))="",0,IF(IF(IF(ISERROR(DATE(2027,12,1)=DATE(YEAR('DisruptRadar — Projeção mensal'!B6),MONTH('DisruptRadar — Projeção mensal'!B6),1)),DATE(2027,12,1)=DATE(YEAR('DisruptRadar — Projeção mensal'!B6),MONTH('DisruptRadar — Projeção mensal'!B6),1),IF(DATE(YEAR('DisruptRadar — Projeção mensal'!B6),MONTH('DisruptRadar — Projeção mensal'!B6),1)="","",DATE(2027,12,1)=DATE(YEAR('DisruptRadar — Projeção mensal'!B6),MONTH('DisruptRadar — Projeção mensal'!B6),1)))="",FALSE,IF(ISERROR(DATE(2027,12,1)=DATE(YEAR('DisruptRadar — Projeção mensal'!B6),MONTH('DisruptRadar — Projeção mensal'!B6),1)),DATE(2027,12,1)=DATE(YEAR('DisruptRadar — Projeção mensal'!B6),MONTH('DisruptRadar — Projeção mensal'!B6),1),IF(DATE(YEAR('DisruptRadar — Projeção mensal'!B6),MONTH('DisruptRadar — Projeção mensal'!B6),1)="","",DATE(2027,12,1)=DATE(YEAR('DisruptRadar — Projeção mensal'!B6),MONTH('DisruptRadar — Projeção mensal'!B6),1)))),0,IF('DisruptRadar — Projeção men (2)'!L13="","",'DisruptRadar — Projeção men (2)'!L13)))+'DisruptRadar — Projeção men (2)'!M10 -> 14976
A14: Verificação de caixa — projeção Base (EUR) | B14: ='DisruptRadar — Projeção men (2)'!B12-('DisruptRadar Business Plan · Pr'!B7+'DisruptRadar — Projeção men (2)'!B13) -> 0 | C14: ='DisruptRadar — Projeção men (2)'!C12-('DisruptRadar Business Plan · Pr'!B7+'DisruptRadar — Projeção men (2)'!C13) -> 0 | D14: ='DisruptRadar — Projeção men (2)'!D12-('DisruptRadar Business Plan · Pr'!B7+'DisruptRadar — Projeção men (2)'!D13) -> 0 | E14: ='DisruptRadar — Projeção men (2)'!E12-('DisruptRadar Business Plan · Pr'!B7+'DisruptRadar — Projeção men (2)'!E13) -> 0 | F14: ='DisruptRadar — Projeção men (2)'!F12-('DisruptRadar Business Plan · Pr'!B7+'DisruptRadar — Projeção men (2)'!F13) -> 0 | G14: ='DisruptRadar — Projeção men (2)'!G12-('DisruptRadar Business Plan · Pr'!B7+'DisruptRadar — Projeção men (2)'!G13) -> 0 | H14: ='DisruptRadar — Projeção men (2)'!H12-('DisruptRadar Business Plan · Pr'!B7+'DisruptRadar — Projeção men (2)'!H13) -> 0 | I14: ='DisruptRadar — Projeção men (2)'!I12-('DisruptRadar Business Plan · Pr'!B7+'DisruptRadar — Projeção men (2)'!I13) -> 0 | J14: ='DisruptRadar — Projeção men (2)'!J12-('DisruptRadar Business Plan · Pr'!B7+'DisruptRadar — Projeção men (2)'!J13) -> 0 | K14: ='DisruptRadar — Projeção men (2)'!K12-('DisruptRadar Business Plan · Pr'!B7+'DisruptRadar — Projeção men (2)'!K13) -> 0 | L14: ='DisruptRadar — Projeção men (2)'!L12-('DisruptRadar Business Plan · Pr'!B7+'DisruptRadar — Projeção men (2)'!L13) -> 0 | M14: ='DisruptRadar — Projeção men (2)'!M12-('DisruptRadar Business Plan · Pr'!B7+'DisruptRadar — Projeção men (2)'!M13) -> 0

Sheet DisruptRadar — Projeção men (3)
A1: DisruptRadar — Projeção mensal · Reconciliação anual Base com a matriz
A2: Financial model (2 pages) · Base
A4: Variable / dimension | B4: Value
A5: Clientes-mês — projeção Base | B5: =SUM('DisruptRadar — Projeção men (2)'!B5,'DisruptRadar — Projeção men (2)'!C5,'DisruptRadar — Projeção men (2)'!D5,'DisruptRadar — Projeção men (2)'!E5,'DisruptRadar — Projeção men (2)'!F5,'DisruptRadar — Projeção men (2)'!G5,'DisruptRadar — Projeção men (2)'!H5,'DisruptRadar — Projeção men (2)'!I5,'DisruptRadar — Projeção men (2)'!J5,'DisruptRadar — Projeção men (2)'!K5,'DisruptRadar — Projeção men (2)'!L5,'DisruptRadar — Projeção men (2)'!M5) -> 304
A6: Receita anual — projeção Base (EUR) | B6: =SUM('DisruptRadar — Projeção men (2)'!B6,'DisruptRadar — Projeção men (2)'!C6,'DisruptRadar — Projeção men (2)'!D6,'DisruptRadar — Projeção men (2)'!E6,'DisruptRadar — Projeção men (2)'!F6,'DisruptRadar — Projeção men (2)'!G6,'DisruptRadar — Projeção men (2)'!H6,'DisruptRadar — Projeção men (2)'!I6,'DisruptRadar — Projeção men (2)'!J6,'DisruptRadar — Projeção men (2)'!K6,'DisruptRadar — Projeção men (2)'!L6,'DisruptRadar — Projeção men (2)'!M6) -> 30096
A7: Entrega anual — projeção Base (EUR) | B7: =SUM('DisruptRadar — Projeção men (2)'!B7,'DisruptRadar — Projeção men (2)'!C7,'DisruptRadar — Projeção men (2)'!D7,'DisruptRadar — Projeção men (2)'!E7,'DisruptRadar — Projeção men (2)'!F7,'DisruptRadar — Projeção men (2)'!G7,'DisruptRadar — Projeção men (2)'!H7,'DisruptRadar — Projeção men (2)'!I7,'DisruptRadar — Projeção men (2)'!J7,'DisruptRadar — Projeção men (2)'!K7,'DisruptRadar — Projeção men (2)'!L7,'DisruptRadar — Projeção men (2)'!M7) -> 9120
A8: Fixos anuais calculados — projeção Base (EUR) | B8: =SUM('DisruptRadar — Projeção men (2)'!B8,'DisruptRadar — Projeção men (2)'!C8,'DisruptRadar — Projeção men (2)'!D8,'DisruptRadar — Projeção men (2)'!E8,'DisruptRadar — Projeção men (2)'!F8,'DisruptRadar — Projeção men (2)'!G8,'DisruptRadar — Projeção men (2)'!H8,'DisruptRadar — Projeção men (2)'!I8,'DisruptRadar — Projeção men (2)'!J8,'DisruptRadar — Projeção men (2)'!K8,'DisruptRadar — Projeção men (2)'!L8,'DisruptRadar — Projeção men (2)'!M8) -> 6000
A9: Custos anuais — projeção Base (EUR) | B9: =SUM('DisruptRadar — Projeção men (2)'!B9,'DisruptRadar — Projeção men (2)'!C9,'DisruptRadar — Projeção men (2)'!D9,'DisruptRadar — Projeção men (2)'!E9,'DisruptRadar — Projeção men (2)'!F9,'DisruptRadar — Projeção men (2)'!G9,'DisruptRadar — Projeção men (2)'!H9,'DisruptRadar — Projeção men (2)'!I9,'DisruptRadar — Projeção men (2)'!J9,'DisruptRadar — Projeção men (2)'!K9,'DisruptRadar — Projeção men (2)'!L9,'DisruptRadar — Projeção men (2)'!M9) -> 15120
A10: EBITDA anual — projeção Base (EUR) | B10: =SUM('DisruptRadar — Projeção men (2)'!B10,'DisruptRadar — Projeção men (2)'!C10,'DisruptRadar — Projeção men (2)'!D10,'DisruptRadar — Projeção men (2)'!E10,'DisruptRadar — Projeção men (2)'!F10,'DisruptRadar — Projeção men (2)'!G10,'DisruptRadar — Projeção men (2)'!H10,'DisruptRadar — Projeção men (2)'!I10,'DisruptRadar — Projeção men (2)'!J10,'DisruptRadar — Projeção men (2)'!K10,'DisruptRadar — Projeção men (2)'!L10,'DisruptRadar — Projeção men (2)'!M10) -> 14976
A11: Caixa mínima — projeção Base (EUR) | B11: =MIN('DisruptRadar — Projeção men (2)'!B12,'DisruptRadar — Projeção men (2)'!C12,'DisruptRadar — Projeção men (2)'!D12,'DisruptRadar — Projeção men (2)'!E12,'DisruptRadar — Projeção men (2)'!F12,'DisruptRadar — Projeção men (2)'!G12,'DisruptRadar — Projeção men (2)'!H12,'DisruptRadar — Projeção men (2)'!I12,'DisruptRadar — Projeção men (2)'!J12,'DisruptRadar — Projeção men (2)'!K12,'DisruptRadar — Projeção men (2)'!L12,'DisruptRadar — Projeção men (2)'!M12) -> 19345
A12: Caixa ao fim do ano — projeção Base (EUR) | B12: =IF('DisruptRadar — Projeção men (2)'!M12="","",'DisruptRadar — Projeção men (2)'!M12) -> 34976
A13: Diferença de receita vs matriz Base (EUR) | B13: ='DisruptRadar — Projeção men (3)'!B6-'DisruptRadar Business Plan · Ma'!B6 -> 0
A14: Diferença de custos vs matriz Base (EUR) | B14: ='DisruptRadar — Projeção men (3)'!B9-'DisruptRadar Business Plan · Ma'!B7 -> 0
A15: Diferença de EBITDA vs matriz Base (EUR) | B15: ='DisruptRadar — Projeção men (3)'!B10-'DisruptRadar Business Plan · Ma'!B8 -> 0

Sheet DisruptRadar — Projeção men (4)
A1: DisruptRadar — Projeção mensal · Sensibilidade Base — fixos mensais
A2: Financial model (2 pages) · Base
A4: Variable / dimension | B4: Value | C4: Value > Base — fixos 300 €/mês | D4: Value > Base — fixos 400 €/mês | E4: Value > Base — fixos 500 €/mês
A5: Fixos anuais da projeção Base (EUR) | B5: ='DisruptRadar — Projeção mensal'!B5 -> 6000 | C5: =3600 -> 3600 | D5: =4800 -> 4800 | E5: =6000 -> 6000
A6: Custos anuais — projeção Base (EUR) | B6: =SUM('DisruptRadar — Projeção men (2)'!B9,'DisruptRadar — Projeção men (2)'!C9,'DisruptRadar — Projeção men (2)'!D9,'DisruptRadar — Projeção men (2)'!E9,'DisruptRadar — Projeção men (2)'!F9,'DisruptRadar — Projeção men (2)'!G9,'DisruptRadar — Projeção men (2)'!H9,'DisruptRadar — Projeção men (2)'!I9,'DisruptRadar — Projeção men (2)'!J9,'DisruptRadar — Projeção men (2)'!K9,'DisruptRadar — Projeção men (2)'!L9,'DisruptRadar — Projeção men (2)'!M9) -> 15120 | C6: =SUM('Model inputs'!C33,'Model inputs'!D33,'Model inputs'!E33,'Model inputs'!F33,'Model inputs'!G33,'Model inputs'!H33,'Model inputs'!I33,'Model inputs'!J33,'Model inputs'!K33,'Model inputs'!L33,'Model inputs'!M33,'Model inputs'!N33) -> 12720 | D6: =SUM('Model inputs'!C32,'Model inputs'!D32,'Model inputs'!E32,'Model inputs'!F32,'Model inputs'!G32,'Model inputs'!H32,'Model inputs'!I32,'Model inputs'!J32,'Model inputs'!K32,'Model inputs'!L32,'Model inputs'!M32,'Model inputs'!N32) -> 13920 | E6: =SUM('Model inputs'!C34,'Model inputs'!D34,'Model inputs'!E34,'Model inputs'!F34,'Model inputs'!G34,'Model inputs'!H34,'Model inputs'!I34,'Model inputs'!J34,'Model inputs'!K34,'Model inputs'!L34,'Model inputs'!M34,'Model inputs'!N34) -> 15120
A7: EBITDA anual — projeção Base (EUR) | B7: =SUM('DisruptRadar — Projeção men (2)'!B10,'DisruptRadar — Projeção men (2)'!C10,'DisruptRadar — Projeção men (2)'!D10,'DisruptRadar — Projeção men (2)'!E10,'DisruptRadar — Projeção men (2)'!F10,'DisruptRadar — Projeção men (2)'!G10,'DisruptRadar — Projeção men (2)'!H10,'DisruptRadar — Projeção men (2)'!I10,'DisruptRadar — Projeção men (2)'!J10,'DisruptRadar — Projeção men (2)'!K10,'DisruptRadar — Projeção men (2)'!L10,'DisruptRadar — Projeção men (2)'!M10) -> 14976 | C7: =SUM('Model inputs'!C45,'Model inputs'!D45,'Model inputs'!E45,'Model inputs'!F45,'Model inputs'!G45,'Model inputs'!H45,'Model inputs'!I45,'Model inputs'!J45,'Model inputs'!K45,'Model inputs'!L45,'Model inputs'!M45,'Model inputs'!N45) -> 17376 | D7: =SUM('Model inputs'!C43,'Model inputs'!D43,'Model inputs'!E43,'Model inputs'!F43,'Model inputs'!G43,'Model inputs'!H43,'Model inputs'!I43,'Model inputs'!J43,'Model inputs'!K43,'Model inputs'!L43,'Model inputs'!M43,'Model inputs'!N43) -> 16176 | E7: =SUM('Model inputs'!C48,'Model inputs'!D48,'Model inputs'!E48,'Model inputs'!F48,'Model inputs'!G48,'Model inputs'!H48,'Model inputs'!I48,'Model inputs'!J48,'Model inputs'!K48,'Model inputs'!L48,'Model inputs'!M48,'Model inputs'!N48) -> 14976
A8: Caixa mínima — projeção Base (EUR) | B8: =MIN('DisruptRadar — Projeção men (2)'!B12,'DisruptRadar — Projeção men (2)'!C12,'DisruptRadar — Projeção men (2)'!D12,'DisruptRadar — Projeção men (2)'!E12,'DisruptRadar — Projeção men (2)'!F12,'DisruptRadar — Projeção men (2)'!G12,'DisruptRadar — Projeção men (2)'!H12,'DisruptRadar — Projeção men (2)'!I12,'DisruptRadar — Projeção men (2)'!J12,'DisruptRadar — Projeção men (2)'!K12,'DisruptRadar — Projeção men (2)'!L12,'DisruptRadar — Projeção men (2)'!M12) -> 19345 | C8: =MIN('Model inputs'!C9,'Model inputs'!D9,'Model inputs'!E9,'Model inputs'!F9,'Model inputs'!G9,'Model inputs'!H9,'Model inputs'!I9,'Model inputs'!J9,'Model inputs'!K9,'Model inputs'!L9,'Model inputs'!M9,'Model inputs'!N9) -> 19745 | D8: =MIN('Model inputs'!C8,'Model inputs'!D8,'Model inputs'!E8,'Model inputs'!F8,'Model inputs'!G8,'Model inputs'!H8,'Model inputs'!I8,'Model inputs'!J8,'Model inputs'!K8,'Model inputs'!L8,'Model inputs'!M8,'Model inputs'!N8) -> 19545 | E8: =MIN('Model inputs'!C10,'Model inputs'!D10,'Model inputs'!E10,'Model inputs'!F10,'Model inputs'!G10,'Model inputs'!H10,'Model inputs'!I10,'Model inputs'!J10,'Model inputs'!K10,'Model inputs'!L10,'Model inputs'!M10,'Model inputs'!N10) -> 19345
A9: Caixa ao fim do ano — projeção Base (EUR) | B9: =IF('DisruptRadar — Projeção men (2)'!M12="","",'DisruptRadar — Projeção men (2)'!M12) -> 34976 | C9: =IF('Model inputs'!N9="","",'Model inputs'!N9) -> 37376 | D9: =IF('Model inputs'!N8="","",'Model inputs'!N8) -> 36176 | E9: =IF('Model inputs'!N10="","",'Model inputs'!N10) -> 34976

Sheet DisruptRadar — Projeção men (5)
A1: DisruptRadar — Projeção mensal · Sensibilidade completa — preço Pro e fixos
A2: Financial model (2 pages) · Base
A4: Variable / dimension | B4: Value | C4: Value > Base — fixos 300 €/mês | D4: Value > Base — fixos 400 €/mês | E4: Value > Teste Pro 109 € — fixos 300 €/mês | F4: Value > Teste Pro 109 € — fixos 400 €/mês | G4: Value > Teste Pro 109 € — fixos 500 €/mês | H4: Value > Teste Pro 119 € — fixos 300 €/mês | I4: Value > Teste Pro 119 € — fixos 400 €/mês | J4: Value > Teste Pro 119 € — fixos 500 €/mês
A5: Preço mensal Pro (EUR) | B5: =99 -> 99 | C5: =99 -> 99 | D5: =99 -> 99 | E5: =109 -> 109 | F5: =109 -> 109 | G5: =109 -> 109 | H5: =119 -> 119 | I5: =119 -> 119 | J5: =119 -> 119
A6: Fixos anuais da projeção Base (EUR) | B6: ='DisruptRadar — Projeção mensal'!B5 -> 6000 | C6: ='DisruptRadar — Projeção men (4)'!C5 -> 3600 | D6: ='DisruptRadar — Projeção men (4)'!D5 -> 4800 | E6: =3600 -> 3600 | F6: =4800 -> 4800 | G6: =6000 -> 6000 | H6: =3600 -> 3600 | I6: =4800 -> 4800 | J6: =6000 -> 6000
A7: Clientes-mês — projeção Base | B7: =SUM('DisruptRadar — Projeção men (2)'!B5,'DisruptRadar — Projeção men (2)'!C5,'DisruptRadar — Projeção men (2)'!D5,'DisruptRadar — Projeção men (2)'!E5,'DisruptRadar — Projeção men (2)'!F5,'DisruptRadar — Projeção men (2)'!G5,'DisruptRadar — Projeção men (2)'!H5,'DisruptRadar — Projeção men (2)'!I5,'DisruptRadar — Projeção men (2)'!J5,'DisruptRadar — Projeção men (2)'!K5,'DisruptRadar — Projeção men (2)'!L5,'DisruptRadar — Projeção men (2)'!M5) -> 304 | C7: =SUM('Model inputs'!C20,'Model inputs'!D20,'Model inputs'!E20,'Model inputs'!F20,'Model inputs'!G20,'Model inputs'!H20,'Model inputs'!I20,'Model inputs'!J20,'Model inputs'!K20,'Model inputs'!L20,'Model inputs'!M20,'Model inputs'!N20) -> 304 | D7: =SUM('Model inputs'!C18,'Model inputs'!D18,'Model inputs'!E18,'Model inputs'!F18,'Model inputs'!G18,'Model inputs'!H18,'Model inputs'!I18,'Model inputs'!J18,'Model inputs'!K18,'Model inputs'!L18,'Model inputs'!M18,'Model inputs'!N18) -> 304 | E7: =SUM('Model inputs'!C23,'Model inputs'!D23,'Model inputs'!E23,'Model inputs'!F23,'Model inputs'!G23,'Model inputs'!H23,'Model inputs'!I23,'Model inputs'!J23,'Model inputs'!K23,'Model inputs'!L23,'Model inputs'!M23,'Model inputs'!N23) -> 304 | F7: =SUM('Model inputs'!C19,'Model inputs'!D19,'Model inputs'!E19,'Model inputs'!F19,'Model inputs'!G19,'Model inputs'!H19,'Model inputs'!I19,'Model inputs'!J19,'Model inputs'!K19,'Model inputs'!L19,'Model inputs'!M19,'Model inputs'!N19) -> 304 | G7: =SUM('Model inputs'!C17,'Model inputs'!D17,'Model inputs'!E17,'Model inputs'!F17,'Model inputs'!G17,'Model inputs'!H17,'Model inputs'!I17,'Model inputs'!J17,'Model inputs'!K17,'Model inputs'!L17,'Model inputs'!M17,'Model inputs'!N17) -> 304 | H7: =SUM('Model inputs'!C24,'Model inputs'!D24,'Model inputs'!E24,'Model inputs'!F24,'Model inputs'!G24,'Model inputs'!H24,'Model inputs'!I24,'Model inputs'!J24,'Model inputs'!K24,'Model inputs'!L24,'Model inputs'!M24,'Model inputs'!N24) -> 304 | I7: =SUM('Model inputs'!C22,'Model inputs'!D22,'Model inputs'!E22,'Model inputs'!F22,'Model inputs'!G22,'Model inputs'!H22,'Model inputs'!I22,'Model inputs'!J22,'Model inputs'!K22,'Model inputs'!L22,'Model inputs'!M22,'Model inputs'!N22) -> 304 | J7: =SUM('Model inputs'!C21,'Model inputs'!D21,'Model inputs'!E21,'Model inputs'!F21,'Model inputs'!G21,'Model inputs'!H21,'Model inputs'!I21,'Model inputs'!J21,'Model inputs'!K21,'Model inputs'!L21,'Model inputs'!M21,'Model inputs'!N21) -> 304
A8: Receita anual — projeção Base (EUR) | B8: =SUM('DisruptRadar — Projeção men (2)'!B6,'DisruptRadar — Projeção men (2)'!C6,'DisruptRadar — Projeção men (2)'!D6,'DisruptRadar — Projeção men (2)'!E6,'DisruptRadar — Projeção men (2)'!F6,'DisruptRadar — Projeção men (2)'!G6,'DisruptRadar — Projeção men (2)'!H6,'DisruptRadar — Projeção men (2)'!I6,'DisruptRadar — Projeção men (2)'!J6,'DisruptRadar — Projeção men (2)'!K6,'DisruptRadar — Projeção men (2)'!L6,'DisruptRadar — Projeção men (2)'!M6) -> 30096 | C8: =SUM('Model inputs'!C71,'Model inputs'!D71,'Model inputs'!E71,'Model inputs'!F71,'Model inputs'!G71,'Model inputs'!H71,'Model inputs'!I71,'Model inputs'!J71,'Model inputs'!K71,'Model inputs'!L71,'Model inputs'!M71,'Model inputs'!N71) -> 30096 | D8: =SUM('Model inputs'!C69,'Model inputs'!D69,'Model inputs'!E69,'Model inputs'!F69,'Model inputs'!G69,'Model inputs'!H69,'Model inputs'!I69,'Model inputs'!J69,'Model inputs'!K69,'Model inputs'!L69,'Model inputs'!M69,'Model inputs'!N69) -> 30096 | E8: =SUM('Model inputs'!C74,'Model inputs'!D74,'Model inputs'!E74,'Model inputs'!F74,'Model inputs'!G74,'Model inputs'!H74,'Model inputs'!I74,'Model inputs'!J74,'Model inputs'!K74,'Model inputs'!L74,'Model inputs'!M74,'Model inputs'!N74) -> 33136 | F8: =SUM('Model inputs'!C70,'Model inputs'!D70,'Model inputs'!E70,'Model inputs'!F70,'Model inputs'!G70,'Model inputs'!H70,'Model inputs'!I70,'Model inputs'!J70,'Model inputs'!K70,'Model inputs'!L70,'Model inputs'!M70,'Model inputs'!N70) -> 33136 | G8: =SUM('Model inputs'!C68,'Model inputs'!D68,'Model inputs'!E68,'Model inputs'!F68,'Model inputs'!G68,'Model inputs'!H68,'Model inputs'!I68,'Model inputs'!J68,'Model inputs'!K68,'Model inputs'!L68,'Model inputs'!M68,'Model inputs'!N68) -> 33136 | H8: =SUM('Model inputs'!C75,'Model inputs'!D75,'Model inputs'!E75,'Model inputs'!F75,'Model inputs'!G75,'Model inputs'!H75,'Model inputs'!I75,'Model inputs'!J75,'Model inputs'!K75,'Model inputs'!L75,'Model inputs'!M75,'Model inputs'!N75) -> 36176 | I8: =SUM('Model inputs'!C73,'Model inputs'!D73,'Model inputs'!E73,'Model inputs'!F73,'Model inputs'!G73,'Model inputs'!H73,'Model inputs'!I73,'Model inputs'!J73,'Model inputs'!K73,'Model inputs'!L73,'Model inputs'!M73,'Model inputs'!N73) -> 36176 | J8: =SUM('Model inputs'!C72,'Model inputs'!D72,'Model inputs'!E72,'Model inputs'!F72,'Model inputs'!G72,'Model inputs'!H72,'Model inputs'!I72,'Model inputs'!J72,'Model inputs'!K72,'Model inputs'!L72,'Model inputs'!M72,'Model inputs'!N72) -> 36176
A9: Entrega anual — projeção Base (EUR) | B9: =SUM('DisruptRadar — Projeção men (2)'!B7,'DisruptRadar — Projeção men (2)'!C7,'DisruptRadar — Projeção men (2)'!D7,'DisruptRadar — Projeção men (2)'!E7,'DisruptRadar — Projeção men (2)'!F7,'DisruptRadar — Projeção men (2)'!G7,'DisruptRadar — Projeção men (2)'!H7,'DisruptRadar — Projeção men (2)'!I7,'DisruptRadar — Projeção men (2)'!J7,'DisruptRadar — Projeção men (2)'!K7,'DisruptRadar — Projeção men (2)'!L7,'DisruptRadar — Projeção men (2)'!M7) -> 9120 | C9: =SUM('Model inputs'!C55,'Model inputs'!D55,'Model inputs'!E55,'Model inputs'!F55,'Model inputs'!G55,'Model inputs'!H55,'Model inputs'!I55,'Model inputs'!J55,'Model inputs'!K55,'Model inputs'!L55,'Model inputs'!M55,'Model inputs'!N55) -> 9120 | D9: =SUM('Model inputs'!C53,'Model inputs'!D53,'Model inputs'!E53,'Model inputs'!F53,'Model inputs'!G53,'Model inputs'!H53,'Model inputs'!I53,'Model inputs'!J53,'Model inputs'!K53,'Model inputs'!L53,'Model inputs'!M53,'Model inputs'!N53) -> 9120 | E9: =SUM('Model inputs'!C58,'Model inputs'!D58,'Model inputs'!E58,'Model inputs'!F58,'Model inputs'!G58,'Model inputs'!H58,'Model inputs'!I58,'Model inputs'!J58,'Model inputs'!K58,'Model inputs'!L58,'Model inputs'!M58,'Model inputs'!N58) -> 9120 | F9: =SUM('Model inputs'!C54,'Model inputs'!D54,'Model inputs'!E54,'Model inputs'!F54,'Model inputs'!G54,'Model inputs'!H54,'Model inputs'!I54,'Model inputs'!J54,'Model inputs'!K54,'Model inputs'!L54,'Model inputs'!M54,'Model inputs'!N54) -> 9120 | G9: =SUM('Model inputs'!C52,'Model inputs'!D52,'Model inputs'!E52,'Model inputs'!F52,'Model inputs'!G52,'Model inputs'!H52,'Model inputs'!I52,'Model inputs'!J52,'Model inputs'!K52,'Model inputs'!L52,'Model inputs'!M52,'Model inputs'!N52) -> 9120 | H9: =SUM('Model inputs'!C59,'Model inputs'!D59,'Model inputs'!E59,'Model inputs'!F59,'Model inputs'!G59,'Model inputs'!H59,'Model inputs'!I59,'Model inputs'!J59,'Model inputs'!K59,'Model inputs'!L59,'Model inputs'!M59,'Model inputs'!N59) -> 9120 | I9: =SUM('Model inputs'!C57,'Model inputs'!D57,'Model inputs'!E57,'Model inputs'!F57,'Model inputs'!G57,'Model inputs'!H57,'Model inputs'!I57,'Model inputs'!J57,'Model inputs'!K57,'Model inputs'!L57,'Model inputs'!M57,'Model inputs'!N57) -> 9120 | J9: =SUM('Model inputs'!C56,'Model inputs'!D56,'Model inputs'!E56,'Model inputs'!F56,'Model inputs'!G56,'Model inputs'!H56,'Model inputs'!I56,'Model inputs'!J56,'Model inputs'!K56,'Model inputs'!L56,'Model inputs'!M56,'Model inputs'!N56) -> 9120
A10: EBITDA anual — projeção Base (EUR) | B10: =SUM('DisruptRadar — Projeção men (2)'!B10,'DisruptRadar — Projeção men (2)'!C10,'DisruptRadar — Projeção men (2)'!D10,'DisruptRadar — Projeção men (2)'!E10,'DisruptRadar — Projeção men (2)'!F10,'DisruptRadar — Projeção men (2)'!G10,'DisruptRadar — Projeção men (2)'!H10,'DisruptRadar — Projeção men (2)'!I10,'DisruptRadar — Projeção men (2)'!J10,'DisruptRadar — Projeção men (2)'!K10,'DisruptRadar — Projeção men (2)'!L10,'DisruptRadar — Projeção men (2)'!M10) -> 14976 | C10: =SUM('Model inputs'!C45,'Model inputs'!D45,'Model inputs'!E45,'Model inputs'!F45,'Model inputs'!G45,'Model inputs'!H45,'Model inputs'!I45,'Model inputs'!J45,'Model inputs'!K45,'Model inputs'!L45,'Model inputs'!M45,'Model inputs'!N45) -> 17376 | D10: =SUM('Model inputs'!C43,'Model inputs'!D43,'Model inputs'!E43,'Model inputs'!F43,'Model inputs'!G43,'Model inputs'!H43,'Model inputs'!I43,'Model inputs'!J43,'Model inputs'!K43,'Model inputs'!L43,'Model inputs'!M43,'Model inputs'!N43) -> 16176 | E10: =SUM('Model inputs'!C49,'Model inputs'!D49,'Model inputs'!E49,'Model inputs'!F49,'Model inputs'!G49,'Model inputs'!H49,'Model inputs'!I49,'Model inputs'!J49,'Model inputs'!K49,'Model inputs'!L49,'Model inputs'!M49,'Model inputs'!N49) -> 20416 | F10: =SUM('Model inputs'!C44,'Model inputs'!D44,'Model inputs'!E44,'Model inputs'!F44,'Model inputs'!G44,'Model inputs'!H44,'Model inputs'!I44,'Model inputs'!J44,'Model inputs'!K44,'Model inputs'!L44,'Model inputs'!M44,'Model inputs'!N44) -> 19216 | G10: =SUM('Model inputs'!C42,'Model inputs'!D42,'Model inputs'!E42,'Model inputs'!F42,'Model inputs'!G42,'Model inputs'!H42,'Model inputs'!I42,'Model inputs'!J42,'Model inputs'!K42,'Model inputs'!L42,'Model inputs'!M42,'Model inputs'!N42) -> 18016 | H10: =SUM('Model inputs'!C50,'Model inputs'!D50,'Model inputs'!E50,'Model inputs'!F50,'Model inputs'!G50,'Model inputs'!H50,'Model inputs'!I50,'Model inputs'!J50,'Model inputs'!K50,'Model inputs'!L50,'Model inputs'!M50,'Model inputs'!N50) -> 23456 | I10: =SUM('Model inputs'!C47,'Model inputs'!D47,'Model inputs'!E47,'Model inputs'!F47,'Model inputs'!G47,'Model inputs'!H47,'Model inputs'!I47,'Model inputs'!J47,'Model inputs'!K47,'Model inputs'!L47,'Model inputs'!M47,'Model inputs'!N47) -> 22256 | J10: =SUM('Model inputs'!C46,'Model inputs'!D46,'Model inputs'!E46,'Model inputs'!F46,'Model inputs'!G46,'Model inputs'!H46,'Model inputs'!I46,'Model inputs'!J46,'Model inputs'!K46,'Model inputs'!L46,'Model inputs'!M46,'Model inputs'!N46) -> 21056

Sheet DisruptRadar — Projeção men (6)
A1: DisruptRadar — Projeção mensal · Limiares de procura — indiferença e breakeven
A2: Financial model (2 pages) · Base
A4: Variable / dimension | B4: Value | C4: Value > Teste Pro 109 € — fixos 500 €/mês | D4: Value > Teste Pro 119 € — fixos 500 €/mês
A5: Preço de referência para indiferença (EUR) | B5: =99 -> 99 | C5: =99 -> 99 | D5: =99 -> 99
A6: Fixos mensais de referência para limiares (EUR) | B6: =500 -> 500 | C6: =500 -> 500 | D6: =500 -> 500
A7: Preço mensal Pro (EUR) | B7: =99 -> 99 | C7: ='DisruptRadar — Projeção men (5)'!G5 -> 109 | D7: ='DisruptRadar — Projeção men (5)'!J5 -> 119
A8: Entrega por cliente-mês — limiares (EUR) | B8: ='DisruptRadar Business Plan · Pr'!B14*'DisruptRadar Business Plan · Pr'!B11 -> 30 | C8: ='Model inputs'!Z37*'Model inputs'!Z27 -> 30 | D8: ='Model inputs'!Z40*'Model inputs'!Z30 -> 30
A9: Margem por cliente-mês no preço de referência (EUR) | B9: ='DisruptRadar — Projeção men (6)'!B5-'DisruptRadar — Projeção men (6)'!B8 -> 69 | C9: ='DisruptRadar — Projeção men (6)'!C5-'DisruptRadar — Projeção men (6)'!C8 -> 69 | D9: ='DisruptRadar — Projeção men (6)'!D5-'DisruptRadar — Projeção men (6)'!D8 -> 69
A10: Margem por cliente-mês no preço testado (EUR) | B10: ='DisruptRadar — Projeção men (6)'!B7-'DisruptRadar — Projeção men (6)'!B8 -> 69 | C10: ='DisruptRadar — Projeção men (6)'!C7-'DisruptRadar — Projeção men (6)'!C8 -> 79 | D10: ='DisruptRadar — Projeção men (6)'!D7-'DisruptRadar — Projeção men (6)'!D8 -> 89
A11: Clientes-mês de referência para limiares | B11: =IF('DisruptRadar — Projeção men (3)'!B5="","",'DisruptRadar — Projeção men (3)'!B5) -> 304 | C11: =IF('DisruptRadar — Projeção men (5)'!G7="","",'DisruptRadar — Projeção men (5)'!G7) -> 304 | D11: =IF('DisruptRadar — Projeção men (5)'!J7="","",'DisruptRadar — Projeção men (5)'!J7) -> 304
A12: EBITDA de referência dos limiares (EUR) | B12: ='DisruptRadar — Projeção men (6)'!B11*'DisruptRadar — Projeção men (6)'!B9-'DisruptRadar — Projeção men (6)'!B6*12 -> 14976 | C12: ='DisruptRadar — Projeção men (6)'!C11*'DisruptRadar — Projeção men (6)'!C9-'DisruptRadar — Projeção men (6)'!C6*12 -> 14976 | D12: ='DisruptRadar — Projeção men (6)'!D11*'DisruptRadar — Projeção men (6)'!D9-'DisruptRadar — Projeção men (6)'!D6*12 -> 14976
A13: Clientes-mês mínimos para EBITDA de referência | B13: =IF(IF(IF(ISERROR('DisruptRadar — Projeção men (6)'!B10>0),'DisruptRadar — Projeção men (6)'!B10>0,IF('DisruptRadar — Projeção men (6)'!B10="","",'DisruptRadar — Projeção men (6)'!B10>0))="",FALSE,IF(ISERROR('DisruptRadar — Projeção men (6)'!B10>0),'DisruptRadar — Projeção men (6)'!B10>0,IF('DisruptRadar — Projeção men (6)'!B10="","",'DisruptRadar — Projeção men (6)'!B10>0))),'DisruptRadar — Projeção men (6)'!B11*'DisruptRadar — Projeção men (6)'!B9/'DisruptRadar — Projeção men (6)'!B10,"") -> 304 | C13: =IF(IF(IF(ISERROR('DisruptRadar — Projeção men (6)'!C10>0),'DisruptRadar — Projeção men (6)'!C10>0,IF('DisruptRadar — Projeção men (6)'!C10="","",'DisruptRadar — Projeção men (6)'!C10>0))="",FALSE,IF(ISERROR('DisruptRadar — Projeção men (6)'!C10>0),'DisruptRadar — Projeção men (6)'!C10>0,IF('DisruptRadar — Projeção men (6)'!C10="","",'DisruptRadar — Projeção men (6)'!C10>0))),'DisruptRadar — Projeção men (6)'!C11*'DisruptRadar — Projeção men (6)'!C9/'DisruptRadar — Projeção men (6)'!C10,"") -> 265.51899 | D13: =IF(IF(IF(ISERROR('DisruptRadar — Projeção men (6)'!D10>0),'DisruptRadar — Projeção men (6)'!D10>0,IF('DisruptRadar — Projeção men (6)'!D10="","",'DisruptRadar — Projeção men (6)'!D10>0))="",FALSE,IF(ISERROR('DisruptRadar — Projeção men (6)'!D10>0),'DisruptRadar — Projeção men (6)'!D10>0,IF('DisruptRadar — Projeção men (6)'!D10="","",'DisruptRadar — Projeção men (6)'!D10>0))),'DisruptRadar — Projeção men (6)'!D11*'DisruptRadar — Projeção men (6)'!D9/'DisruptRadar — Projeção men (6)'!D10,"") -> 235.68539
A14: Clientes-mês inteiros para EBITDA de referência | B14: =IF('DisruptRadar — Projeção men (6)'!B13="","",CEILING('DisruptRadar — Projeção men (6)'!B13,1)) -> 304 | C14: =IF('DisruptRadar — Projeção men (6)'!C13="","",CEILING('DisruptRadar — Projeção men (6)'!C13,1)) -> 266 | D14: =IF('DisruptRadar — Projeção men (6)'!D13="","",CEILING('DisruptRadar — Projeção men (6)'!D13,1)) -> 236
A15: Perda máxima de procura vs referência | B15: =IFERROR(1-'DisruptRadar — Projeção men (6)'!B13/'DisruptRadar — Projeção men (6)'!B11,"") -> 0 | C15: =IFERROR(1-'DisruptRadar — Projeção men (6)'!C13/'DisruptRadar — Projeção men (6)'!C11,"") -> 0.12658228 | D15: =IFERROR(1-'DisruptRadar — Projeção men (6)'!D13/'DisruptRadar — Projeção men (6)'!D11,"") -> 0.2247191
A16: Clientes-mês de breakeven absoluto | B16: =IF(IF(IF(ISERROR('DisruptRadar — Projeção men (6)'!B10>0),'DisruptRadar — Projeção men (6)'!B10>0,IF('DisruptRadar — Projeção men (6)'!B10="","",'DisruptRadar — Projeção men (6)'!B10>0))="",FALSE,IF(ISERROR('DisruptRadar — Projeção men (6)'!B10>0),'DisruptRadar — Projeção men (6)'!B10>0,IF('DisruptRadar — Projeção men (6)'!B10="","",'DisruptRadar — Projeção men (6)'!B10>0))),'DisruptRadar — Projeção men (6)'!B6*12/'DisruptRadar — Projeção men (6)'!B10,"") -> 86.956522 | C16: =IF(IF(IF(ISERROR('DisruptRadar — Projeção men (6)'!C10>0),'DisruptRadar — Projeção men (6)'!C10>0,IF('DisruptRadar — Projeção men (6)'!C10="","",'DisruptRadar — Projeção men (6)'!C10>0))="",FALSE,IF(ISERROR('DisruptRadar — Projeção men (6)'!C10>0),'DisruptRadar — Projeção men (6)'!C10>0,IF('DisruptRadar — Projeção men (6)'!C10="","",'DisruptRadar — Projeção men (6)'!C10>0))),'DisruptRadar — Projeção men (6)'!C6*12/'DisruptRadar — Projeção men (6)'!C10,"") -> 75.949367 | D16: =IF(IF(IF(ISERROR('DisruptRadar — Projeção men (6)'!D10>0),'DisruptRadar — Projeção men (6)'!D10>0,IF('DisruptRadar — Projeção men (6)'!D10="","",'DisruptRadar — Projeção men (6)'!D10>0))="",FALSE,IF(ISERROR('DisruptRadar — Projeção men (6)'!D10>0),'DisruptRadar — Projeção men (6)'!D10>0,IF('DisruptRadar — Projeção men (6)'!D10="","",'DisruptRadar — Projeção men (6)'!D10>0))),'DisruptRadar — Projeção men (6)'!D6*12/'DisruptRadar — Projeção men (6)'!D10,"") -> 67.41573
A17: Clientes-mês inteiros de breakeven absoluto | B17: =IF('DisruptRadar — Projeção men (6)'!B16="","",CEILING('DisruptRadar — Projeção men (6)'!B16,1)) -> 87 | C17: =IF('DisruptRadar — Projeção men (6)'!C16="","",CEILING('DisruptRadar — Projeção men (6)'!C16,1)) -> 76 | D17: =IF('DisruptRadar — Projeção men (6)'!D16="","",CEILING('DisruptRadar — Projeção men (6)'!D16,1)) -> 68
A18: Breakeven como proporção da procura de referência | B18: =IFERROR('DisruptRadar — Projeção men (6)'!B16/'DisruptRadar — Projeção men (6)'!B11,"") -> 0.28604119 | C18: =IFERROR('DisruptRadar — Projeção men (6)'!C16/'DisruptRadar — Projeção men (6)'!C11,"") -> 0.24983344 | D18: =IFERROR('DisruptRadar — Projeção men (6)'!D16/'DisruptRadar — Projeção men (6)'!D11,"") -> 0.22176227
A19: Verificação do EBITDA no ponto de indiferença (EUR) | B19: =IF('DisruptRadar — Projeção men (6)'!B13="","",'DisruptRadar — Projeção men (6)'!B13*'DisruptRadar — Projeção men (6)'!B10-'DisruptRadar — Projeção men (6)'!B6*12-'DisruptRadar — Projeção men (6)'!B12) -> 0 | C19: =IF('DisruptRadar — Projeção men (6)'!C13="","",'DisruptRadar — Projeção men (6)'!C13*'DisruptRadar — Projeção men (6)'!C10-'DisruptRadar — Projeção men (6)'!C6*12-'DisruptRadar — Projeção men (6)'!C12) -> 0 | D19: =IF('DisruptRadar — Projeção men (6)'!D13="","",'DisruptRadar — Projeção men (6)'!D13*'DisruptRadar — Projeção men (6)'!D10-'DisruptRadar — Projeção men (6)'!D6*12-'DisruptRadar — Projeção men (6)'!D12) -> 0

Sheet DisruptRadar — Projeção men (7)
A1: DisruptRadar — Projeção mensal · Teste de perda de procura — cálculo anual
A2: Financial model (2 pages) · Base
A4: Variable / dimension | B4: Value
A5: Perda de procura em teste | B5: =0 -> 0
A6: Preço mensal Pro (EUR) | B6: =99 -> 99
A7: Fixos anuais da projeção Base (EUR) | B7: ='DisruptRadar — Projeção mensal'!B5 -> 6000
A8: Clientes-mês após perda de procura | B8: ='DisruptRadar — Projeção men (3)'!B5*(1-'DisruptRadar — Projeção men (7)'!B5) -> 304
A9: Receita anual após perda de procura (EUR) | B9: ='DisruptRadar — Projeção men (7)'!B8*'DisruptRadar — Projeção men (7)'!B6 -> 30096
A10: Entrega anual após perda de procura (EUR) | B10: ='DisruptRadar — Projeção men (7)'!B8*'DisruptRadar Business Plan · Pr'!B14*'DisruptRadar Business Plan · Pr'!B11 -> 9120
A11: EBITDA anual após perda de procura (EUR) | B11: ='DisruptRadar — Projeção men (7)'!B9-'DisruptRadar — Projeção men (7)'!B10-'DisruptRadar — Projeção men (7)'!B7 -> 14976
A12: Caixa final anual após perda de procura (EUR) | B12: ='DisruptRadar Business Plan · Pr'!B7+'DisruptRadar — Projeção men (7)'!B11 -> 34976
A13: Diferença de EBITDA após perda vs referência (EUR) | B13: ='DisruptRadar — Projeção men (7)'!B11-'DisruptRadar — Projeção men (6)'!B12 -> 0

Sheet Model inputs
A1: Model inputs
A2: Integration values are aggregated snapshots; raw source records are not included.
A4: Variables
A5: Variable / segment | B5: 2026-12 | C5: 2027-01 | D5: 2027-02 | E5: 2027-03 | F5: 2027-04 | G5: 2027-05 | H5: 2027-06 | I5: 2027-07 | J5: 2027-08 | K5: 2027-09 | L5: 2027-10 | M5: 2027-11 | N5: 2027-12 | O5: 2026-01 | P5: 2026-02 | Q5: 2026-03 | R5: 2026-04 | S5: 2026-05 | T5: 2026-06 | U5: 2026-07 | V5: 2026-08 | W5: 2026-09 | X5: 2026-10 | Y5: 2026-11 | Z5: Value | AA5: Value
A6: Caixa final — projeção Base (EUR) · DisruptRadar — Projeção mensal · Projeção mensal Base — clientes, resultado e caixa · Base | B6: ='Model inputs'!B15+'Model inputs'!B41 -> -1500 | C6: ='Model inputs'!C15+'Model inputs'!C41 -> 19569 | D6: ='Model inputs'!D15+'Model inputs'!D41 -> 19345 | E6: ='Model inputs'!E15+'Model inputs'!E41 -> 19466 | F6: ='Model inputs'!F15+'Model inputs'!F41 -> 19932 | G6: ='Model inputs'!G15+'Model inputs'!G41 -> 20812 | H6: ='Model inputs'!H15+'Model inputs'!H41 -> 22106 | I6: ='Model inputs'!I15+'Model inputs'!I41 -> 23814 | ... N6: ='Model inputs'!N15+'Model inputs'!N41 -> 34976
A7: Caixa final — projeção Base (EUR) · DisruptRadar — Projeção mensal · Reconciliação anual Base com a matriz · Base | B7: =IF('Model inputs'!B6="","",'Model inputs'!B6) -> -1500 | C7: =IF('Model inputs'!C6="","",'Model inputs'!C6) -> 19569 | D7: =IF('Model inputs'!D6="","",'Model inputs'!D6) -> 19345 | E7: =IF('Model inputs'!E6="","",'Model inputs'!E6) -> 19466 | F7: =IF('Model inputs'!F6="","",'Model inputs'!F6) -> 19932 | G7: =IF('Model inputs'!G6="","",'Model inputs'!G6) -> 20812 | H7: =IF('Model inputs'!H6="","",'Model inputs'!H6) -> 22106 | I7: =IF('Model inputs'!I6="","",'Model inputs'!I6) -> 23814 | ... N7: =IF('Model inputs'!N6="","",'Model inputs'!N6) -> 34976 | O7: 0 | P7: 0 | Q7: 0 | R7: 0 | S7: 0 | T7: 0 | U7: 0 | V7: 0 | W7: 0 | X7: ='Model inputs'!X15+'Model inputs'!X41 -> -500 | Y7: ='Model inputs'!Y15+'Model inputs'!Y41 -> -1000
A8: Caixa final — projeção Base (EUR) · Base — fixos 400 €/mês | B8: ='Model inputs'!B77+'Model inputs'!B43 -> -1200 | C8: ='Model inputs'!C77+'Model inputs'!C43 -> 19669 | D8: ='Model inputs'!D77+'Model inputs'!D43 -> 19545 | E8: ='Model inputs'!E77+'Model inputs'!E43 -> 19766 | F8: ='Model inputs'!F77+'Model inputs'!F43 -> 20332 | G8: ='Model inputs'!G77+'Model inputs'!G43 -> 21312 | H8: ='Model inputs'!H77+'Model inputs'!H43 -> 22706 | I8: ='Model inputs'!I77+'Model inputs'!I43 -> 24514 | ... N8: ='Model inputs'!N77+'Model inputs'!N43 -> 36176 | O8: 0 | P8: 0 | Q8: 0 | R8: 0 | S8: 0 | T8: 0 | U8: 0 | V8: 0 | W8: 0 | X8: ='Model inputs'!X77+'Model inputs'!X43 -> -400 | Y8: ='Model inputs'!Y77+'Model inputs'!Y43 -> -800
A9: Caixa final — projeção Base (EUR) · Base — fixos 300 €/mês | B9: ='Model inputs'!B78+'Model inputs'!B45 -> -900 | C9: ='Model inputs'!C78+'Model inputs'!C45 -> 19769 | D9: ='Model inputs'!D78+'Model inputs'!D45 -> 19745 | E9: ='Model inputs'!E78+'Model inputs'!E45 -> 20066 | F9: ='Model inputs'!F78+'Model inputs'!F45 -> 20732 | G9: ='Model inputs'!G78+'Model inputs'!G45 -> 21812 | H9: ='Model inputs'!H78+'Model inputs'!H45 -> 23306 | I9: ='Model inputs'!I78+'Model inputs'!I45 -> 25214 | ... N9: ='Model inputs'!N78+'Model inputs'!N45 -> 37376 | O9: 0 | P9: 0 | Q9: 0 | R9: 0 | S9: 0 | T9: 0 | U9: 0 | V9: 0 | W9: 0 | X9: ='Model inputs'!X78+'Model inputs'!X45 -> -300 | Y9: ='Model inputs'!Y78+'Model inputs'!Y45 -> -600
A10: Caixa final — projeção Base (EUR) · Base — fixos 500 €/mês | B10: ='Model inputs'!B79+'Model inputs'!B48 -> -1500 | C10: ='Model inputs'!C79+'Model inputs'!C48 -> 19569 | D10: ='Model inputs'!D79+'Model inputs'!D48 -> 19345 | E10: ='Model inputs'!E79+'Model inputs'!E48 -> 19466 | F10: ='Model inputs'!F79+'Model inputs'!F48 -> 19932 | G10: ='Model inputs'!G79+'Model inputs'!G48 -> 20812 | H10: ='Model inputs'!H79+'Model inputs'!H48 -> 22106 | I10: ='Model inputs'!I79+'Model inputs'!I48 -> 23814 | ... N10: ='Model inputs'!N79+'Model inputs'!N48 -> 34976 | O10: 0 | P10: 0 | Q10: 0 | R10: 0 | S10: 0 | T10: 0 | U10: 0 | V10: 0 | W10: 0 | X10: ='Model inputs'!X79+'Model inputs'!X48 -> -500 | Y10: ='Model inputs'!Y79+'Model inputs'!Y48 -> -1000
A11: Caixa inicial (EUR) · DisruptRadar Business Plan · Matriz de cenários DisruptRadar · Base | Z11: =20000 -> 20000
A12: Caixa inicial (EUR) · DisruptRadar — Projeção mensal · Projeção mensal Base — clientes, resultado e caixa · Base | AA12: =20000 -> 20000
A13: Caixa inicial (EUR) · Pessimista | Z13: =20000 -> 20000
A14: Caixa inicial (EUR) · Otimista | Z14: =20000 -> 20000
A15: Caixa inicial do mês — projeção Base (EUR) · DisruptRadar — Projeção mensal · Projeção mensal Base — clientes, resultado e caixa | B15: =IF(IF(IF(ISERROR(DATE(2026,12,1)=DATE(YEAR('Model inputs'!AA63),MONTH('Model inputs'!AA63),1)),DATE(2026,12,1)=DATE(YEAR('Model inputs'!AA63),MONTH('Model inputs'!AA63),1),IF(DATE(YEAR('Model inputs'!AA63),MONTH('Model inputs'!AA63),1)="","",DATE(2026,12,1)=DATE(YEAR('Model inputs'!AA63),MONTH('Model inputs'!AA63),1)))="",FALSE,IF(ISERROR(DATE(2026,12,1)=DATE(YEAR('Model inputs'!AA63),MONTH('Model inputs'!AA63),1)),DATE(2026,12,1)=DATE(YEAR('Model inputs'!AA63),MONTH('Model inputs'!AA63),1),IF(DATE(YEAR('Model inputs'!AA63),MONTH('Model inputs'!AA63),1)="","",DATE(2026,12,1)=DATE(YEAR('Model inputs'!AA63),MONTH('Model inputs'!AA63),1)))),IF('Model inputs'!Z11="","",'Model inputs'!Z11),IF('Model inputs'!Y7="","",'Model inputs'!Y7)) -> -1000 | C15: =IF(IF(IF(ISERROR(DATE(2027,1,1)=DATE(YEAR('Model inputs'!AA63),MONTH('Model inputs'!AA63),1)),DATE(2027,1,1)=DATE(YEAR('Model inputs'!AA63),MONTH('Model inputs'!AA63),1),IF(DATE(YEAR('Model inputs'!AA63),MONTH('Model inputs'!AA63),1)="","",DATE(2027,1,1)=DATE(YEAR('Model inputs'!AA63),MONTH('Model inputs'!AA63),1)))="",FALSE,IF(ISERROR(DATE(2027,1,1)=DATE(YEAR('Model inputs'!AA63),MONTH('Model inputs'!AA63),1)),DATE(2027,1,1)=DATE(YEAR('Model inputs'!AA63),MONTH('Model inputs'!AA63),1),IF(DATE(YEAR('Model inputs'!AA63),MONTH('Model inputs'!AA63),1)="","",DATE(2027,1,1)=DATE(YEAR('Model inputs'!AA63),MONTH('Model inputs'!AA63),1)))),IF('Model inputs'!Z11="","",'Model inputs'!Z11),IF('Model inputs'!B6="","",'Model inputs'!B6)) -> 20000 | D15: =IF(IF(IF(ISERROR(DATE(2027,2,1)=DATE(YEAR('Model inputs'!AA63),MONTH('Model inputs'!AA63),1)),DATE(2027,2,1)=DATE(YEAR('Model inputs'!AA63),MONTH('Model inputs'!AA63),1),IF(DATE(YEAR('Model inputs'!AA63),MONTH('Model inputs'!AA63),1)="","",DATE(2027,2,1)=DATE(YEAR('Model inputs'!AA63),MONTH('Model inputs'!AA63),1)))="",FALSE,IF(ISERROR(DATE(2027,2,1)=DATE(YEAR('Model inputs'!AA63),MONTH('Model inputs'!AA63),1)),DATE(2027,2,1)=DATE(YEAR('Model inputs'!AA63),MONTH('Model inputs'!AA63),1),IF(DATE(YEAR('Model inputs'!AA63),MONTH('Model inputs'!AA63),1)="","",DATE(2027,2,1)=DATE(YEAR('Model inputs'!AA63),MONTH('Model inputs'!AA63),1)))),IF('Model inputs'!Z11="","",'Model inputs'!Z11),IF('Model inputs'!C6="","",'Model inputs'!C6)) -> 19569 | E15: =IF(IF(IF(ISERROR(DATE(2027,3,1)=DATE(YEAR('Model inputs'!AA63),MONTH('Model inputs'!AA63),1)),DATE(2027,3,1)=DATE(YEAR('Model inputs'!AA63),MONTH('Model inputs'!AA63),1),IF(DATE(YEAR('Model inputs'!AA63),MONTH('Model inputs'!AA63),1)="","",DATE(2027,3,1)=DATE(YEAR('Model inputs'!AA63),MONTH('Model inputs'!AA63),1)))="",FALSE,IF(ISERROR(DATE(2027,3,1)=DATE(YEAR('Model inputs'!AA63),MONTH('Model inputs'!AA63),1)),DATE(2027,3,1)=DATE(YEAR('Model inputs'!AA63),MONTH('Model inputs'!AA63),1),IF(DATE(YEAR('Model inputs'!AA63),MONTH('Model inputs'!AA63),1)="","",DATE(2027,3,1)=DATE(YEAR('Model inputs'!AA63),MONTH('Model inputs'!AA63),1)))),IF('Model inputs'!Z11="","",'Model inputs'!Z11),IF('Model inputs'!D6="","",'Model inputs'!D6)) -> 19345 | F15: =IF(IF(IF(ISERROR(DATE(2027,4,1)=DATE(YEAR('Model inputs'!AA63),MONTH('Model inputs'!AA63),1)),DATE(2027,4,1)=DATE(YEAR('Model inputs'!AA63),MONTH('Model inputs'!AA63),1),IF(DATE(YEAR('Model inputs'!AA63),MONTH('Model inputs'!AA63),1)="","",DATE(2027,4,1)=DATE(YEAR('Model inputs'!AA63),MONTH('Model inputs'!AA63),1)))="",FALSE,IF(ISERROR(DATE(2027,4,1)=DATE(YEAR('Model inputs'!AA63),MONTH('Model inputs'!AA63),1)),DATE(2027,4,1)=DATE(YEAR('Model inputs'!AA63),MONTH('Model inputs'!AA63),1),IF(DATE(YEAR('Model inputs'!AA63),MONTH('Model inputs'!AA63),1)="","",DATE(2027,4,1)=DATE(YEAR('Model inputs'!AA63),MONTH('Model inputs'!AA63),1)))),IF('Model inputs'!Z11="","",'Model inputs'!Z11),IF('Model inputs'!E6="","",'Model inputs'!E6)) -> 19466 | G15: =IF(IF(IF(ISERROR(DATE(2027,5,1)=DATE(YEAR('Model inputs'!AA63),MONTH('Model inputs'!AA63),1)),DATE(2027,5,1)=DATE(YEAR('Model inputs'!AA63),MONTH('Model inputs'!AA63),1),IF(DATE(YEAR('Model inputs'!AA63),MONTH('Model inputs'!AA63),1)="","",DATE(2027,5,1)=DATE(YEAR('Model inputs'!AA63),MONTH('Model inputs'!AA63),1)))="",FALSE,IF(ISERROR(DATE(2027,5,1)=DATE(YEAR('Model inputs'!AA63),MONTH('Model inputs'!AA63),1)),DATE(2027,5,1)=DATE(YEAR('Model inputs'!AA63),MONTH('Model inputs'!AA63),1),IF(DATE(YEAR('Model inputs'!AA63),MONTH('Model inputs'!AA63),1)="","",DATE(2027,5,1)=DATE(YEAR('Model inputs'!AA63),MONTH('Model inputs'!AA63),1)))),IF('Model inputs'!Z11="","",'Model inputs'!Z11),IF('Model inputs'!F6="","",'Model inputs'!F6)) -> 19932 | H15: =IF(IF(IF(ISERROR(DATE(2027,6,1)=DATE(YEAR('Model inputs'!AA63),MONTH('Model inputs'!AA63),1)),DATE(2027,6,1)=DATE(YEAR('Model inputs'!AA63),MONTH('Model inputs'!AA63),1),IF(DATE(YEAR('Model inputs'!AA63),MONTH('Model inputs'!AA63),1)="","",DATE(2027,6,1)=DATE(YEAR('Model inputs'!AA63),MONTH('Model inputs'!AA63),1)))="",FALSE,IF(ISERROR(DATE(2027,6,1)=DATE(YEAR('Model inputs'!AA63),MONTH('Model inputs'!AA63),1)),DATE(2027,6,1)=DATE(YEAR('Model inputs'!AA63),MONTH('Model inputs'!AA63),1),IF(DATE(YEAR('Model inputs'!AA63),MONTH('Model inputs'!AA63),1)="","",DATE(2027,6,1)=DATE(YEAR('Model inputs'!AA63),MONTH('Model inputs'!AA63),1)))),IF('Model inputs'!Z11="","",'Model inputs'!Z11),IF('Model inputs'!G6="","",'Model inputs'!G6)) -> 20812 | I15: =IF(IF(IF(ISERROR(DATE(2027,7,1)=DATE(YEAR('Model inputs'!AA63),MONTH('Model inputs'!AA63),1)),DATE(2027,7,1)=DATE(YEAR('Model inputs'!AA63),MONTH('Model inputs'!AA63),1),IF(DATE(YEAR('Model inputs'!AA63),MONTH('Model inputs'!AA63),1)="","",DATE(2027,7,1)=DATE(YEAR('Model inputs'!AA63),MONTH('Model inputs'!AA63),1)))="",FALSE,IF(ISERROR(DATE(2027,7,1)=DATE(YEAR('Model inputs'!AA63),MONTH('Model inputs'!AA63),1)),DATE(2027,7,1)=DATE(YEAR('Model inputs'!AA63),MONTH('Model inputs'!AA63),1),IF(DATE(YEAR('Model inputs'!AA63),MONTH('Model inputs'!AA63),1)="","",DATE(2027,7,1)=DATE(YEAR('Model inputs'!AA63),MONTH('Model inputs'!AA63),1)))),IF('Model inputs'!Z11="","",'Model inputs'!Z11),IF('Model inputs'!H6="","",'Model inputs'!H6)) -> 22106 | J15: =IF(IF(IF(ISERROR(DATE(2027,8,1)=DATE(YEAR('Model inputs'!AA63),MONTH('Model inputs'!AA63),1)),DATE(2027,8,1)=DATE(YEAR('Model inputs'!AA63),MONTH('Model inputs'!AA63),1),IF(DATE(YEAR('Model inputs'!AA63),MONTH('Model inputs'!AA63),1)="","",DATE(2027,8,1)=DATE(YEAR('Model inputs'!AA63),MONTH('Model inputs'!AA63),1)))="",FALSE,IF(ISERROR(DATE(2027,8,1)=DATE(YEAR('Model inputs'!AA63),MONTH('Model inputs'!AA63),1)),DATE(2027,8,1)=DATE(YEAR('Model inputs'!AA63),MONTH('Model inputs'!AA63),1),IF(DATE(YEAR('Model inputs'!AA63),MONTH('Model inputs'!AA63),1)="","",DATE(2027,8,1)=DATE(YEAR('Model inputs'!AA63),MONTH('Model inputs'!AA63),1)))),IF('Model inputs'!Z11="","",'Model inputs'!Z11),IF('Model inputs'!I6="","",'Model inputs'!I6)) -> 23814 | K15: =IF(IF(IF(ISERROR(DATE(2027,9,1)=DATE(YEAR('Model inputs'!AA63),MONTH('Model inputs'!AA63),1)),DATE(2027,9,1)=DATE(YEAR('Model inputs'!AA63),MONTH('Model inputs'!AA63),1),IF(DATE(YEAR('Model inputs'!AA63),MONTH('Model inputs'!AA63),1)="","",DATE(2027,9,1)=DATE(YEAR('Model inputs'!AA63),MONTH('Model inputs'!AA63),1)))="",FALSE,IF(ISERROR(DATE(2027,9,1)=DATE(YEAR('Model inputs'!AA63),MONTH('Model inputs'!AA63),1)),DATE(2027,9,1)=DATE(YEAR('Model inputs'!AA63),MONTH('Model inputs'!AA63),1),IF(DATE(YEAR('Model inputs'!AA63),MONTH('Model inputs'!AA63),1)="","",DATE(2027,9,1)=DATE(YEAR('Model inputs'!AA63),MONTH('Model inputs'!AA63),1)))),IF('Model inputs'!Z11="","",'Model inputs'!Z11),IF('Model inputs'!J6="","",'Model inputs'!J6)) -> 25936 | L15: =IF(IF(IF(ISERROR(DATE(2027,10,1)=DATE(YEAR('Model inputs'!AA63),MONTH('Model inputs'!AA63),1)),DATE(2027,10,1)=DATE(YEAR('Model inputs'!AA63),MONTH('Model inputs'!AA63),1),IF(DATE(YEAR('Model inputs'!AA63),MONTH('Model inputs'!AA63),1)="","",DATE(2027,10,1)=DATE(YEAR('Model inputs'!AA63),MONTH('Model inputs'!AA63),1)))="",FALSE,IF(ISERROR(DATE(2027,10,1)=DATE(YEAR('Model inputs'!AA63),MONTH('Model inputs'!AA63),1)),DATE(2027,10,1)=DATE(YEAR('Model inputs'!AA63),MONTH('Model inputs'!AA63),1),IF(DATE(YEAR('Model inputs'!AA63),MONTH('Model inputs'!AA63),1)="","",DATE(2027,10,1)=DATE(YEAR('Model inputs'!AA63),MONTH('Model inputs'!AA63),1)))),IF('Model inputs'!Z11="","",'Model inputs'!Z11),IF('Model inputs'!K6="","",'Model inputs'!K6)) -> 28196 | M15: =IF(IF(IF(ISERROR(DATE(2027,11,1)=DATE(YEAR('Model inputs'!AA63),MONTH('Model inputs'!AA63),1)),DATE(2027,11,1)=DATE(YEAR('Model inputs'!AA63),MONTH('Model inputs'!AA63),1),IF(DATE(YEAR('Model inputs'!AA63),MONTH('Model inputs'!AA63),1)="","",DATE(2027,11,1)=DATE(YEAR('Model inputs'!AA63),MONTH('Model inputs'!AA63),1)))="",FALSE,IF(ISERROR(DATE(2027,11,1)=DATE(YEAR('Model inputs'!AA63),MONTH('Model inputs'!AA63),1)),DATE(2027,11,1)=DATE(YEAR('Model inputs'!AA63),MONTH('Model inputs'!AA63),1),IF(DATE(YEAR('Model inputs'!AA63),MONTH('Model inputs'!AA63),1)="","",DATE(2027,11,1)=DATE(YEAR('Model inputs'!AA63),MONTH('Model inputs'!AA63),1)))),IF('Model inputs'!Z11="","",'Model inputs'!Z11),IF('Model inputs'!L6="","",'Model inputs'!L6)) -> 30456 | N15: =IF(IF(IF(ISERROR(DATE(2027,12,1)=DATE(YEAR('Model inputs'!AA63),MONTH('Model inputs'!AA63),1)),DATE(2027,12,1)=DATE(YEAR('Model inputs'!AA63),MONTH('Model inputs'!AA63),1),IF(DATE(YEAR('Model inputs'!AA63),MONTH('Model inputs'!AA63),1)="","",DATE(2027,12,1)=DATE(YEAR('Model inputs'!AA63),MONTH('Model inputs'!AA63),1)))="",FALSE,IF(ISERROR(DATE(2027,12,1)=DATE(YEAR('Model inputs'!AA63),MONTH('Model inputs'!AA63),1)),DATE(2027,12,1)=DATE(YEAR('Model inputs'!AA63),MONTH('Model inputs'!AA63),1),IF(DATE(YEAR('Model inputs'!AA63),MONTH('Model inputs'!AA63),1)="","",DATE(2027,12,1)=DATE(YEAR('Model inputs'!AA63),MONTH('Model inputs'!AA63),1)))),IF('Model inputs'!Z11="","",'Model inputs'!Z11),IF('Model inputs'!M6="","",'Model inputs'!M6)) -> 32716 | W15: 0 | X15: =IF(IF(IF(ISERROR(DATE(2026,10,1)=DATE(YEAR('Model inputs'!AA63),MONTH('Model inputs'!AA63),1)),DATE(2026,10,1)=DATE(YEAR('Model inputs'!AA63),MONTH('Model inputs'!AA63),1),IF(DATE(YEAR('Model inputs'!AA63),MONTH('Model inputs'!AA63),1)="","",DATE(2026,10,1)=DATE(YEAR('Model inputs'!AA63),MONTH('Model inputs'!AA63),1)))="",FALSE,IF(ISERROR(DATE(2026,10,1)=DATE(YEAR('Model inputs'!AA63),MONTH('Model inputs'!AA63),1)),DATE(2026,10,1)=DATE(YEAR('Model inputs'!AA63),MONTH('Model inputs'!AA63),1),IF(DATE(YEAR('Model inputs'!AA63),MONTH('Model inputs'!AA63),1)="","",DATE(2026,10,1)=DATE(YEAR('Model inputs'!AA63),MONTH('Model inputs'!AA63),1)))),IF('Model inputs'!Z11="","",'Model inputs'!Z11),IF('Model inputs'!W7="","",'Model inputs'!W7)) -> 0 | Y15: =IF(IF(IF(ISERROR(DATE(2026,11,1)=DATE(YEAR('Model inputs'!AA63),MONTH('Model inputs'!AA63),1)),DATE(2026,11,1)=DATE(YEAR('Model inputs'!AA63),MONTH('Model inputs'!AA63),1),IF(DATE(YEAR('Model inputs'!AA63),MONTH('Model inputs'!AA63),1)="","",DATE(2026,11,1)=DATE(YEAR('Model inputs'!AA63),MONTH('Model inputs'!AA63),1)))="",FALSE,IF(ISERROR(DATE(2026,11,1)=DATE(YEAR('Model inputs'!AA63),MONTH('Model inputs'!AA63),1)),DATE(2026,11,1)=DATE(YEAR('Model inputs'!AA63),MONTH('Model inputs'!AA63),1),IF(DATE(YEAR('Model inputs'!AA63),MONTH('Model inputs'!AA63),1)="","",DATE(2026,11,1)=DATE(YEAR('Model inputs'!AA63),MONTH('Model inputs'!AA63),1)))),IF('Model inputs'!Z11="","",'Model inputs'!Z11),IF('Model inputs'!X7="","",'Model inputs'!X7)) -> -500
A16: Clientes no fim do mês — projeção Base · DisruptRadar — Projeção mensal · Projeção mensal Base — clientes, resultado e caixa · Base | B16: 0 | C16: =1 -> 1 | D16: =4 -> 4 | E16: =9 -> 9 | F16: =14 -> 14 | G16: =20 -> 20 | H16: =26 -> 26 | I16: =32 -> 32 | J16: =38 -> 38 | K16: =40 -> 40 | L16: =40 -> 40 | M16: =40 -> 40 | N16: =40 -> 40 | O16: 0 | P16: 0 | Q16: 0 | R16: 0 | S16: 0 | T16: 0 | U16: 0 | V16: 0 | W16: 0 | X16: 0 | Y16: 0
A17: Clientes no fim do mês — projeção Base · DisruptRadar — Projeção mensal · Sensibilidade completa — preço Pro e fixos · Teste Pro 109 € — fixos 500 €/mês | B17: 0 | C17: =1 -> 1 | D17: =4 -> 4 | E17: =9 -> 9 | F17: =14 -> 14 | G17: =20 -> 20 | H17: =26 -> 26 | I17: =32 -> 32 | J17: =38 -> 38 | K17: =40 -> 40 | L17: =40 -> 40 | M17: =40 -> 40 | N17: =40 -> 40 | O17: 0 | P17: 0 | Q17: 0 | R17: 0 | S17: 0 | T17: 0 | U17: 0 | V17: 0 | W17: 0 | X17: 0 | Y17: 0
A18: Clientes no fim do mês — projeção Base · Base — fixos 400 €/mês | B18: 0 | C18: =1 -> 1 | D18: =4 -> 4 | E18: =9 -> 9 | F18: =14 -> 14 | G18: =20 -> 20 | H18: =26 -> 26 | I18: =32 -> 32 | J18: =38 -> 38 | K18: =40 -> 40 | L18: =40 -> 40 | M18: =40 -> 40 | N18: =40 -> 40 | O18: 0 | P18: 0 | Q18: 0 | R18: 0 | S18: 0 | T18: 0 | U18: 0 | V18: 0 | W18: 0 | X18: 0 | Y18: 0
A19: Clientes no fim do mês — projeção Base · Teste Pro 109 € — fixos 400 €/mês | B19: 0 | C19: =1 -> 1 | D19: =4 -> 4 | E19: =9 -> 9 | F19: =14 -> 14 | G19: =20 -> 20 | H19: =26 -> 26 | I19: =32 -> 32 | J19: =38 -> 38 | K19: =40 -> 40 | L19: =40 -> 40 | M19: =40 -> 40 | N19: =40 -> 40 | O19: 0 | P19: 0 | Q19: 0 | R19: 0 | S19: 0 | T19: 0 | U19: 0 | V19: 0 | W19: 0 | X19: 0 | Y19: 0
A20: Clientes no fim do mês — projeção Base · Base — fixos 300 €/mês | B20: 0 | C20: =1 -> 1 | D20: =4 -> 4 | E20: =9 -> 9 | F20: =14 -> 14 | G20: =20 -> 20 | H20: =26 -> 26 | I20: =32 -> 32 | J20: =38 -> 38 | K20: =40 -> 40 | L20: =40 -> 40 | M20: =40 -> 40 | N20: =40 -> 40 | O20: 0 | P20: 0 | Q20: 0 | R20: 0 | S20: 0 | T20: 0 | U20: 0 | V20: 0 | W20: 0 | X20: 0 | Y20: 0
A21: Clientes no fim do mês — projeção Base · DisruptRadar — Projeção mensal · Sensibilidade completa — preço Pro e fixos · Teste Pro 119 € — fixos 500 €/mês | B21: 0 | C21: =1 -> 1 | D21: =4 -> 4 | E21: =9 -> 9 | F21: =14 -> 14 | G21: =20 -> 20 | H21: =26 -> 26 | I21: =32 -> 32 | J21: =38 -> 38 | K21: =40 -> 40 | L21: =40 -> 40 | M21: =40 -> 40 | N21: =40 -> 40 | O21: 0 | P21: 0 | Q21: 0 | R21: 0 | S21: 0 | T21: 0 | U21: 0 | V21: 0 | W21: 0 | X21: 0 | Y21: 0
A22: Clientes no fim do mês — projeção Base · Teste Pro 119 € — fixos 400 €/mês | B22: 0 | C22: =1 -> 1 | D22: =4 -> 4 | E22: =9 -> 9 | F22: =14 -> 14 | G22: =20 -> 20 | H22: =26 -> 26 | I22: =32 -> 32 | J22: =38 -> 38 | K22: =40 -> 40 | L22: =40 -> 40 | M22: =40 -> 40 | N22: =40 -> 40 | O22: 0 | P22: 0 | Q22: 0 | R22: 0 | S22: 0 | T22: 0 | U22: 0 | V22: 0 | W22: 0 | X22: 0 | Y22: 0
A23: Clientes no fim do mês — projeção Base · Teste Pro 109 € — fixos 300 €/mês | B23: 0 | C23: =1 -> 1 | D23: =4 -> 4 | E23: =9 -> 9 | F23: =14 -> 14 | G23: =20 -> 20 | H23: =26 -> 26 | I23: =32 -> 32 | J23: =38 -> 38 | K23: =40 -> 40 | L23: =40 -> 40 | M23: =40 -> 40 | N23: =40 -> 40 | O23: 0 | P23: 0 | Q23: 0 | R23: 0 | S23: 0 | T23: 0 | U23: 0 | V23: 0 | W23: 0 | X23: 0 | Y23: 0
A24: Clientes no fim do mês — projeção Base · Teste Pro 119 € — fixos 300 €/mês | B24: 0 | C24: =1 -> 1 | D24: =4 -> 4 | E24: =9 -> 9 | F24: =14 -> 14 | G24: =20 -> 20 | H24: =26 -> 26 | I24: =32 -> 32 | J24: =38 -> 38 | K24: =40 -> 40 | L24: =40 -> 40 | M24: =40 -> 40 | N24: =40 -> 40 | O24: 0 | P24: 0 | Q24: 0 | R24: 0 | S24: 0 | T24: 0 | U24: 0 | V24: 0 | W24: 0 | X24: 0 | Y24: 0
A25: Custo variável por domínio por mês — estimativa (EUR) · DisruptRadar Business Plan · Premissas DisruptRadar — Ano 1 · Base | Z25: =3 -> 3
A26: Custo variável por domínio por mês — estimativa (EUR) · DisruptRadar — Projeção mensal · Projeção mensal Base — clientes, resultado e caixa · Base | AA26: =3 -> 3
A27: Custo variável por domínio por mês — estimativa (EUR) · Teste Pro 109 € — fixos 500 €/mês | Z27: =3 -> 3
A28: Custo variável por domínio por mês — estimativa (EUR) · Pessimista | Z28: =3 -> 3
A29: Custo variável por domínio por mês — estimativa (EUR) · Otimista | Z29: =3 -> 3
A30: Custo variável por domínio por mês — estimativa (EUR) · Teste Pro 119 € — fixos 500 €/mês | Z30: =3 -> 3
A31: Custos totais mensais — projeção Base (EUR) · DisruptRadar — Projeção mensal · Projeção mensal Base — clientes, resultado e caixa · Base | B31: ='Model inputs'!B51+'Model inputs'!B62 -> 500 | C31: ='Model inputs'!C51+'Model inputs'!C62 -> 530 | D31: ='Model inputs'!D51+'Model inputs'!D62 -> 620 | E31: ='Model inputs'!E51+'Model inputs'!E62 -> 770 | F31: ='Model inputs'!F51+'Model inputs'!F62 -> 920 | G31: ='Model inputs'!G51+'Model inputs'!G62 -> 1100 | H31: ='Model inputs'!H51+'Model inputs'!H62 -> 1280 | I31: ='Model inputs'!I51+'Model inputs'!I62 -> 1460 | ... N31: ='Model inputs'!N51+'Model inputs'!N62 -> 1700 | O31: 0 | P31: 0 | Q31: 0 | R31: 0 | S31: 0 | T31: 0 | U31: 0 | V31: 0 | W31: 0 | X31: ='Model inputs'!X51+'Model inputs'!X62 -> 500 | Y31: ='Model inputs'!Y51+'Model inputs'!Y62 -> 500
A32: Custos totais mensais — projeção Base (EUR) · Base — fixos 400 €/mês | B32: ='Model inputs'!B53+'Model inputs'!B103 -> 400 | C32: ='Model inputs'!C53+'Model inputs'!C103 -> 430 | D32: ='Model inputs'!D53+'Model inputs'!D103 -> 520 | E32: ='Model inputs'!E53+'Model inputs'!E103 -> 670 | F32: ='Model inputs'!F53+'Model inputs'!F103 -> 820 | G32: ='Model inputs'!G53+'Model inputs'!G103 -> 1000 | H32: ='Model inputs'!H53+'Model inputs'!H103 -> 1180 | I32: ='Model inputs'!I53+'Model inputs'!I103 -> 1360 | ... N32: ='Model inputs'!N53+'Model inputs'!N103 -> 1600 | O32: 0 | P32: 0 | Q32: 0 | R32: 0 | S32: 0 | T32: 0 | U32: 0 | V32: 0 | W32: 0 | X32: ='Model inputs'!X53+'Model inputs'!X103 -> 400 | Y32: ='Model inputs'!Y53+'Model inputs'!Y103 -> 400
A33: Custos totais mensais — projeção Base (EUR) · Base — fixos 300 €/mês | B33: ='Model inputs'!B55+'Model inputs'!B104 -> 300 | C33: ='Model inputs'!C55+'Model inputs'!C104 -> 330 | D33: ='Model inputs'!D55+'Model inputs'!D104 -> 420 | E33: ='Model inputs'!E55+'Model inputs'!E104 -> 570 | F33: ='Model inputs'!F55+'Model inputs'!F104 -> 720 | G33: ='Model inputs'!G55+'Model inputs'!G104 -> 900 | H33: ='Model inputs'!H55+'Model inputs'!H104 -> 1080 | I33: ='Model inputs'!I55+'Model inputs'!I104 -> 1260 | ... N33: ='Model inputs'!N55+'Model inputs'!N104 -> 1500 | O33: 0 | P33: 0 | Q33: 0 | R33: 0 | S33: 0 | T33: 0 | U33: 0 | V33: 0 | W33: 0 | X33: ='Model inputs'!X55+'Model inputs'!X104 -> 300 | Y33: ='Model inputs'!Y55+'Model inputs'!Y104 -> 300
A34: Custos totais mensais — projeção Base (EUR) · Base — fixos 500 €/mês | B34: ='Model inputs'!B102+'Model inputs'!B105 -> 500 | C34: ='Model inputs'!C102+'Model inputs'!C105 -> 530 | D34: ='Model inputs'!D102+'Model inputs'!D105 -> 620 | E34: ='Model inputs'!E102+'Model inputs'!E105 -> 770 | F34: ='Model inputs'!F102+'Model inputs'!F105 -> 920 | G34: ='Model inputs'!G102+'Model inputs'!G105 -> 1100 | H34: ='Model inputs'!H102+'Model inputs'!H105 -> 1280 | I34: ='Model inputs'!I102+'Model inputs'!I105 -> 1460 | ... N34: ='Model inputs'!N102+'Model inputs'!N105 -> 1700 | O34: 0 | P34: 0 | Q34: 0 | R34: 0 | S34: 0 | T34: 0 | U34: 0 | V34: 0 | W34: 0 | X34: ='Model inputs'!X102+'Model inputs'!X105 -> 500 | Y34: ='Model inputs'!Y102+'Model inputs'!Y105 -> 500
A35: Domínios médios por cliente Pro — hipótese · DisruptRadar Business Plan · Premissas DisruptRadar — Ano 1 · Base | Z35: =10 -> 10
A36: Domínios médios por cliente Pro — hipótese · DisruptRadar — Projeção mensal · Projeção mensal Base — clientes, resultado e caixa · Base | AA36: =10 -> 10
A37: Domínios médios por cliente Pro — hipótese · Teste Pro 109 € — fixos 500 €/mês | Z37: =10 -> 10
A38: Domínios médios por cliente Pro — hipótese · Pessimista | Z38: =10 -> 10
A39: Domínios médios por cliente Pro — hipótese · Otimista | Z39: =10 -> 10
A40: Domínios médios por cliente Pro — hipótese · Teste Pro 119 € — fixos 500 €/mês | Z40: =10 -> 10
A41: EBITDA mensal — projeção Base (EUR) · DisruptRadar — Projeção mensal · Projeção mensal Base — clientes, resultado e caixa · Base | B41: ='Model inputs'!B67-'Model inputs'!B31 -> -500 | C41: ='Model inputs'!C67-'Model inputs'!C31 -> -431 | D41: ='Model inputs'!D67-'Model inputs'!D31 -> -224 | E41: ='Model inputs'!E67-'Model inputs'!E31 -> 121 | F41: ='Model inputs'!F67-'Model inputs'!F31 -> 466 | G41: ='Model inputs'!G67-'Model inputs'!G31 -> 880 | H41: ='Model inputs'!H67-'Model inputs'!H31 -> 1294 | I41: ='Model inputs'!I67-'Model inputs'!I31 -> 1708 | ... N41: ='Model inputs'!N67-'Model inputs'!N31 -> 2260 | O41: 0 | P41: 0 | Q41: 0 | R41: 0 | S41: 0 | T41: 0 | U41: 0 | V41: 0 | W41: 0 | X41: ='Model inputs'!X67-'Model inputs'!X31 -> -500 | Y41: ='Model inputs'!Y67-'Model inputs'!Y31 -> -500
A42: EBITDA mensal — projeção Base (EUR) · Teste Pro 109 € — fixos 500 €/mês | B42: ='Model inputs'!B68-'Model inputs'!B88 -> -500 | C42: ='Model inputs'!C68-'Model inputs'!C88 -> -421 | D42: ='Model inputs'!D68-'Model inputs'!D88 -> -184 | E42: ='Model inputs'!E68-'Model inputs'!E88 -> 211 | F42: ='Model inputs'!F68-'Model inputs'!F88 -> 606 | G42: ='Model inputs'!G68-'Model inputs'!G88 -> 1080 | H42: ='Model inputs'!H68-'Model inputs'!H88 -> 1554 | I42: ='Model inputs'!I68-'Model inputs'!I88 -> 2028 | ... N42: ='Model inputs'!N68-'Model inputs'!N88 -> 2660 | O42: 0 | P42: 0 | Q42: 0 | R42: 0 | S42: 0 | T42: 0 | U42: 0 | V42: 0 | W42: 0 | X42: ='Model inputs'!X68-'Model inputs'!X88 -> -500 | Y42: ='Model inputs'!Y68-'Model inputs'!Y88 -> -500
A43: EBITDA mensal — projeção Base (EUR) · Base — fixos 400 €/mês | B43: ='Model inputs'!B69-'Model inputs'!B32 -> -400 | C43: ='Model inputs'!C69-'Model inputs'!C32 -> -331 | D43: ='Model inputs'!D69-'Model inputs'!D32 -> -124 | E43: ='Model inputs'!E69-'Model inputs'!E32 -> 221 | F43: ='Model inputs'!F69-'Model inputs'!F32 -> 566 | G43: ='Model inputs'!G69-'Model inputs'!G32 -> 980 | H43: ='Model inputs'!H69-'Model inputs'!H32 -> 1394 | I43: ='Model inputs'!I69-'Model inputs'!I32 -> 1808 | ... N43: ='Model inputs'!N69-'Model inputs'!N32 -> 2360 | O43: 0 | P43: 0 | Q43: 0 | R43: 0 | S43: 0 | T43: 0 | U43: 0 | V43: 0 | W43: 0 | X43: ='Model inputs'!X69-'Model inputs'!X32 -> -400 | Y43: ='Model inputs'!Y69-'Model inputs'!Y32 -> -400
A44: EBITDA mensal — projeção Base (EUR) · Teste Pro 109 € — fixos 400 €/mês | B44: ='Model inputs'!B70-'Model inputs'!B89 -> -400 | C44: ='Model inputs'!C70-'Model inputs'!C89 -> -321 | D44: ='Model inputs'!D70-'Model inputs'!D89 -> -84 | E44: ='Model inputs'!E70-'Model inputs'!E89 -> 311 | F44: ='Model inputs'!F70-'Model inputs'!F89 -> 706 | G44: ='Model inputs'!G70-'Model inputs'!G89 -> 1180 | H44: ='Model inputs'!H70-'Model inputs'!H89 -> 1654 | I44: ='Model inputs'!I70-'Model inputs'!I89 -> 2128 | ... N44: ='Model inputs'!N70-'Model inputs'!N89 -> 2760 | O44: 0 | P44: 0 | Q44: 0 | R44: 0 | S44: 0 | T44: 0 | U44: 0 | V44: 0 | W44: 0 | X44: ='Model inputs'!X70-'Model inputs'!X89 -> -400 | Y44: ='Model inputs'!Y70-'Model inputs'!Y89 -> -400
A45: EBITDA mensal — projeção Base (EUR) · Base — fixos 300 €/mês | B45: ='Model inputs'!B71-'Model inputs'!B33 -> -300 | C45: ='Model inputs'!C71-'Model inputs'!C33 -> -231 | D45: ='Model inputs'!D71-'Model inputs'!D33 -> -24 | E45: ='Model inputs'!E71-'Model inputs'!E33 -> 321 | F45: ='Model inputs'!F71-'Model inputs'!F33 -> 666 | G45: ='Model inputs'!G71-'Model inputs'!G33 -> 1080 | H45: ='Model inputs'!H71-'Model inputs'!H33 -> 1494 | I45: ='Model inputs'!I71-'Model inputs'!I33 -> 1908 | ... N45: ='Model inputs'!N71-'Model inputs'!N33 -> 2460 | O45: 0 | P45: 0 | Q45: 0 | R45: 0 | S45: 0 | T45: 0 | U45: 0 | V45: 0 | W45: 0 | X45: ='Model inputs'!X71-'Model inputs'!X33 -> -300 | Y45: ='Model inputs'!Y71-'Model inputs'!Y33 -> -300
A46: EBITDA mensal — projeção Base (EUR) · Teste Pro 119 € — fixos 500 €/mês | B46: ='Model inputs'!B72-'Model inputs'!B90 -> -500 | C46: ='Model inputs'!C72-'Model inputs'!C90 -> -411 | D46: ='Model inputs'!D72-'Model inputs'!D90 -> -144 | E46: ='Model inputs'!E72-'Model inputs'!E90 -> 301 | F46: ='Model inputs'!F72-'Model inputs'!F90 -> 746 | G46: ='Model inputs'!G72-'Model inputs'!G90 -> 1280 | H46: ='Model inputs'!H72-'Model inputs'!H90 -> 1814 | I46: ='Model inputs'!I72-'Model inputs'!I90 -> 2348 | ... N46: ='Model inputs'!N72-'Model inputs'!N90 -> 3060 | O46: 0 | P46: 0 | Q46: 0 | R46: 0 | S46: 0 | T46: 0 | U46: 0 | V46: 0 | W46: 0 | X46: ='Model inputs'!X72-'Model inputs'!X90 -> -500 | Y46: ='Model inputs'!Y72-'Model inputs'!Y90 -> -500
A47: EBITDA mensal — projeção Base (EUR) · Teste Pro 119 € — fixos 400 €/mês | B47: ='Model inputs'!B73-'Model inputs'!B91 -> -400 | C47: ='Model inputs'!C73-'Model inputs'!C91 -> -311 | D47: ='Model inputs'!D73-'Model inputs'!D91 -> -44 | E47: ='Model inputs'!E73-'Model inputs'!E91 -> 401 | F47: ='Model inputs'!F73-'Model inputs'!F91 -> 846 | G47: ='Model inputs'!G73-'Model inputs'!G91 -> 1380 | H47: ='Model inputs'!H73-'Model inputs'!H91 -> 1914 | I47: ='Model inputs'!I73-'Model inputs'!I91 -> 2448 | ... N47: ='Model inputs'!N73-'Model inputs'!N91 -> 3160 | O47: 0 | P47: 0 | Q47: 0 | R47: 0 | S47: 0 | T47: 0 | U47: 0 | V47: 0 | W47: 0 | X47: ='Model inputs'!X73-'Model inputs'!X91 -> -400 | Y47: ='Model inputs'!Y73-'Model inputs'!Y91 -> -400
A48: EBITDA mensal — projeção Base (EUR) · Base — fixos 500 €/mês | B48: ='Model inputs'!B106-'Model inputs'!B34 -> -500 | C48: ='Model inputs'!C106-'Model inputs'!C34 -> -431 | D48: ='Model inputs'!D106-'Model inputs'!D34 -> -224 | E48: ='Model inputs'!E106-'Model inputs'!E34 -> 121 | F48: ='Model inputs'!F106-'Model inputs'!F34 -> 466 | G48: ='Model inputs'!G106-'Model inputs'!G34 -> 880 | H48: ='Model inputs'!H106-'Model inputs'!H34 -> 1294 | I48: ='Model inputs'!I106-'Model inputs'!I34 -> 1708 | ... N48: ='Model inputs'!N106-'Model inputs'!N34 -> 2260 | O48: 0 | P48: 0 | Q48: 0 | R48: 0 | S48: 0 | T48: 0 | U48: 0 | V48: 0 | W48: 0 | X48: ='Model inputs'!X106-'Model inputs'!X34 -> -500 | Y48: ='Model inputs'!Y106-'Model inputs'!Y34 -> -500
A49: EBITDA mensal — projeção Base (EUR) · Teste Pro 109 € — fixos 300 €/mês | B49: ='Model inputs'!B74-'Model inputs'!B92 -> -300 | C49: ='Model inputs'!C74-'Model inputs'!C92 -> -221 | D49: ='Model inputs'!D74-'Model inputs'!D92 -> 16 | E49: ='Model inputs'!E74-'Model inputs'!E92 -> 411 | F49: ='Model inputs'!F74-'Model inputs'!F92 -> 806 | G49: ='Model inputs'!G74-'Model inputs'!G92 -> 1280 | H49: ='Model inputs'!H74-'Model inputs'!H92 -> 1754 | I49: ='Model inputs'!I74-'Model inputs'!I92 -> 2228 | ... N49: ='Model inputs'!N74-'Model inputs'!N92 -> 2860 | O49: 0 | P49: 0 | Q49: 0 | R49: 0 | S49: 0 | T49: 0 | U49: 0 | V49: 0 | W49: 0 | X49: ='Model inputs'!X74-'Model inputs'!X92 -> -300 | Y49: ='Model inputs'!Y74-'Model inputs'!Y92 -> -300
A50: EBITDA mensal — projeção Base (EUR) · Teste Pro 119 € — fixos 300 €/mês | B50: ='Model inputs'!B75-'Model inputs'!B93 -> -300 | C50: ='Model inputs'!C75-'Model inputs'!C93 -> -211 | D50: ='Model inputs'!D75-'Model inputs'!D93 -> 56 | E50: ='Model inputs'!E75-'Model inputs'!E93 -> 501 | F50: ='Model inputs'!F75-'Model inputs'!F93 -> 946 | G50: ='Model inputs'!G75-'Model inputs'!G93 -> 1480 | H50: ='Model inputs'!H75-'Model inputs'!H93 -> 2014 | I50: ='Model inputs'!I75-'Model inputs'!I93 -> 2548 | ... N50: ='Model inputs'!N75-'Model inputs'!N93 -> 3260 | O50: 0 | P50: 0 | Q50: 0 | R50: 0 | S50: 0 | T50: 0 | U50: 0 | V50: 0 | W50: 0 | X50: ='Model inputs'!X75-'Model inputs'!X93 -> -300 | Y50: ='Model inputs'!Y75-'Model inputs'!Y93 -> -300
A51: Entrega mensal — projeção Base (EUR) · DisruptRadar — Projeção mensal · Projeção mensal Base — clientes, resultado e caixa · Base | B51: ='Model inputs'!B16*'Model inputs'!Z35*'Model inputs'!Z25 -> 0 | C51: ='Model inputs'!C16*'Model inputs'!Z35*'Model inputs'!Z25 -> 30 | D51: ='Model inputs'!D16*'Model inputs'!Z35*'Model inputs'!Z25 -> 120 | E51: ='Model inputs'!E16*'Model inputs'!Z35*'Model inputs'!Z25 -> 270 | F51: ='Model inputs'!F16*'Model inputs'!Z35*'Model inputs'!Z25 -> 420 | G51: ='Model inputs'!G16*'Model inputs'!Z35*'Model inputs'!Z25 -> 600 | H51: ='Model inputs'!H16*'Model inputs'!Z35*'Model inputs'!Z25 -> 780 | I51: ='Model inputs'!I16*'Model inputs'!Z35*'Model inputs'!Z25 -> 960 | J51: ='Model inputs'!J16*'Model inputs'!Z35*'Model inputs'!Z25 -> 1140 | K51: ='Model inputs'!K16*'Model inputs'!Z35*'Model inputs'!Z25 -> 1200 | L51: ='Model inputs'!L16*'Model inputs'!Z35*'Model inputs'!Z25 -> 1200 | M51: ='Model inputs'!M16*'Model inputs'!Z35*'Model inputs'!Z25 -> 1200 | N51: ='Model inputs'!N16*'Model inputs'!Z35*'Model inputs'!Z25 -> 1200 | O51: 0 | P51: 0 | Q51: 0 | R51: 0 | S51: 0 | T51: 0 | U51: 0 | V51: 0 | W51: 0 | X51: ='Model inputs'!X16*'Model inputs'!Z35*'Model inputs'!Z25 -> 0 | Y51: ='Model inputs'!Y16*'Model inputs'!Z35*'Model inputs'!Z25 -> 0
A52: Entrega mensal — projeção Base (EUR) · Teste Pro 109 € — fixos 500 €/mês | B52: ='Model inputs'!B17*'Model inputs'!Z37*'Model inputs'!Z27 -> 0 | C52: ='Model inputs'!C17*'Model inputs'!Z37*'Model inputs'!Z27 -> 30 | D52: ='Model inputs'!D17*'Model inputs'!Z37*'Model inputs'!Z27 -> 120 | E52: ='Model inputs'!E17*'Model inputs'!Z37*'Model inputs'!Z27 -> 270 | F52: ='Model inputs'!F17*'Model inputs'!Z37*'Model inputs'!Z27 -> 420 | G52: ='Model inputs'!G17*'Model inputs'!Z37*'Model inputs'!Z27 -> 600 | H52: ='Model inputs'!H17*'Model inputs'!Z37*'Model inputs'!Z27 -> 780 | I52: ='Model inputs'!I17*'Model inputs'!Z37*'Model inputs'!Z27 -> 960 | J52: ='Model inputs'!J17*'Model inputs'!Z37*'Model inputs'!Z27 -> 1140 | K52: ='Model inputs'!K17*'Model inputs'!Z37*'Model inputs'!Z27 -> 1200 | L52: ='Model inputs'!L17*'Model inputs'!Z37*'Model inputs'!Z27 -> 1200 | M52: ='Model inputs'!M17*'Model inputs'!Z37*'Model inputs'!Z27 -> 1200 | N52: ='Model inputs'!N17*'Model inputs'!Z37*'Model inputs'!Z27 -> 1200 | O52: 0 | P52: 0 | Q52: 0 | R52: 0 | S52: 0 | T52: 0 | U52: 0 | V52: 0 | W52: 0 | X52: ='Model inputs'!X17*'Model inputs'!Z37*'Model inputs'!Z27 -> 0 | Y52: ='Model inputs'!Y17*'Model inputs'!Z37*'Model inputs'!Z27 -> 0
A53: Entrega mensal — projeção Base (EUR) · Base — fixos 400 €/mês | B53: ='Model inputs'!B18*'Model inputs'!AA95*'Model inputs'!AA81 -> 0 | C53: ='Model inputs'!C18*'Model inputs'!AA95*'Model inputs'!AA81 -> 30 | D53: ='Model inputs'!D18*'Model inputs'!AA95*'Model inputs'!AA81 -> 120 | E53: ='Model inputs'!E18*'Model inputs'!AA95*'Model inputs'!AA81 -> 270 | F53: ='Model inputs'!F18*'Model inputs'!AA95*'Model inputs'!AA81 -> 420 | G53: ='Model inputs'!G18*'Model inputs'!AA95*'Model inputs'!AA81 -> 600 | H53: ='Model inputs'!H18*'Model inputs'!AA95*'Model inputs'!AA81 -> 780 | I53: ='Model inputs'!I18*'Model inputs'!AA95*'Model inputs'!AA81 -> 960 | J53: ='Model inputs'!J18*'Model inputs'!AA95*'Model inputs'!AA81 -> 1140 | K53: ='Model inputs'!K18*'Model inputs'!AA95*'Model inputs'!AA81 -> 1200 | L53: ='Model inputs'!L18*'Model inputs'!AA95*'Model inputs'!AA81 -> 1200 | M53: ='Model inputs'!M18*'Model inputs'!AA95*'Model inputs'!AA81 -> 1200 | N53: ='Model inputs'!N18*'Model inputs'!AA95*'Model inputs'!AA81 -> 1200 | O53: 0 | P53: 0 | Q53: 0 | R53: 0 | S53: 0 | T53: 0 | U53: 0 | V53: 0 | W53: 0 | X53: ='Model inputs'!X18*'Model inputs'!AA95*'Model inputs'!AA81 -> 0 | Y53: ='Model inputs'!Y18*'Model inputs'!AA95*'Model inputs'!AA81 -> 0
A54: Entrega mensal — projeção Base (EUR) · Teste Pro 109 € — fixos 400 €/mês | B54: ='Model inputs'!B19*'Model inputs'!AA96*'Model inputs'!AA82 -> 0 | C54: ='Model inputs'!C19*'Model inputs'!AA96*'Model inputs'!AA82 -> 30 | D54: ='Model inputs'!D19*'Model inputs'!AA96*'Model inputs'!AA82 -> 120 | E54: ='Model inputs'!E19*'Model inputs'!AA96*'Model inputs'!AA82 -> 270 | F54: ='Model inputs'!F19*'Model inputs'!AA96*'Model inputs'!AA82 -> 420 | G54: ='Model inputs'!G19*'Model inputs'!AA96*'Model inputs'!AA82 -> 600 | H54: ='Model inputs'!H19*'Model inputs'!AA96*'Model inputs'!AA82 -> 780 | I54: ='Model inputs'!I19*'Model inputs'!AA96*'Model inputs'!AA82 -> 960 | J54: ='Model inputs'!J19*'Model inputs'!AA96*'Model inputs'!AA82 -> 1140 | K54: ='Model inputs'!K19*'Model inputs'!AA96*'Model inputs'!AA82 -> 1200 | L54: ='Model inputs'!L19*'Model inputs'!AA96*'Model inputs'!AA82 -> 1200 | M54: ='Model inputs'!M19*'Model inputs'!AA96*'Model inputs'!AA82 -> 1200 | N54: ='Model inputs'!N19*'Model inputs'!AA96*'Model inputs'!AA82 -> 1200 | O54: 0 | P54: 0 | Q54: 0 | R54: 0 | S54: 0 | T54: 0 | U54: 0 | V54: 0 | W54: 0 | X54: ='Model inputs'!X19*'Model inputs'!AA96*'Model inputs'!AA82 -> 0 | Y54: ='Model inputs'!Y19*'Model inputs'!AA96*'Model inputs'!AA82 -> 0
A55: Entrega mensal — projeção Base (EUR) · Base — fixos 300 €/mês | B55: ='Model inputs'!B20*'Model inputs'!AA97*'Model inputs'!AA83 -> 0 | C55: ='Model inputs'!C20*'Model inputs'!AA97*'Model inputs'!AA83 -> 30 | D55: ='Model inputs'!D20*'Model inputs'!AA97*'Model inputs'!AA83 -> 120 | E55: ='Model inputs'!E20*'Model inputs'!AA97*'Model inputs'!AA83 -> 270 | F55: ='Model inputs'!F20*'Model inputs'!AA97*'Model inputs'!AA83 -> 420 | G55: ='Model inputs'!G20*'Model inputs'!AA97*'Model inputs'!AA83 -> 600 | H55: ='Model inputs'!H20*'Model inputs'!AA97*'Model inputs'!AA83 -> 780 | I55: ='Model inputs'!I20*'Model inputs'!AA97*'Model inputs'!AA83 -> 960 | J55: ='Model inputs'!J20*'Model inputs'!AA97*'Model inputs'!AA83 -> 1140 | K55: ='Model inputs'!K20*'Model inputs'!AA97*'Model inputs'!AA83 -> 1200 | L55: ='Model inputs'!L20*'Model inputs'!AA97*'Model inputs'!AA83 -> 1200 | M55: ='Model inputs'!M20*'Model inputs'!AA97*'Model inputs'!AA83 -> 1200 | N55: ='Model inputs'!N20*'Model inputs'!AA97*'Model inputs'!AA83 -> 1200 | O55: 0 | P55: 0 | Q55: 0 | R55: 0 | S55: 0 | T55: 0 | U55: 0 | V55: 0 | W55: 0 | X55: ='Model inputs'!X20*'Model inputs'!AA97*'Model inputs'!AA83 -> 0 | Y55: ='Model inputs'!Y20*'Model inputs'!AA97*'Model inputs'!AA83 -> 0
A56: Entrega mensal — projeção Base (EUR) · Teste Pro 119 € — fixos 500 €/mês | B56: ='Model inputs'!B21*'Model inputs'!Z40*'Model inputs'!Z30 -> 0 | C56: ='Model inputs'!C21*'Model inputs'!Z40*'Model inputs'!Z30 -> 30 | D56: ='Model inputs'!D21*'Model inputs'!Z40*'Model inputs'!Z30 -> 120 | E56: ='Model inputs'!E21*'Model inputs'!Z40*'Model inputs'!Z30 -> 270 | F56: ='Model inputs'!F21*'Model inputs'!Z40*'Model inputs'!Z30 -> 420 | G56: ='Model inputs'!G21*'Model inputs'!Z40*'Model inputs'!Z30 -> 600 | H56: ='Model inputs'!H21*'Model inputs'!Z40*'Model inputs'!Z30 -> 780 | I56: ='Model inputs'!I21*'Model inputs'!Z40*'Model inputs'!Z30 -> 960 | J56: ='Model inputs'!J21*'Model inputs'!Z40*'Model inputs'!Z30 -> 1140 | K56: ='Model inputs'!K21*'Model inputs'!Z40*'Model inputs'!Z30 -> 1200 | L56: ='Model inputs'!L21*'Model inputs'!Z40*'Model inputs'!Z30 -> 1200 | M56: ='Model inputs'!M21*'Model inputs'!Z40*'Model inputs'!Z30 -> 1200 | N56: ='Model inputs'!N21*'Model inputs'!Z40*'Model inputs'!Z30 -> 1200 | O56: 0 | P56: 0 | Q56: 0 | R56: 0 | S56: 0 | T56: 0 | U56: 0 | V56: 0 | W56: 0 | X56: ='Model inputs'!X21*'Model inputs'!Z40*'Model inputs'!Z30 -> 0 | Y56: ='Model inputs'!Y21*'Model inputs'!Z40*'Model inputs'!Z30 -> 0
A57: Entrega mensal — projeção Base (EUR) · Teste Pro 119 € — fixos 400 €/mês | B57: ='Model inputs'!B22*'Model inputs'!AA99*'Model inputs'!AA85 -> 0 | C57: ='Model inputs'!C22*'Model inputs'!AA99*'Model inputs'!AA85 -> 30 | D57: ='Model inputs'!D22*'Model inputs'!AA99*'Model inputs'!AA85 -> 120 | E57: ='Model inputs'!E22*'Model inputs'!AA99*'Model inputs'!AA85 -> 270 | F57: ='Model inputs'!F22*'Model inputs'!AA99*'Model inputs'!AA85 -> 420 | G57: ='Model inputs'!G22*'Model inputs'!AA99*'Model inputs'!AA85 -> 600 | H57: ='Model inputs'!H22*'Model inputs'!AA99*'Model inputs'!AA85 -> 780 | I57: ='Model inputs'!I22*'Model inputs'!AA99*'Model inputs'!AA85 -> 960 | J57: ='Model inputs'!J22*'Model inputs'!AA99*'Model inputs'!AA85 -> 1140 | K57: ='Model inputs'!K22*'Model inputs'!AA99*'Model inputs'!AA85 -> 1200 | L57: ='Model inputs'!L22*'Model inputs'!AA99*'Model inputs'!AA85 -> 1200 | M57: ='Model inputs'!M22*'Model inputs'!AA99*'Model inputs'!AA85 -> 1200 | N57: ='Model inputs'!N22*'Model inputs'!AA99*'Model inputs'!AA85 -> 1200 | O57: 0 | P57: 0 | Q57: 0 | R57: 0 | S57: 0 | T57: 0 | U57: 0 | V57: 0 | W57: 0 | X57: ='Model inputs'!X22*'Model inputs'!AA99*'Model inputs'!AA85 -> 0 | Y57: ='Model inputs'!Y22*'Model inputs'!AA99*'Model inputs'!AA85 -> 0
A58: Entrega mensal — projeção Base (EUR) · Teste Pro 109 € — fixos 300 €/mês | B58: ='Model inputs'!B23*'Model inputs'!AA100*'Model inputs'!AA86 -> 0 | C58: ='Model inputs'!C23*'Model inputs'!AA100*'Model inputs'!AA86 -> 30 | D58: ='Model inputs'!D23*'Model inputs'!AA100*'Model inputs'!AA86 -> 120 | E58: ='Model inputs'!E23*'Model inputs'!AA100*'Model inputs'!AA86 -> 270 | F58: ='Model inputs'!F23*'Model inputs'!AA100*'Model inputs'!AA86 -> 420 | G58: ='Model inputs'!G23*'Model inputs'!AA100*'Model inputs'!AA86 -> 600 | H58: ='Model inputs'!H23*'Model inputs'!AA100*'Model inputs'!AA86 -> 780 | I58: ='Model inputs'!I23*'Model inputs'!AA100*'Model inputs'!AA86 -> 960 | J58: ='Model inputs'!J23*'Model inputs'!AA100*'Model inputs'!AA86 -> 1140 | K58: ='Model inputs'!K23*'Model inputs'!AA100*'Model inputs'!AA86 -> 1200 | L58: ='Model inputs'!L23*'Model inputs'!AA100*'Model inputs'!AA86 -> 1200 | M58: ='Model inputs'!M23*'Model inputs'!AA100*'Model inputs'!AA86 -> 1200 | N58: ='Model inputs'!N23*'Model inputs'!AA100*'Model inputs'!AA86 -> 1200 | O58: 0 | P58: 0 | Q58: 0 | R58: 0 | S58: 0 | T58: 0 | U58: 0 | V58: 0 | W58: 0 | X58: ='Model inputs'!X23*'Model inputs'!AA100*'Model inputs'!AA86 -> 0 | Y58: ='Model inputs'!Y23*'Model inputs'!AA100*'Model inputs'!AA86 -> 0
A59: Entrega mensal — projeção Base (EUR) · Teste Pro 119 € — fixos 300 €/mês | B59: ='Model inputs'!B24*'Model inputs'!AA101*'Model inputs'!AA87 -> 0 | C59: ='Model inputs'!C24*'Model inputs'!AA101*'Model inputs'!AA87 -> 30 | D59: ='Model inputs'!D24*'Model inputs'!AA101*'Model inputs'!AA87 -> 120 | E59: ='Model inputs'!E24*'Model inputs'!AA101*'Model inputs'!AA87 -> 270 | F59: ='Model inputs'!F24*'Model inputs'!AA101*'Model inputs'!AA87 -> 420 | G59: ='Model inputs'!G24*'Model inputs'!AA101*'Model inputs'!AA87 -> 600 | H59: ='Model inputs'!H24*'Model inputs'!AA101*'Model inputs'!AA87 -> 780 | I59: ='Model inputs'!I24*'Model inputs'!AA101*'Model inputs'!AA87 -> 960 | J59: ='Model inputs'!J24*'Model inputs'!AA101*'Model inputs'!AA87 -> 1140 | K59: ='Model inputs'!K24*'Model inputs'!AA101*'Model inputs'!AA87 -> 1200 | L59: ='Model inputs'!L24*'Model inputs'!AA101*'Model inputs'!AA87 -> 1200 | M59: ='Model inputs'!M24*'Model inputs'!AA101*'Model inputs'!AA87 -> 1200 | N59: ='Model inputs'!N24*'Model inputs'!AA101*'Model inputs'!AA87 -> 1200 | O59: 0 | P59: 0 | Q59: 0 | R59: 0 | S59: 0 | T59: 0 | U59: 0 | V59: 0 | W59: 0 | X59: ='Model inputs'!X24*'Model inputs'!AA101*'Model inputs'!AA87 -> 0 | Y59: ='Model inputs'!Y24*'Model inputs'!AA101*'Model inputs'!AA87 -> 0
A60: Fixos anuais da projeção Base (EUR) · DisruptRadar — Projeção mensal · Projeção mensal Base — clientes, resultado e caixa | AA60: ='DisruptRadar — Projeção mensal'!B5 -> 6000
A61: Fixos anuais da projeção Base (EUR) · DisruptRadar — Projeção mensal · Reconciliação anual Base com a matriz | Z61: ='DisruptRadar — Projeção mensal'!B5 -> 6000
A62: Fixos mensais — projeção Base (EUR) · DisruptRadar — Projeção mensal · Projeção mensal Base — clientes, resultado e caixa | B62: ='Model inputs'!AA60/12 -> 500 | C62: ='Model inputs'!AA60/12 -> 500 | D62: ='Model inputs'!AA60/12 -> 500 | E62: ='Model inputs'!AA60/12 -> 500 | F62: ='Model inputs'!AA60/12 -> 500 | G62: ='Model inputs'!AA60/12 -> 500 | H62: ='Model inputs'!AA60/12 -> 500 | I62: ='Model inputs'!AA60/12 -> 500 | J62: ='Model inputs'!AA60/12 -> 500 | K62: ='Model inputs'!AA60/12 -> 500 | L62: ='Model inputs'!AA60/12 -> 500 | M62: ='Model inputs'!AA60/12 -> 500 | N62: ='Model inputs'!AA60/12 -> 500 | O62: 0 | P62: 0 | Q62: 0 | R62: 0 | S62: 0 | T62: 0 | U62: 0 | V62: 0 | W62: 0 | X62: ='Model inputs'!AA60/12 -> 500 | Y62: ='Model inputs'!AA60/12 -> 500
A63: Início da projeção Base · DisruptRadar — Projeção mensal · Projeção mensal Base — clientes, resultado e caixa | AA63: =DATE(2027,1,1) -> 46388
A64: Movimento de caixa acumulado — projeção Base (EUR) | B64: =IF(IF(IF(IF(ISERROR(DATE(2026,12,1)=DATE(YEAR('Model inputs'!AA63),MONTH('Model inputs'!AA63),1)),DATE(2026,12,1)=DATE(YEAR('Model inputs'!AA63),MONTH('Model inputs'!AA63),1),IF(DATE(YEAR('Model inputs'!AA63),MONTH('Model inputs'!AA63),1)="","",DATE(2026,12,1)=DATE(YEAR('Model inputs'!AA63),MONTH('Model inputs'!AA63),1)))="",FALSE,IF(ISERROR(DATE(2026,12,1)=DATE(YEAR('Model inputs'!AA63),MONTH('Model inputs'!AA63),1)),DATE(2026,12,1)=DATE(YEAR('Model inputs'!AA63),MONTH('Model inputs'!AA63),1),IF(DATE(YEAR('Model inputs'!AA63),MONTH('Model inputs'!AA63),1)="","",DATE(2026,12,1)=DATE(YEAR('Model inputs'!AA63),MONTH('Model inputs'!AA63),1)))),0,IF('Model inputs'!Y64="","",'Model inputs'!Y64))="",0,IF(IF(IF(ISERROR(DATE(2026,12,1)=DATE(YEAR('Model inputs'!AA63),MONTH('Model inputs'!AA63),1)),DATE(2026,12,1)=DATE(YEAR('Model inputs'!AA63),MONTH('Model inputs'!AA63),1),IF(DATE(YEAR('Model inputs'!AA63),MONTH('Model inputs'!AA63),1)="","",DATE(2026,12,1)=DATE(YEAR('Model inputs'!AA63),MONTH('Model inputs'!AA63),1)))="",FALSE,IF(ISERROR(DATE(2026,12,1)=DATE(YEAR('Model inputs'!AA63),MONTH('Model inputs'!AA63),1)),DATE(2026,12,1)=DATE(YEAR('Model inputs'!AA63),MONTH('Model inputs'!AA63),1),IF(DATE(YEAR('Model inputs'!AA63),MONTH('Model inputs'!AA63),1)="","",DATE(2026,12,1)=DATE(YEAR('Model inputs'!AA63),MONTH('Model inputs'!AA63),1)))),0,IF('Model inputs'!Y64="","",'Model inputs'!Y64)))+'Model inputs'!B41 -> -1500 | C64: =IF(IF(IF(IF(ISERROR(DATE(2027,1,1)=DATE(YEAR('Model inputs'!AA63),MONTH('Model inputs'!AA63),1)),DATE(2027,1,1)=DATE(YEAR('Model inputs'!AA63),MONTH('Model inputs'!AA63),1),IF(DATE(YEAR('Model inputs'!AA63),MONTH('Model inputs'!AA63),1)="","",DATE(2027,1,1)=DATE(YEAR('Model inputs'!AA63),MONTH('Model inputs'!AA63),1)))="",FALSE,IF(ISERROR(DATE(2027,1,1)=DATE(YEAR('Model inputs'!AA63),MONTH('Model inputs'!AA63),1)),DATE(2027,1,1)=DATE(YEAR('Model inputs'!AA63),MONTH('Model inputs'!AA63),1),IF(DATE(YEAR('Model inputs'!AA63),MONTH('Model inputs'!AA63),1)="","",DATE(2027,1,1)=DATE(YEAR('Model inputs'!AA63),MONTH('Model inputs'!AA63),1)))),0,IF('Model inputs'!B64="","",'Model inputs'!B64))="",0,IF(IF(IF(ISERROR(DATE(2027,1,1)=DATE(YEAR('Model inputs'!AA63),MONTH('Model inputs'!AA63),1)),DATE(2027,1,1)=DATE(YEAR('Model inputs'!AA63),MONTH('Model inputs'!AA63),1),IF(DATE(YEAR('Model inputs'!AA63),MONTH('Model inputs'!AA63),1)="","",DATE(2027,1,1)=DATE(YEAR('Model inputs'!AA63),MONTH('Model inputs'!AA63),1)))="",FALSE,IF(ISERROR(DATE(2027,1,1)=DATE(YEAR('Model inputs'!AA63),MONTH('Model inputs'!AA63),1)),DATE(2027,1,1)=DATE(YEAR('Model inputs'!AA63),MONTH('Model inputs'!AA63),1),IF(DATE(YEAR('Model inputs'!AA63),MONTH('Model inputs'!AA63),1)="","",DATE(2027,1,1)=DATE(YEAR('Model inputs'!AA63),MONTH('Model inputs'!AA63),1)))),0,IF('Model inputs'!B64="","",'Model inputs'!B64)))+'Model inputs'!C41 -> -431 | D64: =IF(IF(IF(IF(ISERROR(DATE(2027,2,1)=DATE(YEAR('Model inputs'!AA63),MONTH('Model inputs'!AA63),1)),DATE(2027,2,1)=DATE(YEAR('Model inputs'!AA63),MONTH('Model inputs'!AA63),1),IF(DATE(YEAR('Model inputs'!AA63),MONTH('Model inputs'!AA63),1)="","",DATE(2027,2,1)=DATE(YEAR('Model inputs'!AA63),MONTH('Model inputs'!AA63),1)))="",FALSE,IF(ISERROR(DATE(2027,2,1)=DATE(YEAR('Model inputs'!AA63),MONTH('Model inputs'!AA63),1)),DATE(2027,2,1)=DATE(YEAR('Model inputs'!AA63),MONTH('Model inputs'!AA63),1),IF(DATE(YEAR('Model inputs'!AA63),MONTH('Model inputs'!AA63),1)="","",DATE(2027,2,1)=DATE(YEAR('Model inputs'!AA63),MONTH('Model inputs'!AA63),1)))),0,IF('Model inputs'!C64="","",'Model inputs'!C64))="",0,IF(IF(IF(ISERROR(DATE(2027,2,1)=DATE(YEAR('Model inputs'!AA63),MONTH('Model inputs'!AA63),1)),DATE(2027,2,1)=DATE(YEAR('Model inputs'!AA63),MONTH('Model inputs'!AA63),1),IF(DATE(YEAR('Model inputs'!AA63),MONTH('Model inputs'!AA63),1)="","",DATE(2027,2,1)=DATE(YEAR('Model inputs'!AA63),MONTH('Model inputs'!AA63),1)))="",FALSE,IF(ISERROR(DATE(2027,2,1)=DATE(YEAR('Model inputs'!AA63),MONTH('Model inputs'!AA63),1)),DATE(2027,2,1)=DATE(YEAR('Model inputs'!AA63),MONTH('Model inputs'!AA63),1),IF(DATE(YEAR('Model inputs'!AA63),MONTH('Model inputs'!AA63),1)="","",DATE(2027,2,1)=DATE(YEAR('Model inputs'!AA63),MONTH('Model inputs'!AA63),1)))),0,IF('Model inputs'!C64="","",'Model inputs'!C64)))+'Model inputs'!D41 -> -655 | E64: =IF(IF(IF(IF(ISERROR(DATE(2027,3,1)=DATE(YEAR('Model inputs'!AA63),MONTH('Model inputs'!AA63),1)),DATE(2027,3,1)=DATE(YEAR('Model inputs'!AA63),MONTH('Model inputs'!AA63),1),IF(DATE(YEAR('Model inputs'!AA63),MONTH('Model inputs'!AA63),1)="","",DATE(2027,3,1)=DATE(YEAR('Model inputs'!AA63),MONTH('Model inputs'!AA63),1)))="",FALSE,IF(ISERROR(DATE(2027,3,1)=DATE(YEAR('Model inputs'!AA63),MONTH('Model inputs'!AA63),1)),DATE(2027,3,1)=DATE(YEAR('Model inputs'!AA63),MONTH('Model inputs'!AA63),1),IF(DATE(YEAR('Model inputs'!AA63),MONTH('Model inputs'!AA63),1)="","",DATE(2027,3,1)=DATE(YEAR('Model inputs'!AA63),MONTH('Model inputs'!AA63),1)))),0,IF('Model inputs'!D64="","",'Model inputs'!D64))="",0,IF(IF(IF(ISERROR(DATE(2027,3,1)=DATE(YEAR('Model inputs'!AA63),MONTH('Model inputs'!AA63),1)),DATE(2027,3,1)=DATE(YEAR('Model inputs'!AA63),MONTH('Model inputs'!AA63),1),IF(DATE(YEAR('Model inputs'!AA63),MONTH('Model inputs'!AA63),1)="","",DATE(2027,3,1)=DATE(YEAR('Model inputs'!AA63),MONTH('Model inputs'!AA63),1)))="",FALSE,IF(ISERROR(DATE(2027,3,1)=DATE(YEAR('Model inputs'!AA63),MONTH('Model inputs'!AA63),1)),DATE(2027,3,1)=DATE(YEAR('Model inputs'!AA63),MONTH('Model inputs'!AA63),1),IF(DATE(YEAR('Model inputs'!AA63),MONTH('Model inputs'!AA63),1)="","",DATE(2027,3,1)=DATE(YEAR('Model inputs'!AA63),MONTH('Model inputs'!AA63),1)))),0,IF('Model inputs'!D64="","",'Model inputs'!D64)))+'Model inputs'!E41 -> -534 | F64: =IF(IF(IF(IF(ISERROR(DATE(2027,4,1)=DATE(YEAR('Model inputs'!AA63),MONTH('Model inputs'!AA63),1)),DATE(2027,4,1)=DATE(YEAR('Model inputs'!AA63),MONTH('Model inputs'!AA63),1),IF(DATE(YEAR('Model inputs'!AA63),MONTH('Model inputs'!AA63),1)="","",DATE(2027,4,1)=DATE(YEAR('Model inputs'!AA63),MONTH('Model inputs'!AA63),1)))="",FALSE,IF(ISERROR(DATE(2027,4,1)=DATE(YEAR('Model inputs'!AA63),MONTH('Model inputs'!AA63),1)),DATE(2027,4,1)=DATE(YEAR('Model inputs'!AA63),MONTH('Model inputs'!AA63),1),IF(DATE(YEAR('Model inputs'!AA63),MONTH('Model inputs'!AA63),1)="","",DATE(2027,4,1)=DATE(YEAR('Model inputs'!AA63),MONTH('Model inputs'!AA63),1)))),0,IF('Model inputs'!E64="","",'Model inputs'!E64))="",0,IF(IF(IF(ISERROR(DATE(2027,4,1)=DATE(YEAR('Model inputs'!AA63),MONTH('Model inputs'!AA63),1)),DATE(2027,4,1)=DATE(YEAR('Model inputs'!AA63),MONTH('Model inputs'!AA63),1),IF(DATE(YEAR('Model inputs'!AA63),MONTH('Model inputs'!AA63),1)="","",DATE(2027,4,1)=DATE(YEAR('Model inputs'!AA63),MONTH('Model inputs'!AA63),1)))="",FALSE,IF(ISERROR(DATE(2027,4,1)=DATE(YEAR('Model inputs'!AA63),MONTH('Model inputs'!AA63),1)),DATE(2027,4,1)=DATE(YEAR('Model inputs'!AA63),MONTH('Model inputs'!AA63),1),IF(DATE(YEAR('Model inputs'!AA63),MONTH('Model inputs'!AA63),1)="","",DATE(2027,4,1)=DATE(YEAR('Model inputs'!AA63),MONTH('Model inputs'!AA63),1)))),0,IF('Model inputs'!E64="","",'Model inputs'!E64)))+'Model inputs'!F41 -> -68 | G64: =IF(IF(IF(IF(ISERROR(DATE(2027,5,1)=DATE(YEAR('Model inputs'!AA63),MONTH('Model inputs'!AA63),1)),DATE(2027,5,1)=DATE(YEAR('Model inputs'!AA63),MONTH('Model inputs'!AA63),1),IF(DATE(YEAR('Model inputs'!AA63),MONTH('Model inputs'!AA63),1)="","",DATE(2027,5,1)=DATE(YEAR('Model inputs'!AA63),MONTH('Model inputs'!AA63),1)))="",FALSE,IF(ISERROR(DATE(2027,5,1)=DATE(YEAR('Model inputs'!AA63),MONTH('Model inputs'!AA63),1)),DATE(2027,5,1)=DATE(YEAR('Model inputs'!AA63),MONTH('Model inputs'!AA63),1),IF(DATE(YEAR('Model inputs'!AA63),MONTH('Model inputs'!AA63),1)="","",DATE(2027,5,1)=DATE(YEAR('Model inputs'!AA63),MONTH('Model inputs'!AA63),1)))),0,IF('Model inputs'!F64="","",'Model inputs'!F64))="",0,IF(IF(IF(ISERROR(DATE(2027,5,1)=DATE(YEAR('Model inputs'!AA63),MONTH('Model inputs'!AA63),1)),DATE(2027,5,1)=DATE(YEAR('Model inputs'!AA63),MONTH('Model inputs'!AA63),1),IF(DATE(YEAR('Model inputs'!AA63),MONTH('Model inputs'!AA63),1)="","",DATE(2027,5,1)=DATE(YEAR('Model inputs'!AA63),MONTH('Model inputs'!AA63),1)))="",FALSE,IF(ISERROR(DATE(2027,5,1)=DATE(YEAR('Model inputs'!AA63),MONTH('Model inputs'!AA63),1)),DATE(2027,5,1)=DATE(YEAR('Model inputs'!AA63),MONTH('Model inputs'!AA63),1),IF(DATE(YEAR('Model inputs'!AA63),MONTH('Model inputs'!AA63),1)="","",DATE(2027,5,1)=DATE(YEAR('Model inputs'!AA63),MONTH('Model inputs'!AA63),1)))),0,IF('Model inputs'!F64="","",'Model inputs'!F64)))+'Model inputs'!G41 -> 812 | H64: =IF(IF(IF(IF(ISERROR(DATE(2027,6,1)=DATE(YEAR('Model inputs'!AA63),MONTH('Model inputs'!AA63),1)),DATE(2027,6,1)=DATE(YEAR('Model inputs'!AA63),MONTH('Model inputs'!AA63),1),IF(DATE(YEAR('Model inputs'!AA63),MONTH('Model inputs'!AA63),1)="","",DATE(2027,6,1)=DATE(YEAR('Model inputs'!AA63),MONTH('Model inputs'!AA63),1)))="",FALSE,IF(ISERROR(DATE(2027,6,1)=DATE(YEAR('Model inputs'!AA63),MONTH('Model inputs'!AA63),1)),DATE(2027,6,1)=DATE(YEAR('Model inputs'!AA63),MONTH('Model inputs'!AA63),1),IF(DATE(YEAR('Model inputs'!AA63),MONTH('Model inputs'!AA63),1)="","",DATE(2027,6,1)=DATE(YEAR('Model inputs'!AA63),MONTH('Model inputs'!AA63),1)))),0,IF('Model inputs'!G64="","",'Model inputs'!G64))="",0,IF(IF(IF(ISERROR(DATE(2027,6,1)=DATE(YEAR('Model inputs'!AA63),MONTH('Model inputs'!AA63),1)),DATE(2027,6,1)=DATE(YEAR('Model inputs'!AA63),MONTH('Model inputs'!AA63),1),IF(DATE(YEAR('Model inputs'!AA63),MONTH('Model inputs'!AA63),1)="","",DATE(2027,6,1)=DATE(YEAR('Model inputs'!AA63),MONTH('Model inputs'!AA63),1)))="",FALSE,IF(ISERROR(DATE(2027,6,1)=DATE(YEAR('Model inputs'!AA63),MONTH('Model inputs'!AA63),1)),DATE(2027,6,1)=DATE(YEAR('Model inputs'!AA63),MONTH('Model inputs'!AA63),1),IF(DATE(YEAR('Model inputs'!AA63),MONTH('Model inputs'!AA63),1)="","",DATE(2027,6,1)=DATE(YEAR('Model inputs'!AA63),MONTH('Model inputs'!AA63),1)))),0,IF('Model inputs'!G64="","",'Model inputs'!G64)))+'Model inputs'!H41 -> 2106 | I64: =IF(IF(IF(IF(ISERROR(DATE(2027,7,1)=DATE(YEAR('Model inputs'!AA63),MONTH('Model inputs'!AA63),1)),DATE(2027,7,1)=DATE(YEAR('Model inputs'!AA63),MONTH('Model inputs'!AA63),1),IF(DATE(YEAR('Model inputs'!AA63),MONTH('Model inputs'!AA63),1)="","",DATE(2027,7,1)=DATE(YEAR('Model inputs'!AA63),MONTH('Model inputs'!AA63),1)))="",FALSE,IF(ISERROR(DATE(2027,7,1)=DATE(YEAR('Model inputs'!AA63),MONTH('Model inputs'!AA63),1)),DATE(2027,7,1)=DATE(YEAR('Model inputs'!AA63),MONTH('Model inputs'!AA63),1),IF(DATE(YEAR('Model inputs'!AA63),MONTH('Model inputs'!AA63),1)="","",DATE(2027,7,1)=DATE(YEAR('Model inputs'!AA63),MONTH('Model inputs'!AA63),1)))),0,IF('Model inputs'!H64="","",'Model inputs'!H64))="",0,IF(IF(IF(ISERROR(DATE(2027,7,1)=DATE(YEAR('Model inputs'!AA63),MONTH('Model inputs'!AA63),1)),DATE(2027,7,1)=DATE(YEAR('Model inputs'!AA63),MONTH('Model inputs'!AA63),1),IF(DATE(YEAR('Model inputs'!AA63),MONTH('Model inputs'!AA63),1)="","",DATE(2027,7,1)=DATE(YEAR('Model inputs'!AA63),MONTH('Model inputs'!AA63),1)))="",FALSE,IF(ISERROR(DATE(2027,7,1)=DATE(YEAR('Model inputs'!AA63),MONTH('Model inputs'!AA63),1)),DATE(2027,7,1)=DATE(YEAR('Model inputs'!AA63),MONTH('Model inputs'!AA63),1),IF(DATE(YEAR('Model inputs'!AA63),MONTH('Model inputs'!AA63),1)="","",DATE(2027,7,1)=DATE(YEAR('Model inputs'!AA63),MONTH('Model inputs'!AA63),1)))),0,IF('Model inputs'!H64="","",'Model inputs'!H64)))+'Model inputs'!I41 -> 3814 | J64: =IF(IF(IF(IF(ISERROR(DATE(2027,8,1)=DATE(YEAR('Model inputs'!AA63),MONTH('Model inputs'!AA63),1)),DATE(2027,8,1)=DATE(YEAR('Model inputs'!AA63),MONTH('Model inputs'!AA63),1),IF(DATE(YEAR('Model inputs'!AA63),MONTH('Model inputs'!AA63),1)="","",DATE(2027,8,1)=DATE(YEAR('Model inputs'!AA63),MONTH('Model inputs'!AA63),1)))="",FALSE,IF(ISERROR(DATE(2027,8,1)=DATE(YEAR('Model inputs'!AA63),MONTH('Model inputs'!AA63),1)),DATE(2027,8,1)=DATE(YEAR('Model inputs'!AA63),MONTH('Model inputs'!AA63),1),IF(DATE(YEAR('Model inputs'!AA63),MONTH('Model inputs'!AA63),1)="","",DATE(2027,8,1)=DATE(YEAR('Model inputs'!AA63),MONTH('Model inputs'!AA63),1)))),0,IF('Model inputs'!I64="","",'Model inputs'!I64))="",0,IF(IF(IF(ISERROR(DATE(2027,8,1)=DATE(YEAR('Model inputs'!AA63),MONTH('Model inputs'!AA63),1)),DATE(2027,8,1)=DATE(YEAR('Model inputs'!AA63),MONTH('Model inputs'!AA63),1),IF(DATE(YEAR('Model inputs'!AA63),MONTH('Model inputs'!AA63),1)="","",DATE(2027,8,1)=DATE(YEAR('Model inputs'!AA63),MONTH('Model inputs'!AA63),1)))="",FALSE,IF(ISERROR(DATE(2027,8,1)=DATE(YEAR('Model inputs'!AA63),MONTH('Model inputs'!AA63),1)),DATE(2027,8,1)=DATE(YEAR('Model inputs'!AA63),MONTH('Model inputs'!AA63),1),IF(DATE(YEAR('Model inputs'!AA63),MONTH('Model inputs'!AA63),1)="","",DATE(2027,8,1)=DATE(YEAR('Model inputs'!AA63),MONTH('Model inputs'!AA63),1)))),0,IF('Model inputs'!I64="","",'Model inputs'!I64)))+'Model inputs'!J41 -> 5936 | K64: =IF(IF(IF(IF(ISERROR(DATE(2027,9,1)=DATE(YEAR('Model inputs'!AA63),MONTH('Model inputs'!AA63),1)),DATE(2027,9,1)=DATE(YEAR('Model inputs'!AA63),MONTH('Model inputs'!AA63),1),IF(DATE(YEAR('Model inputs'!AA63),MONTH('Model inputs'!AA63),1)="","",DATE(2027,9,1)=DATE(YEAR('Model inputs'!AA63),MONTH('Model inputs'!AA63),1)))="",FALSE,IF(ISERROR(DATE(2027,9,1)=DATE(YEAR('Model inputs'!AA63),MONTH('Model inputs'!AA63),1)),DATE(2027,9,1)=DATE(YEAR('Model inputs'!AA63),MONTH('Model inputs'!AA63),1),IF(DATE(YEAR('Model inputs'!AA63),MONTH('Model inputs'!AA63),1)="","",DATE(2027,9,1)=DATE(YEAR('Model inputs'!AA63),MONTH('Model inputs'!AA63),1)))),0,IF('Model inputs'!J64="","",'Model inputs'!J64))="",0,IF(IF(IF(ISERROR(DATE(2027,9,1)=DATE(YEAR('Model inputs'!AA63),MONTH('Model inputs'!AA63),1)),DATE(2027,9,1)=DATE(YEAR('Model inputs'!AA63),MONTH('Model inputs'!AA63),1),IF(DATE(YEAR('Model inputs'!AA63),MONTH('Model inputs'!AA63),1)="","",DATE(2027,9,1)=DATE(YEAR('Model inputs'!AA63),MONTH('Model inputs'!AA63),1)))="",FALSE,IF(ISERROR(DATE(2027,9,1)=DATE(YEAR('Model inputs'!AA63),MONTH('Model inputs'!AA63),1)),DATE(2027,9,1)=DATE(YEAR('Model inputs'!AA63),MONTH('Model inputs'!AA63),1),IF(DATE(YEAR('Model inputs'!AA63),MONTH('Model inputs'!AA63),1)="","",DATE(2027,9,1)=DATE(YEAR('Model inputs'!AA63),MONTH('Model inputs'!AA63),1)))),0,IF('Model inputs'!J64="","",'Model inputs'!J64)))+'Model inputs'!K41 -> 8196 | L64: =IF(IF(IF(IF(ISERROR(DATE(2027,10,1)=DATE(YEAR('Model inputs'!AA63),MONTH('Model inputs'!AA63),1)),DATE(2027,10,1)=DATE(YEAR('Model inputs'!AA63),MONTH('Model inputs'!AA63),1),IF(DATE(YEAR('Model inputs'!AA63),MONTH('Model inputs'!AA63),1)="","",DATE(2027,10,1)=DATE(YEAR('Model inputs'!AA63),MONTH('Model inputs'!AA63),1)))="",FALSE,IF(ISERROR(DATE(2027,10,1)=DATE(YEAR('Model inputs'!AA63),MONTH('Model inputs'!AA63),1)),DATE(2027,10,1)=DATE(YEAR('Model inputs'!AA63),MONTH('Model inputs'!AA63),1),IF(DATE(YEAR('Model inputs'!AA63),MONTH('Model inputs'!AA63),1)="","",DATE(2027,10,1)=DATE(YEAR('Model inputs'!AA63),MONTH('Model inputs'!AA63),1)))),0,IF('Model inputs'!K64="","",'Model inputs'!K64))="",0,IF(IF(IF(ISERROR(DATE(2027,10,1)=DATE(YEAR('Model inputs'!AA63),MONTH('Model inputs'!AA63),1)),DATE(2027,10,1)=DATE(YEAR('Model inputs'!AA63),MONTH('Model inputs'!AA63),1),IF(DATE(YEAR('Model inputs'!AA63),MONTH('Model inputs'!AA63),1)="","",DATE(2027,10,1)=DATE(YEAR('Model inputs'!AA63),MONTH('Model inputs'!AA63),1)))="",FALSE,IF(ISERROR(DATE(2027,10,1)=DATE(YEAR('Model inputs'!AA63),MONTH('Model inputs'!AA63),1)),DATE(2027,10,1)=DATE(YEAR('Model inputs'!AA63),MONTH('Model inputs'!AA63),1),IF(DATE(YEAR('Model inputs'!AA63),MONTH('Model inputs'!AA63),1)="","",DATE(2027,10,1)=DATE(YEAR('Model inputs'!AA63),MONTH('Model inputs'!AA63),1)))),0,IF('Model inputs'!K64="","",'Model inputs'!K64)))+'Model inputs'!L41 -> 10456 | M64: =IF(IF(IF(IF(ISERROR(DATE(2027,11,1)=DATE(YEAR('Model inputs'!AA63),MONTH('Model inputs'!AA63),1)),DATE(2027,11,1)=DATE(YEAR('Model inputs'!AA63),MONTH('Model inputs'!AA63),1),IF(DATE(YEAR('Model inputs'!AA63),MONTH('Model inputs'!AA63),1)="","",DATE(2027,11,1)=DATE(YEAR('Model inputs'!AA63),MONTH('Model inputs'!AA63),1)))="",FALSE,IF(ISERROR(DATE(2027,11,1)=DATE(YEAR('Model inputs'!AA63),MONTH('Model inputs'!AA63),1)),DATE(2027,11,1)=DATE(YEAR('Model inputs'!AA63),MONTH('Model inputs'!AA63),1),IF(DATE(YEAR('Model inputs'!AA63),MONTH('Model inputs'!AA63),1)="","",DATE(2027,11,1)=DATE(YEAR('Model inputs'!AA63),MONTH('Model inputs'!AA63),1)))),0,IF('Model inputs'!L64="","",'Model inputs'!L64))="",0,IF(IF(IF(ISERROR(DATE(2027,11,1)=DATE(YEAR('Model inputs'!AA63),MONTH('Model inputs'!AA63),1)),DATE(2027,11,1)=DATE(YEAR('Model inputs'!AA63),MONTH('Model inputs'!AA63),1),IF(DATE(YEAR('Model inputs'!AA63),MONTH('Model inputs'!AA63),1)="","",DATE(2027,11,1)=DATE(YEAR('Model inputs'!AA63),MONTH('Model inputs'!AA63),1)))="",FALSE,IF(ISERROR(DATE(2027,11,1)=DATE(YEAR('Model inputs'!AA63),MONTH('Model inputs'!AA63),1)),DATE(2027,11,1)=DATE(YEAR('Model inputs'!AA63),MONTH('Model inputs'!AA63),1),IF(DATE(YEAR('Model inputs'!AA63),MONTH('Model inputs'!AA63),1)="","",DATE(2027,11,1)=DATE(YEAR('Model inputs'!AA63),MONTH('Model inputs'!AA63),1)))),0,IF('Model inputs'!L64="","",'Model inputs'!L64)))+'Model inputs'!M41 -> 12716 | N64: =IF(IF(IF(IF(ISERROR(DATE(2027,12,1)=DATE(YEAR('Model inputs'!AA63),MONTH('Model inputs'!AA63),1)),DATE(2027,12,1)=DATE(YEAR('Model inputs'!AA63),MONTH('Model inputs'!AA63),1),IF(DATE(YEAR('Model inputs'!AA63),MONTH('Model inputs'!AA63),1)="","",DATE(2027,12,1)=DATE(YEAR('Model inputs'!AA63),MONTH('Model inputs'!AA63),1)))="",FALSE,IF(ISERROR(DATE(2027,12,1)=DATE(YEAR('Model inputs'!AA63),MONTH('Model inputs'!AA63),1)),DATE(2027,12,1)=DATE(YEAR('Model inputs'!AA63),MONTH('Model inputs'!AA63),1),IF(DATE(YEAR('Model inputs'!AA63),MONTH('Model inputs'!AA63),1)="","",DATE(2027,12,1)=DATE(YEAR('Model inputs'!AA63),MONTH('Model inputs'!AA63),1)))),0,IF('Model inputs'!M64="","",'Model inputs'!M64))="",0,IF(IF(IF(ISERROR(DATE(2027,12,1)=DATE(YEAR('Model inputs'!AA63),MONTH('Model inputs'!AA63),1)),DATE(2027,12,1)=DATE(YEAR('Model inputs'!AA63),MONTH('Model inputs'!AA63),1),IF(DATE(YEAR('Model inputs'!AA63),MONTH('Model inputs'!AA63),1)="","",DATE(2027,12,1)=DATE(YEAR('Model inputs'!AA63),MONTH('Model inputs'!AA63),1)))="",FALSE,IF(ISERROR(DATE(2027,12,1)=DATE(YEAR('Model inputs'!AA63),MONTH('Model inputs'!AA63),1)),DATE(2027,12,1)=DATE(YEAR('Model inputs'!AA63),MONTH('Model inputs'!AA63),1),IF(DATE(YEAR('Model inputs'!AA63),MONTH('Model inputs'!AA63),1)="","",DATE(2027,12,1)=DATE(YEAR('Model inputs'!AA63),MONTH('Model inputs'!AA63),1)))),0,IF('Model inputs'!M64="","",'Model inputs'!M64)))+'Model inputs'!N41 -> 14976 | O64: 0 | P64: 0 | Q64: 0 | R64: 0 | S64: 0 | T64: 0 | U64: 0 | V64: 0 | W64: 0 | X64: =IF(IF(IF(IF(ISERROR(DATE(2026,10,1)=DATE(YEAR('Model inputs'!AA63),MONTH('Model inputs'!AA63),1)),DATE(2026,10,1)=DATE(YEAR('Model inputs'!AA63),MONTH('Model inputs'!AA63),1),IF(DATE(YEAR('Model inputs'!AA63),MONTH('Model inputs'!AA63),1)="","",DATE(2026,10,1)=DATE(YEAR('Model inputs'!AA63),MONTH('Model inputs'!AA63),1)))="",FALSE,IF(ISERROR(DATE(2026,10,1)=DATE(YEAR('Model inputs'!AA63),MONTH('Model inputs'!AA63),1)),DATE(2026,10,1)=DATE(YEAR('Model inputs'!AA63),MONTH('Model inputs'!AA63),1),IF(DATE(YEAR('Model inputs'!AA63),MONTH('Model inputs'!AA63),1)="","",DATE(2026,10,1)=DATE(YEAR('Model inputs'!AA63),MONTH('Model inputs'!AA63),1)))),0,IF('Model inputs'!W64="","",'Model inputs'!W64))="",0,IF(IF(IF(ISERROR(DATE(2026,10,1)=DATE(YEAR('Model inputs'!AA63),MONTH('Model inputs'!AA63),1)),DATE(2026,10,1)=DATE(YEAR('Model inputs'!AA63),MONTH('Model inputs'!AA63),1),IF(DATE(YEAR('Model inputs'!AA63),MONTH('Model inputs'!AA63),1)="","",DATE(2026,10,1)=DATE(YEAR('Model inputs'!AA63),MONTH('Model inputs'!AA63),1)))="",FALSE,IF(ISERROR(DATE(2026,10,1)=DATE(YEAR('Model inputs'!AA63),MONTH('Model inputs'!AA63),1)),DATE(2026,10,1)=DATE(YEAR('Model inputs'!AA63),MONTH('Model inputs'!AA63),1),IF(DATE(YEAR('Model inputs'!AA63),MONTH('Model inputs'!AA63),1)="","",DATE(2026,10,1)=DATE(YEAR('Model inputs'!AA63),MONTH('Model inputs'!AA63),1)))),0,IF('Model inputs'!W64="","",'Model inputs'!W64)))+'Model inputs'!X41 -> -500 | Y64: =IF(IF(IF(IF(ISERROR(DATE(2026,11,1)=DATE(YEAR('Model inputs'!AA63),MONTH('Model inputs'!AA63),1)),DATE(2026,11,1)=DATE(YEAR('Model inputs'!AA63),MONTH('Model inputs'!AA63),1),IF(DATE(YEAR('Model inputs'!AA63),MONTH('Model inputs'!AA63),1)="","",DATE(2026,11,1)=DATE(YEAR('Model inputs'!AA63),MONTH('Model inputs'!AA63),1)))="",FALSE,IF(ISERROR(DATE(2026,11,1)=DATE(YEAR('Model inputs'!AA63),MONTH('Model inputs'!AA63),1)),DATE(2026,11,1)=DATE(YEAR('Model inputs'!AA63),MONTH('Model inputs'!AA63),1),IF(DATE(YEAR('Model inputs'!AA63),MONTH('Model inputs'!AA63),1)="","",DATE(2026,11,1)=DATE(YEAR('Model inputs'!AA63),MONTH('Model inputs'!AA63),1)))),0,IF('Model inputs'!X64="","",'Model inputs'!X64))="",0,IF(IF(IF(ISERROR(DATE(2026,11,1)=DATE(YEAR('Model inputs'!AA63),MONTH('Model inputs'!AA63),1)),DATE(2026,11,1)=DATE(YEAR('Model inputs'!AA63),MONTH('Model inputs'!AA63),1),IF(DATE(YEAR('Model inputs'!AA63),MONTH('Model inputs'!AA63),1)="","",DATE(2026,11,1)=DATE(YEAR('Model inputs'!AA63),MONTH('Model inputs'!AA63),1)))="",FALSE,IF(ISERROR(DATE(2026,11,1)=DATE(YEAR('Model inputs'!AA63),MONTH('Model inputs'!AA63),1)),DATE(2026,11,1)=DATE(YEAR('Model inputs'!AA63),MONTH('Model inputs'!AA63),1),IF(DATE(YEAR('Model inputs'!AA63),MONTH('Model inputs'!AA63),1)="","",DATE(2026,11,1)=DATE(YEAR('Model inputs'!AA63),MONTH('Model inputs'!AA63),1)))),0,IF('Model inputs'!X64="","",'Model inputs'!X64)))+'Model inputs'!Y41 -> -1000
A65: Preço mensal Pro (EUR) · DisruptRadar Business Plan · Premissas DisruptRadar — Ano 1 | Z65: =99 -> 99
A66: Preço mensal Pro (EUR) · DisruptRadar — Projeção mensal · Projeção mensal Base — clientes, resultado e caixa | AA66: =99 -> 99
A67: Receita mensal — projeção Base (EUR) · DisruptRadar — Projeção mensal · Projeção mensal Base — clientes, resultado e caixa · Base | B67: ='Model inputs'!B16*'Model inputs'!Z65 -> 0 | C67: ='Model inputs'!C16*'Model inputs'!Z65 -> 99 | D67: ='Model inputs'!D16*'Model inputs'!Z65 -> 396 | E67: ='Model inputs'!E16*'Model inputs'!Z65 -> 891 | F67: ='Model inputs'!F16*'Model inputs'!Z65 -> 1386 | G67: ='Model inputs'!G16*'Model inputs'!Z65 -> 1980 | H67: ='Model inputs'!H16*'Model inputs'!Z65 -> 2574 | I67: ='Model inputs'!I16*'Model inputs'!Z65 -> 3168 | J67: ='Model inputs'!J16*'Model inputs'!Z65 -> 3762 | K67: ='Model inputs'!K16*'Model inputs'!Z65 -> 3960 | L67: ='Model inputs'!L16*'Model inputs'!Z65 -> 3960 | M67: ='Model inputs'!M16*'Model inputs'!Z65 -> 3960 | N67: ='Model inputs'!N16*'Model inputs'!Z65 -> 3960 | O67: 0 | P67: 0 | Q67: 0 | R67: 0 | S67: 0 | T67: 0 | U67: 0 | V67: 0 | W67: 0 | X67: ='Model inputs'!X16*'Model inputs'!Z65 -> 0 | Y67: ='Model inputs'!Y16*'Model inputs'!Z65 -> 0
A68: Receita mensal — projeção Base (EUR) · Teste Pro 109 € — fixos 500 €/mês | B68: ='Model inputs'!B17*'DisruptRadar — Projeção men (5)'!G5 -> 0 | C68: ='Model inputs'!C17*'DisruptRadar — Projeção men (5)'!G5 -> 109 | D68: ='Model inputs'!D17*'DisruptRadar — Projeção men (5)'!G5 -> 436 | E68: ='Model inputs'!E17*'DisruptRadar — Projeção men (5)'!G5 -> 981 | F68: ='Model inputs'!F17*'DisruptRadar — Projeção men (5)'!G5 -> 1526 | G68: ='Model inputs'!G17*'DisruptRadar — Projeção men (5)'!G5 -> 2180 | H68: ='Model inputs'!H17*'DisruptRadar — Projeção men (5)'!G5 -> 2834 | I68: ='Model inputs'!I17*'DisruptRadar — Projeção men (5)'!G5 -> 3488 | J68: ='Model inputs'!J17*'DisruptRadar — Projeção men (5)'!G5 -> 4142 | K68: ='Model inputs'!K17*'DisruptRadar — Projeção men (5)'!G5 -> 4360 | L68: ='Model inputs'!L17*'DisruptRadar — Projeção men (5)'!G5 -> 4360 | M68: ='Model inputs'!M17*'DisruptRadar — Projeção men (5)'!G5 -> 4360 | N68: ='Model inputs'!N17*'DisruptRadar — Projeção men (5)'!G5 -> 4360 | O68: 0 | P68: 0 | Q68: 0 | R68: 0 | S68: 0 | T68: 0 | U68: 0 | V68: 0 | W68: 0 | X68: ='Model inputs'!X17*'DisruptRadar — Projeção men (5)'!G5 -> 0 | Y68: ='Model inputs'!Y17*'DisruptRadar — Projeção men (5)'!G5 -> 0
A69: Receita mensal — projeção Base (EUR) · Base — fixos 400 €/mês | B69: ='Model inputs'!B18*'Model inputs'!AA125 -> 0 | C69: ='Model inputs'!C18*'Model inputs'!AA125 -> 99 | D69: ='Model inputs'!D18*'Model inputs'!AA125 -> 396 | E69: ='Model inputs'!E18*'Model inputs'!AA125 -> 891 | F69: ='Model inputs'!F18*'Model inputs'!AA125 -> 1386 | G69: ='Model inputs'!G18*'Model inputs'!AA125 -> 1980 | H69: ='Model inputs'!H18*'Model inputs'!AA125 -> 2574 | I69: ='Model inputs'!I18*'Model inputs'!AA125 -> 3168 | J69: ='Model inputs'!J18*'Model inputs'!AA125 -> 3762 | K69: ='Model inputs'!K18*'Model inputs'!AA125 -> 3960 | L69: ='Model inputs'!L18*'Model inputs'!AA125 -> 3960 | M69: ='Model inputs'!M18*'Model inputs'!AA125 -> 3960 | N69: ='Model inputs'!N18*'Model inputs'!AA125 -> 3960 | O69: 0 | P69: 0 | Q69: 0 | R69: 0 | S69: 0 | T69: 0 | U69: 0 | V69: 0 | W69: 0 | X69: ='Model inputs'!X18*'Model inputs'!AA125 -> 0 | Y69: ='Model inputs'!Y18*'Model inputs'!AA125 -> 0
A70: Receita mensal — projeção Base (EUR) · Teste Pro 109 € — fixos 400 €/mês | B70: ='Model inputs'!B19*'DisruptRadar — Projeção men (5)'!F5 -> 0 | C70: ='Model inputs'!C19*'DisruptRadar — Projeção men (5)'!F5 -> 109 | D70: ='Model inputs'!D19*'DisruptRadar — Projeção men (5)'!F5 -> 436 | E70: ='Model inputs'!E19*'DisruptRadar — Projeção men (5)'!F5 -> 981 | F70: ='Model inputs'!F19*'DisruptRadar — Projeção men (5)'!F5 -> 1526 | G70: ='Model inputs'!G19*'DisruptRadar — Projeção men (5)'!F5 -> 2180 | H70: ='Model inputs'!H19*'DisruptRadar — Projeção men (5)'!F5 -> 2834 | I70: ='Model inputs'!I19*'DisruptRadar — Projeção men (5)'!F5 -> 3488 | J70: ='Model inputs'!J19*'DisruptRadar — Projeção men (5)'!F5 -> 4142 | K70: ='Model inputs'!K19*'DisruptRadar — Projeção men (5)'!F5 -> 4360 | L70: ='Model inputs'!L19*'DisruptRadar — Projeção men (5)'!F5 -> 4360 | M70: ='Model inputs'!M19*'DisruptRadar — Projeção men (5)'!F5 -> 4360 | N70: ='Model inputs'!N19*'DisruptRadar — Projeção men (5)'!F5 -> 4360 | O70: 0 | P70: 0 | Q70: 0 | R70: 0 | S70: 0 | T70: 0 | U70: 0 | V70: 0 | W70: 0 | X70: ='Model inputs'!X19*'DisruptRadar — Projeção men (5)'!F5 -> 0 | Y70: ='Model inputs'!Y19*'DisruptRadar — Projeção men (5)'!F5 -> 0
A71: Receita mensal — projeção Base (EUR) · Base — fixos 300 €/mês | B71: ='Model inputs'!B20*'Model inputs'!AA126 -> 0 | C71: ='Model inputs'!C20*'Model inputs'!AA126 -> 99 | D71: ='Model inputs'!D20*'Model inputs'!AA126 -> 396 | E71: ='Model inputs'!E20*'Model inputs'!AA126 -> 891 | F71: ='Model inputs'!F20*'Model inputs'!AA126 -> 1386 | G71: ='Model inputs'!G20*'Model inputs'!AA126 -> 1980 | H71: ='Model inputs'!H20*'Model inputs'!AA126 -> 2574 | I71: ='Model inputs'!I20*'Model inputs'!AA126 -> 3168 | J71: ='Model inputs'!J20*'Model inputs'!AA126 -> 3762 | K71: ='Model inputs'!K20*'Model inputs'!AA126 -> 3960 | L71: ='Model inputs'!L20*'Model inputs'!AA126 -> 3960 | M71: ='Model inputs'!M20*'Model inputs'!AA126 -> 3960 | N71: ='Model inputs'!N20*'Model inputs'!AA126 -> 3960 | O71: 0 | P71: 0 | Q71: 0 | R71: 0 | S71: 0 | T71: 0 | U71: 0 | V71: 0 | W71: 0 | X71: ='Model inputs'!X20*'Model inputs'!AA126 -> 0 | Y71: ='Model inputs'!Y20*'Model inputs'!AA126 -> 0
A72: Receita mensal — projeção Base (EUR) · Teste Pro 119 € — fixos 500 €/mês | B72: ='Model inputs'!B21*'DisruptRadar — Projeção men (5)'!J5 -> 0 | C72: ='Model inputs'!C21*'DisruptRadar — Projeção men (5)'!J5 -> 119 | D72: ='Model inputs'!D21*'DisruptRadar — Projeção men (5)'!J5 -> 476 | E72: ='Model inputs'!E21*'DisruptRadar — Projeção men (5)'!J5 -> 1071 | F72: ='Model inputs'!F21*'DisruptRadar — Projeção men (5)'!J5 -> 1666 | G72: ='Model inputs'!G21*'DisruptRadar — Projeção men (5)'!J5 -> 2380 | H72: ='Model inputs'!H21*'DisruptRadar — Projeção men (5)'!J5 -> 3094 | I72: ='Model inputs'!I21*'DisruptRadar — Projeção men (5)'!J5 -> 3808 | J72: ='Model inputs'!J21*'DisruptRadar — Projeção men (5)'!J5 -> 4522 | K72: ='Model inputs'!K21*'DisruptRadar — Projeção men (5)'!J5 -> 4760 | L72: ='Model inputs'!L21*'DisruptRadar — Projeção men (5)'!J5 -> 4760 | M72: ='Model inputs'!M21*'DisruptRadar — Projeção men (5)'!J5 -> 4760 | N72: ='Model inputs'!N21*'DisruptRadar — Projeção men (5)'!J5 -> 4760 | O72: 0 | P72: 0 | Q72: 0 | R72: 0 | S72: 0 | T72: 0 | U72: 0 | V72: 0 | W72: 0 | X72: ='Model inputs'!X21*'DisruptRadar — Projeção men (5)'!J5 -> 0 | Y72: ='Model inputs'!Y21*'DisruptRadar — Projeção men (5)'!J5 -> 0
A73: Receita mensal — projeção Base (EUR) · Teste Pro 119 € — fixos 400 €/mês | B73: ='Model inputs'!B22*'DisruptRadar — Projeção men (5)'!I5 -> 0 | C73: ='Model inputs'!C22*'DisruptRadar — Projeção men (5)'!I5 -> 119 | D73: ='Model inputs'!D22*'DisruptRadar — Projeção men (5)'!I5 -> 476 | E73: ='Model inputs'!E22*'DisruptRadar — Projeção men (5)'!I5 -> 1071 | F73: ='Model inputs'!F22*'DisruptRadar — Projeção men (5)'!I5 -> 1666 | G73: ='Model inputs'!G22*'DisruptRadar — Projeção men (5)'!I5 -> 2380 | H73: ='Model inputs'!H22*'DisruptRadar — Projeção men (5)'!I5 -> 3094 | I73: ='Model inputs'!I22*'DisruptRadar — Projeção men (5)'!I5 -> 3808 | J73: ='Model inputs'!J22*'DisruptRadar — Projeção men (5)'!I5 -> 4522 | K73: ='Model inputs'!K22*'DisruptRadar — Projeção men (5)'!I5 -> 4760 | L73: ='Model inputs'!L22*'DisruptRadar — Projeção men (5)'!I5 -> 4760 | M73: ='Model inputs'!M22*'DisruptRadar — Projeção men (5)'!I5 -> 4760 | N73: ='Model inputs'!N22*'DisruptRadar — Projeção men (5)'!I5 -> 4760 | O73: 0 | P73: 0 | Q73: 0 | R73: 0 | S73: 0 | T73: 0 | U73: 0 | V73: 0 | W73: 0 | X73: ='Model inputs'!X22*'DisruptRadar — Projeção men (5)'!I5 -> 0 | Y73: ='Model inputs'!Y22*'DisruptRadar — Projeção men (5)'!I5 -> 0
A74: Receita mensal — projeção Base (EUR) · Teste Pro 109 € — fixos 300 €/mês | B74: ='Model inputs'!B23*'DisruptRadar — Projeção men (5)'!E5 -> 0 | C74: ='Model inputs'!C23*'DisruptRadar — Projeção men (5)'!E5 -> 109 | D74: ='Model inputs'!D23*'DisruptRadar — Projeção men (5)'!E5 -> 436 | E74: ='Model inputs'!E23*'DisruptRadar — Projeção men (5)'!E5 -> 981 | F74: ='Model inputs'!F23*'DisruptRadar — Projeção men (5)'!E5 -> 1526 | G74: ='Model inputs'!G23*'DisruptRadar — Projeção men (5)'!E5 -> 2180 | H74: ='Model inputs'!H23*'DisruptRadar — Projeção men (5)'!E5 -> 2834 | I74: ='Model inputs'!I23*'DisruptRadar — Projeção men (5)'!E5 -> 3488 | J74: ='Model inputs'!J23*'DisruptRadar — Projeção men (5)'!E5 -> 4142 | K74: ='Model inputs'!K23*'DisruptRadar — Projeção men (5)'!E5 -> 4360 | L74: ='Model inputs'!L23*'DisruptRadar — Projeção men (5)'!E5 -> 4360 | M74: ='Model inputs'!M23*'DisruptRadar — Projeção men (5)'!E5 -> 4360 | N74: ='Model inputs'!N23*'DisruptRadar — Projeção men (5)'!E5 -> 4360 | O74: 0 | P74: 0 | Q74: 0 | R74: 0 | S74: 0 | T74: 0 | U74: 0 | V74: 0 | W74: 0 | X74: ='Model inputs'!X23*'DisruptRadar — Projeção men (5)'!E5 -> 0 | Y74: ='Model inputs'!Y23*'DisruptRadar — Projeção men (5)'!E5 -> 0
A75: Receita mensal — projeção Base (EUR) · Teste Pro 119 € — fixos 300 €/mês | B75: ='Model inputs'!B24*'DisruptRadar — Projeção men (5)'!H5 -> 0 | C75: ='Model inputs'!C24*'DisruptRadar — Projeção men (5)'!H5 -> 119 | D75: ='Model inputs'!D24*'DisruptRadar — Projeção men (5)'!H5 -> 476 | E75: ='Model inputs'!E24*'DisruptRadar — Projeção men (5)'!H5 -> 1071 | F75: ='Model inputs'!F24*'DisruptRadar — Projeção men (5)'!H5 -> 1666 | G75: ='Model inputs'!G24*'DisruptRadar — Projeção men (5)'!H5 -> 2380 | H75: ='Model inputs'!H24*'DisruptRadar — Projeção men (5)'!H5 -> 3094 | I75: ='Model inputs'!I24*'DisruptRadar — Projeção men (5)'!H5 -> 3808 | J75: ='Model inputs'!J24*'DisruptRadar — Projeção men (5)'!H5 -> 4522 | K75: ='Model inputs'!K24*'DisruptRadar — Projeção men (5)'!H5 -> 4760 | L75: ='Model inputs'!L24*'DisruptRadar — Projeção men (5)'!H5 -> 4760 | M75: ='Model inputs'!M24*'DisruptRadar — Projeção men (5)'!H5 -> 4760 | N75: ='Model inputs'!N24*'DisruptRadar — Projeção men (5)'!H5 -> 4760 | O75: 0 | P75: 0 | Q75: 0 | R75: 0 | S75: 0 | T75: 0 | U75: 0 | V75: 0 | W75: 0 | X75: ='Model inputs'!X24*'DisruptRadar — Projeção men (5)'!H5 -> 0 | Y75: ='Model inputs'!Y24*'DisruptRadar — Projeção men (5)'!H5 -> 0
A76: Caixa inicial do mês — projeção Base (EUR) · Caixa final — projeção Base (EUR) · DisruptRadar — Projeção mensal · Projeção mensal Base — clientes, resultado e caixa · Base · Base | B76: =IF('Model inputs'!B15="","",'Model inputs'!B15) -> -1000 | C76: =IF('Model inputs'!C15="","",'Model inputs'!C15) -> 20000 | D76: =IF('Model inputs'!D15="","",'Model inputs'!D15) -> 19569 | E76: =IF('Model inputs'!E15="","",'Model inputs'!E15) -> 19345 | F76: =IF('Model inputs'!F15="","",'Model inputs'!F15) -> 19466 | G76: =IF('Model inputs'!G15="","",'Model inputs'!G15) -> 19932 | H76: =IF('Model inputs'!H15="","",'Model inputs'!H15) -> 20812 | I76: =IF('Model inputs'!I15="","",'Model inputs'!I15) -> 22106 | ... N76: =IF('Model inputs'!N15="","",'Model inputs'!N15) -> 32716 | O76: 0 | P76: 0 | Q76: 0 | R76: 0 | S76: 0 | T76: 0 | U76: 0 | V76: 0 | W76: =IF('Model inputs'!W15="","",'Model inputs'!W15) -> 0 | X76: =IF('Model inputs'!X15="","",'Model inputs'!X15) -> 0 | Y76: =IF('Model inputs'!Y15="","",'Model inputs'!Y15) -> -500
A77: Caixa inicial do mês — projeção Base (EUR) · Caixa final — projeção Base (EUR) · Base — fixos 400 €/mês · Base — fixos 400 €/mês | B77: =IF(IF(IF(ISERROR(DATE(2026,12,1)=DATE(YEAR('Model inputs'!AA122),MONTH('Model inputs'!AA122),1)),DATE(2026,12,1)=DATE(YEAR('Model inputs'!AA122),MONTH('Model inputs'!AA122),1),IF(DATE(YEAR('Model inputs'!AA122),MONTH('Model inputs'!AA122),1)="","",DATE(2026,12,1)=DATE(YEAR('Model inputs'!AA122),MONTH('Model inputs'!AA122),1)))="",FALSE,IF(ISERROR(DATE(2026,12,1)=DATE(YEAR('Model inputs'!AA122),MONTH('Model inputs'!AA122),1)),DATE(2026,12,1)=DATE(YEAR('Model inputs'!AA122),MONTH('Model inputs'!AA122),1),IF(DATE(YEAR('Model inputs'!AA122),MONTH('Model inputs'!AA122),1)="","",DATE(2026,12,1)=DATE(YEAR('Model inputs'!AA122),MONTH('Model inputs'!AA122),1)))),IF('Model inputs'!AA107="","",'Model inputs'!AA107),IF('Model inputs'!Y8="","",'Model inputs'!Y8)) -> -800 | C77: =IF(IF(IF(ISERROR(DATE(2027,1,1)=DATE(YEAR('Model inputs'!AA122),MONTH('Model inputs'!AA122),1)),DATE(2027,1,1)=DATE(YEAR('Model inputs'!AA122),MONTH('Model inputs'!AA122),1),IF(DATE(YEAR('Model inputs'!AA122),MONTH('Model inputs'!AA122),1)="","",DATE(2027,1,1)=DATE(YEAR('Model inputs'!AA122),MONTH('Model inputs'!AA122),1)))="",FALSE,IF(ISERROR(DATE(2027,1,1)=DATE(YEAR('Model inputs'!AA122),MONTH('Model inputs'!AA122),1)),DATE(2027,1,1)=DATE(YEAR('Model inputs'!AA122),MONTH('Model inputs'!AA122),1),IF(DATE(YEAR('Model inputs'!AA122),MONTH('Model inputs'!AA122),1)="","",DATE(2027,1,1)=DATE(YEAR('Model inputs'!AA122),MONTH('Model inputs'!AA122),1)))),IF('Model inputs'!AA107="","",'Model inputs'!AA107),IF('Model inputs'!B8="","",'Model inputs'!B8)) -> 20000 | D77: =IF(IF(IF(ISERROR(DATE(2027,2,1)=DATE(YEAR('Model inputs'!AA122),MONTH('Model inputs'!AA122),1)),DATE(2027,2,1)=DATE(YEAR('Model inputs'!AA122),MONTH('Model inputs'!AA122),1),IF(DATE(YEAR('Model inputs'!AA122),MONTH('Model inputs'!AA122),1)="","",DATE(2027,2,1)=DATE(YEAR('Model inputs'!AA122),MONTH('Model inputs'!AA122),1)))="",FALSE,IF(ISERROR(DATE(2027,2,1)=DATE(YEAR('Model inputs'!AA122),MONTH('Model inputs'!AA122),1)),DATE(2027,2,1)=DATE(YEAR('Model inputs'!AA122),MONTH('Model inputs'!AA122),1),IF(DATE(YEAR('Model inputs'!AA122),MONTH('Model inputs'!AA122),1)="","",DATE(2027,2,1)=DATE(YEAR('Model inputs'!AA122),MONTH('Model inputs'!AA122),1)))),IF('Model inputs'!AA107="","",'Model inputs'!AA107),IF('Model inputs'!C8="","",'Model inputs'!C8)) -> 19669 | E77: =IF(IF(IF(ISERROR(DATE(2027,3,1)=DATE(YEAR('Model inputs'!AA122),MONTH('Model inputs'!AA122),1)),DATE(2027,3,1)=DATE(YEAR('Model inputs'!AA122),MONTH('Model inputs'!AA122),1),IF(DATE(YEAR('Model inputs'!AA122),MONTH('Model inputs'!AA122),1)="","",DATE(2027,3,1)=DATE(YEAR('Model inputs'!AA122),MONTH('Model inputs'!AA122),1)))="",FALSE,IF(ISERROR(DATE(2027,3,1)=DATE(YEAR('Model inputs'!AA122),MONTH('Model inputs'!AA122),1)),DATE(2027,3,1)=DATE(YEAR('Model inputs'!AA122),MONTH('Model inputs'!AA122),1),IF(DATE(YEAR('Model inputs'!AA122),MONTH('Model inputs'!AA122),1)="","",DATE(2027,3,1)=DATE(YEAR('Model inputs'!AA122),MONTH('Model inputs'!AA122),1)))),IF('Model inputs'!AA107="","",'Model inputs'!AA107),IF('Model inputs'!D8="","",'Model inputs'!D8)) -> 19545 | F77: =IF(IF(IF(ISERROR(DATE(2027,4,1)=DATE(YEAR('Model inputs'!AA122),MONTH('Model inputs'!AA122),1)),DATE(2027,4,1)=DATE(YEAR('Model inputs'!AA122),MONTH('Model inputs'!AA122),1),IF(DATE(YEAR('Model inputs'!AA122),MONTH('Model inputs'!AA122),1)="","",DATE(2027,4,1)=DATE(YEAR('Model inputs'!AA122),MONTH('Model inputs'!AA122),1)))="",FALSE,IF(ISERROR(DATE(2027,4,1)=DATE(YEAR('Model inputs'!AA122),MONTH('Model inputs'!AA122),1)),DATE(2027,4,1)=DATE(YEAR('Model inputs'!AA122),MONTH('Model inputs'!AA122),1),IF(DATE(YEAR('Model inputs'!AA122),MONTH('Model inputs'!AA122),1)="","",DATE(2027,4,1)=DATE(YEAR('Model inputs'!AA122),MONTH('Model inputs'!AA122),1)))),IF('Model inputs'!AA107="","",'Model inputs'!AA107),IF('Model inputs'!E8="","",'Model inputs'!E8)) -> 19766 | G77: =IF(IF(IF(ISERROR(DATE(2027,5,1)=DATE(YEAR('Model inputs'!AA122),MONTH('Model inputs'!AA122),1)),DATE(2027,5,1)=DATE(YEAR('Model inputs'!AA122),MONTH('Model inputs'!AA122),1),IF(DATE(YEAR('Model inputs'!AA122),MONTH('Model inputs'!AA122),1)="","",DATE(2027,5,1)=DATE(YEAR('Model inputs'!AA122),MONTH('Model inputs'!AA122),1)))="",FALSE,IF(ISERROR(DATE(2027,5,1)=DATE(YEAR('Model inputs'!AA122),MONTH('Model inputs'!AA122),1)),DATE(2027,5,1)=DATE(YEAR('Model inputs'!AA122),MONTH('Model inputs'!AA122),1),IF(DATE(YEAR('Model inputs'!AA122),MONTH('Model inputs'!AA122),1)="","",DATE(2027,5,1)=DATE(YEAR('Model inputs'!AA122),MONTH('Model inputs'!AA122),1)))),IF('Model inputs'!AA107="","",'Model inputs'!AA107),IF('Model inputs'!F8="","",'Model inputs'!F8)) -> 20332 | H77: =IF(IF(IF(ISERROR(DATE(2027,6,1)=DATE(YEAR('Model inputs'!AA122),MONTH('Model inputs'!AA122),1)),DATE(2027,6,1)=DATE(YEAR('Model inputs'!AA122),MONTH('Model inputs'!AA122),1),IF(DATE(YEAR('Model inputs'!AA122),MONTH('Model inputs'!AA122),1)="","",DATE(2027,6,1)=DATE(YEAR('Model inputs'!AA122),MONTH('Model inputs'!AA122),1)))="",FALSE,IF(ISERROR(DATE(2027,6,1)=DATE(YEAR('Model inputs'!AA122),MONTH('Model inputs'!AA122),1)),DATE(2027,6,1)=DATE(YEAR('Model inputs'!AA122),MONTH('Model inputs'!AA122),1),IF(DATE(YEAR('Model inputs'!AA122),MONTH('Model inputs'!AA122),1)="","",DATE(2027,6,1)=DATE(YEAR('Model inputs'!AA122),MONTH('Model inputs'!AA122),1)))),IF('Model inputs'!AA107="","",'Model inputs'!AA107),IF('Model inputs'!G8="","",'Model inputs'!G8)) -> 21312 | I77: =IF(IF(IF(ISERROR(DATE(2027,7,1)=DATE(YEAR('Model inputs'!AA122),MONTH('Model inputs'!AA122),1)),DATE(2027,7,1)=DATE(YEAR('Model inputs'!AA122),MONTH('Model inputs'!AA122),1),IF(DATE(YEAR('Model inputs'!AA122),MONTH('Model inputs'!AA122),1)="","",DATE(2027,7,1)=DATE(YEAR('Model inputs'!AA122),MONTH('Model inputs'!AA122),1)))="",FALSE,IF(ISERROR(DATE(2027,7,1)=DATE(YEAR('Model inputs'!AA122),MONTH('Model inputs'!AA122),1)),DATE(2027,7,1)=DATE(YEAR('Model inputs'!AA122),MONTH('Model inputs'!AA122),1),IF(DATE(YEAR('Model inputs'!AA122),MONTH('Model inputs'!AA122),1)="","",DATE(2027,7,1)=DATE(YEAR('Model inputs'!AA122),MONTH('Model inputs'!AA122),1)))),IF('Model inputs'!AA107="","",'Model inputs'!AA107),IF('Model inputs'!H8="","",'Model inputs'!H8)) -> 22706 | J77: =IF(IF(IF(ISERROR(DATE(2027,8,1)=DATE(YEAR('Model inputs'!AA122),MONTH('Model inputs'!AA122),1)),DATE(2027,8,1)=DATE(YEAR('Model inputs'!AA122),MONTH('Model inputs'!AA122),1),IF(DATE(YEAR('Model inputs'!AA122),MONTH('Model inputs'!AA122),1)="","",DATE(2027,8,1)=DATE(YEAR('Model inputs'!AA122),MONTH('Model inputs'!AA122),1)))="",FALSE,IF(ISERROR(DATE(2027,8,1)=DATE(YEAR('Model inputs'!AA122),MONTH('Model inputs'!AA122),1)),DATE(2027,8,1)=DATE(YEAR('Model inputs'!AA122),MONTH('Model inputs'!AA122),1),IF(DATE(YEAR('Model inputs'!AA122),MONTH('Model inputs'!AA122),1)="","",DATE(2027,8,1)=DATE(YEAR('Model inputs'!AA122),MONTH('Model inputs'!AA122),1)))),IF('Model inputs'!AA107="","",'Model inputs'!AA107),IF('Model inputs'!I8="","",'Model inputs'!I8)) -> 24514 | K77: =IF(IF(IF(ISERROR(DATE(2027,9,1)=DATE(YEAR('Model inputs'!AA122),MONTH('Model inputs'!AA122),1)),DATE(2027,9,1)=DATE(YEAR('Model inputs'!AA122),MONTH('Model inputs'!AA122),1),IF(DATE(YEAR('Model inputs'!AA122),MONTH('Model inputs'!AA122),1)="","",DATE(2027,9,1)=DATE(YEAR('Model inputs'!AA122),MONTH('Model inputs'!AA122),1)))="",FALSE,IF(ISERROR(DATE(2027,9,1)=DATE(YEAR('Model inputs'!AA122),MONTH('Model inputs'!AA122),1)),DATE(2027,9,1)=DATE(YEAR('Model inputs'!AA122),MONTH('Model inputs'!AA122),1),IF(DATE(YEAR('Model inputs'!AA122),MONTH('Model inputs'!AA122),1)="","",DATE(2027,9,1)=DATE(YEAR('Model inputs'!AA122),MONTH('Model inputs'!AA122),1)))),IF('Model inputs'!AA107="","",'Model inputs'!AA107),IF('Model inputs'!J8="","",'Model inputs'!J8)) -> 26736 | L77: =IF(IF(IF(ISERROR(DATE(2027,10,1)=DATE(YEAR('Model inputs'!AA122),MONTH('Model inputs'!AA122),1)),DATE(2027,10,1)=DATE(YEAR('Model inputs'!AA122),MONTH('Model inputs'!AA122),1),IF(DATE(YEAR('Model inputs'!AA122),MONTH('Model inputs'!AA122),1)="","",DATE(2027,10,1)=DATE(YEAR('Model inputs'!AA122),MONTH('Model inputs'!AA122),1)))="",FALSE,IF(ISERROR(DATE(2027,10,1)=DATE(YEAR('Model inputs'!AA122),MONTH('Model inputs'!AA122),1)),DATE(2027,10,1)=DATE(YEAR('Model inputs'!AA122),MONTH('Model inputs'!AA122),1),IF(DATE(YEAR('Model inputs'!AA122),MONTH('Model inputs'!AA122),1)="","",DATE(2027,10,1)=DATE(YEAR('Model inputs'!AA122),MONTH('Model inputs'!AA122),1)))),IF('Model inputs'!AA107="","",'Model inputs'!AA107),IF('Model inputs'!K8="","",'Model inputs'!K8)) -> 29096 | M77: =IF(IF(IF(ISERROR(DATE(2027,11,1)=DATE(YEAR('Model inputs'!AA122),MONTH('Model inputs'!AA122),1)),DATE(2027,11,1)=DATE(YEAR('Model inputs'!AA122),MONTH('Model inputs'!AA122),1),IF(DATE(YEAR('Model inputs'!AA122),MONTH('Model inputs'!AA122),1)="","",DATE(2027,11,1)=DATE(YEAR('Model inputs'!AA122),MONTH('Model inputs'!AA122),1)))="",FALSE,IF(ISERROR(DATE(2027,11,1)=DATE(YEAR('Model inputs'!AA122),MONTH('Model inputs'!AA122),1)),DATE(2027,11,1)=DATE(YEAR('Model inputs'!AA122),MONTH('Model inputs'!AA122),1),IF(DATE(YEAR('Model inputs'!AA122),MONTH('Model inputs'!AA122),1)="","",DATE(2027,11,1)=DATE(YEAR('Model inputs'!AA122),MONTH('Model inputs'!AA122),1)))),IF('Model inputs'!AA107="","",'Model inputs'!AA107),IF('Model inputs'!L8="","",'Model inputs'!L8)) -> 31456 | N77: =IF(IF(IF(ISERROR(DATE(2027,12,1)=DATE(YEAR('Model inputs'!AA122),MONTH('Model inputs'!AA122),1)),DATE(2027,12,1)=DATE(YEAR('Model inputs'!AA122),MONTH('Model inputs'!AA122),1),IF(DATE(YEAR('Model inputs'!AA122),MONTH('Model inputs'!AA122),1)="","",DATE(2027,12,1)=DATE(YEAR('Model inputs'!AA122),MONTH('Model inputs'!AA122),1)))="",FALSE,IF(ISERROR(DATE(2027,12,1)=DATE(YEAR('Model inputs'!AA122),MONTH('Model inputs'!AA122),1)),DATE(2027,12,1)=DATE(YEAR('Model inputs'!AA122),MONTH('Model inputs'!AA122),1),IF(DATE(YEAR('Model inputs'!AA122),MONTH('Model inputs'!AA122),1)="","",DATE(2027,12,1)=DATE(YEAR('Model inputs'!AA122),MONTH('Model inputs'!AA122),1)))),IF('Model inputs'!AA107="","",'Model inputs'!AA107),IF('Model inputs'!M8="","",'Model inputs'!M8)) -> 33816 | O77: 0 | P77: 0 | Q77: 0 | R77: 0 | S77: 0 | T77: 0 | U77: 0 | V77: 0 | W77: 0 | X77: =IF(IF(IF(ISERROR(DATE(2026,10,1)=DATE(YEAR('Model inputs'!AA122),MONTH('Model inputs'!AA122),1)),DATE(2026,10,1)=DATE(YEAR('Model inputs'!AA122),MONTH('Model inputs'!AA122),1),IF(DATE(YEAR('Model inputs'!AA122),MONTH('Model inputs'!AA122),1)="","",DATE(2026,10,1)=DATE(YEAR('Model inputs'!AA122),MONTH('Model inputs'!AA122),1)))="",FALSE,IF(ISERROR(DATE(2026,10,1)=DATE(YEAR('Model inputs'!AA122),MONTH('Model inputs'!AA122),1)),DATE(2026,10,1)=DATE(YEAR('Model inputs'!AA122),MONTH('Model inputs'!AA122),1),IF(DATE(YEAR('Model inputs'!AA122),MONTH('Model inputs'!AA122),1)="","",DATE(2026,10,1)=DATE(YEAR('Model inputs'!AA122),MONTH('Model inputs'!AA122),1)))),IF('Model inputs'!AA107="","",'Model inputs'!AA107),IF('Model inputs'!W8="","",'Model inputs'!W8)) -> 0 | Y77: =IF(IF(IF(ISERROR(DATE(2026,11,1)=DATE(YEAR('Model inputs'!AA122),MONTH('Model inputs'!AA122),1)),DATE(2026,11,1)=DATE(YEAR('Model inputs'!AA122),MONTH('Model inputs'!AA122),1),IF(DATE(YEAR('Model inputs'!AA122),MONTH('Model inputs'!AA122),1)="","",DATE(2026,11,1)=DATE(YEAR('Model inputs'!AA122),MONTH('Model inputs'!AA122),1)))="",FALSE,IF(ISERROR(DATE(2026,11,1)=DATE(YEAR('Model inputs'!AA122),MONTH('Model inputs'!AA122),1)),DATE(2026,11,1)=DATE(YEAR('Model inputs'!AA122),MONTH('Model inputs'!AA122),1),IF(DATE(YEAR('Model inputs'!AA122),MONTH('Model inputs'!AA122),1)="","",DATE(2026,11,1)=DATE(YEAR('Model inputs'!AA122),MONTH('Model inputs'!AA122),1)))),IF('Model inputs'!AA107="","",'Model inputs'!AA107),IF('Model inputs'!X8="","",'Model inputs'!X8)) -> -400
A78: Caixa inicial do mês — projeção Base (EUR) · Caixa final — projeção Base (EUR) · Base — fixos 300 €/mês · Base — fixos 300 €/mês | B78: =IF(IF(IF(ISERROR(DATE(2026,12,1)=DATE(YEAR('Model inputs'!AA123),MONTH('Model inputs'!AA123),1)),DATE(2026,12,1)=DATE(YEAR('Model inputs'!AA123),MONTH('Model inputs'!AA123),1),IF(DATE(YEAR('Model inputs'!AA123),MONTH('Model inputs'!AA123),1)="","",DATE(2026,12,1)=DATE(YEAR('Model inputs'!AA123),MONTH('Model inputs'!AA123),1)))="",FALSE,IF(ISERROR(DATE(2026,12,1)=DATE(YEAR('Model inputs'!AA123),MONTH('Model inputs'!AA123),1)),DATE(2026,12,1)=DATE(YEAR('Model inputs'!AA123),MONTH('Model inputs'!AA123),1),IF(DATE(YEAR('Model inputs'!AA123),MONTH('Model inputs'!AA123),1)="","",DATE(2026,12,1)=DATE(YEAR('Model inputs'!AA123),MONTH('Model inputs'!AA123),1)))),IF('Model inputs'!AA108="","",'Model inputs'!AA108),IF('Model inputs'!Y9="","",'Model inputs'!Y9)) -> -600 | C78: =IF(IF(IF(ISERROR(DATE(2027,1,1)=DATE(YEAR('Model inputs'!AA123),MONTH('Model inputs'!AA123),1)),DATE(2027,1,1)=DATE(YEAR('Model inputs'!AA123),MONTH('Model inputs'!AA123),1),IF(DATE(YEAR('Model inputs'!AA123),MONTH('Model inputs'!AA123),1)="","",DATE(2027,1,1)=DATE(YEAR('Model inputs'!AA123),MONTH('Model inputs'!AA123),1)))="",FALSE,IF(ISERROR(DATE(2027,1,1)=DATE(YEAR('Model inputs'!AA123),MONTH('Model inputs'!AA123),1)),DATE(2027,1,1)=DATE(YEAR('Model inputs'!AA123),MONTH('Model inputs'!AA123),1),IF(DATE(YEAR('Model inputs'!AA123),MONTH('Model inputs'!AA123),1)="","",DATE(2027,1,1)=DATE(YEAR('Model inputs'!AA123),MONTH('Model inputs'!AA123),1)))),IF('Model inputs'!AA108="","",'Model inputs'!AA108),IF('Model inputs'!B9="","",'Model inputs'!B9)) -> 20000 | D78: =IF(IF(IF(ISERROR(DATE(2027,2,1)=DATE(YEAR('Model inputs'!AA123),MONTH('Model inputs'!AA123),1)),DATE(2027,2,1)=DATE(YEAR('Model inputs'!AA123),MONTH('Model inputs'!AA123),1),IF(DATE(YEAR('Model inputs'!AA123),MONTH('Model inputs'!AA123),1)="","",DATE(2027,2,1)=DATE(YEAR('Model inputs'!AA123),MONTH('Model inputs'!AA123),1)))="",FALSE,IF(ISERROR(DATE(2027,2,1)=DATE(YEAR('Model inputs'!AA123),MONTH('Model inputs'!AA123),1)),DATE(2027,2,1)=DATE(YEAR('Model inputs'!AA123),MONTH('Model inputs'!AA123),1),IF(DATE(YEAR('Model inputs'!AA123),MONTH('Model inputs'!AA123),1)="","",DATE(2027,2,1)=DATE(YEAR('Model inputs'!AA123),MONTH('Model inputs'!AA123),1)))),IF('Model inputs'!AA108="","",'Model inputs'!AA108),IF('Model inputs'!C9="","",'Model inputs'!C9)) -> 19769 | E78: =IF(IF(IF(ISERROR(DATE(2027,3,1)=DATE(YEAR('Model inputs'!AA123),MONTH('Model inputs'!AA123),1)),DATE(2027,3,1)=DATE(YEAR('Model inputs'!AA123),MONTH('Model inputs'!AA123),1),IF(DATE(YEAR('Model inputs'!AA123),MONTH('Model inputs'!AA123),1)="","",DATE(2027,3,1)=DATE(YEAR('Model inputs'!AA123),MONTH('Model inputs'!AA123),1)))="",FALSE,IF(ISERROR(DATE(2027,3,1)=DATE(YEAR('Model inputs'!AA123),MONTH('Model inputs'!AA123),1)),DATE(2027,3,1)=DATE(YEAR('Model inputs'!AA123),MONTH('Model inputs'!AA123),1),IF(DATE(YEAR('Model inputs'!AA123),MONTH('Model inputs'!AA123),1)="","",DATE(2027,3,1)=DATE(YEAR('Model inputs'!AA123),MONTH('Model inputs'!AA123),1)))),IF('Model inputs'!AA108="","",'Model inputs'!AA108),IF('Model inputs'!D9="","",'Model inputs'!D9)) -> 19745 | F78: =IF(IF(IF(ISERROR(DATE(2027,4,1)=DATE(YEAR('Model inputs'!AA123),MONTH('Model inputs'!AA123),1)),DATE(2027,4,1)=DATE(YEAR('Model inputs'!AA123),MONTH('Model inputs'!AA123),1),IF(DATE(YEAR('Model inputs'!AA123),MONTH('Model inputs'!AA123),1)="","",DATE(2027,4,1)=DATE(YEAR('Model inputs'!AA123),MONTH('Model inputs'!AA123),1)))="",FALSE,IF(ISERROR(DATE(2027,4,1)=DATE(YEAR('Model inputs'!AA123),MONTH('Model inputs'!AA123),1)),DATE(2027,4,1)=DATE(YEAR('Model inputs'!AA123),MONTH('Model inputs'!AA123),1),IF(DATE(YEAR('Model inputs'!AA123),MONTH('Model inputs'!AA123),1)="","",DATE(2027,4,1)=DATE(YEAR('Model inputs'!AA123),MONTH('Model inputs'!AA123),1)))),IF('Model inputs'!AA108="","",'Model inputs'!AA108),IF('Model inputs'!E9="","",'Model inputs'!E9)) -> 20066 | G78: =IF(IF(IF(ISERROR(DATE(2027,5,1)=DATE(YEAR('Model inputs'!AA123),MONTH('Model inputs'!AA123),1)),DATE(2027,5,1)=DATE(YEAR('Model inputs'!AA123),MONTH('Model inputs'!AA123),1),IF(DATE(YEAR('Model inputs'!AA123),MONTH('Model inputs'!AA123),1)="","",DATE(2027,5,1)=DATE(YEAR('Model inputs'!AA123),MONTH('Model inputs'!AA123),1)))="",FALSE,IF(ISERROR(DATE(2027,5,1)=DATE(YEAR('Model inputs'!AA123),MONTH('Model inputs'!AA123),1)),DATE(2027,5,1)=DATE(YEAR('Model inputs'!AA123),MONTH('Model inputs'!AA123),1),IF(DATE(YEAR('Model inputs'!AA123),MONTH('Model inputs'!AA123),1)="","",DATE(2027,5,1)=DATE(YEAR('Model inputs'!AA123),MONTH('Model inputs'!AA123),1)))),IF('Model inputs'!AA108="","",'Model inputs'!AA108),IF('Model inputs'!F9="","",'Model inputs'!F9)) -> 20732 | H78: =IF(IF(IF(ISERROR(DATE(2027,6,1)=DATE(YEAR('Model inputs'!AA123),MONTH('Model inputs'!AA123),1)),DATE(2027,6,1)=DATE(YEAR('Model inputs'!AA123),MONTH('Model inputs'!AA123),1),IF(DATE(YEAR('Model inputs'!AA123),MONTH('Model inputs'!AA123),1)="","",DATE(2027,6,1)=DATE(YEAR('Model inputs'!AA123),MONTH('Model inputs'!AA123),1)))="",FALSE,IF(ISERROR(DATE(2027,6,1)=DATE(YEAR('Model inputs'!AA123),MONTH('Model inputs'!AA123),1)),DATE(2027,6,1)=DATE(YEAR('Model inputs'!AA123),MONTH('Model inputs'!AA123),1),IF(DATE(YEAR('Model inputs'!AA123),MONTH('Model inputs'!AA123),1)="","",DATE(2027,6,1)=DATE(YEAR('Model inputs'!AA123),MONTH('Model inputs'!AA123),1)))),IF('Model inputs'!AA108="","",'Model inputs'!AA108),IF('Model inputs'!G9="","",'Model inputs'!G9)) -> 21812 | I78: =IF(IF(IF(ISERROR(DATE(2027,7,1)=DATE(YEAR('Model inputs'!AA123),MONTH('Model inputs'!AA123),1)),DATE(2027,7,1)=DATE(YEAR('Model inputs'!AA123),MONTH('Model inputs'!AA123),1),IF(DATE(YEAR('Model inputs'!AA123),MONTH('Model inputs'!AA123),1)="","",DATE(2027,7,1)=DATE(YEAR('Model inputs'!AA123),MONTH('Model inputs'!AA123),1)))="",FALSE,IF(ISERROR(DATE(2027,7,1)=DATE(YEAR('Model inputs'!AA123),MONTH('Model inputs'!AA123),1)),DATE(2027,7,1)=DATE(YEAR('Model inputs'!AA123),MONTH('Model inputs'!AA123),1),IF(DATE(YEAR('Model inputs'!AA123),MONTH('Model inputs'!AA123),1)="","",DATE(2027,7,1)=DATE(YEAR('Model inputs'!AA123),MONTH('Model inputs'!AA123),1)))),IF('Model inputs'!AA108="","",'Model inputs'!AA108),IF('Model inputs'!H9="","",'Model inputs'!H9)) -> 23306 | J78: =IF(IF(IF(ISERROR(DATE(2027,8,1)=DATE(YEAR('Model inputs'!AA123),MONTH('Model inputs'!AA123),1)),DATE(2027,8,1)=DATE(YEAR('Model inputs'!AA123),MONTH('Model inputs'!AA123),1),IF(DATE(YEAR('Model inputs'!AA123),MONTH('Model inputs'!AA123),1)="","",DATE(2027,8,1)=DATE(YEAR('Model inputs'!AA123),MONTH('Model inputs'!AA123),1)))="",FALSE,IF(ISERROR(DATE(2027,8,1)=DATE(YEAR('Model inputs'!AA123),MONTH('Model inputs'!AA123),1)),DATE(2027,8,1)=DATE(YEAR('Model inputs'!AA123),MONTH('Model inputs'!AA123),1),IF(DATE(YEAR('Model inputs'!AA123),MONTH('Model inputs'!AA123),1)="","",DATE(2027,8,1)=DATE(YEAR('Model inputs'!AA123),MONTH('Model inputs'!AA123),1)))),IF('Model inputs'!AA108="","",'Model inputs'!AA108),IF('Model inputs'!I9="","",'Model inputs'!I9)) -> 25214 | K78: =IF(IF(IF(ISERROR(DATE(2027,9,1)=DATE(YEAR('Model inputs'!AA123),MONTH('Model inputs'!AA123),1)),DATE(2027,9,1)=DATE(YEAR('Model inputs'!AA123),MONTH('Model inputs'!AA123),1),IF(DATE(YEAR('Model inputs'!AA123),MONTH('Model inputs'!AA123),1)="","",DATE(2027,9,1)=DATE(YEAR('Model inputs'!AA123),MONTH('Model inputs'!AA123),1)))="",FALSE,IF(ISERROR(DATE(2027,9,1)=DATE(YEAR('Model inputs'!AA123),MONTH('Model inputs'!AA123),1)),DATE(2027,9,1)=DATE(YEAR('Model inputs'!AA123),MONTH('Model inputs'!AA123),1),IF(DATE(YEAR('Model inputs'!AA123),MONTH('Model inputs'!AA123),1)="","",DATE(2027,9,1)=DATE(YEAR('Model inputs'!AA123),MONTH('Model inputs'!AA123),1)))),IF('Model inputs'!AA108="","",'Model inputs'!AA108),IF('Model inputs'!J9="","",'Model inputs'!J9)) -> 27536 | L78: =IF(IF(IF(ISERROR(DATE(2027,10,1)=DATE(YEAR('Model inputs'!AA123),MONTH('Model inputs'!AA123),1)),DATE(2027,10,1)=DATE(YEAR('Model inputs'!AA123),MONTH('Model inputs'!AA123),1),IF(DATE(YEAR('Model inputs'!AA123),MONTH('Model inputs'!AA123),1)="","",DATE(2027,10,1)=DATE(YEAR('Model inputs'!AA123),MONTH('Model inputs'!AA123),1)))="",FALSE,IF(ISERROR(DATE(2027,10,1)=DATE(YEAR('Model inputs'!AA123),MONTH('Model inputs'!AA123),1)),DATE(2027,10,1)=DATE(YEAR('Model inputs'!AA123),MONTH('Model inputs'!AA123),1),IF(DATE(YEAR('Model inputs'!AA123),MONTH('Model inputs'!AA123),1)="","",DATE(2027,10,1)=DATE(YEAR('Model inputs'!AA123),MONTH('Model inputs'!AA123),1)))),IF('Model inputs'!AA108="","",'Model inputs'!AA108),IF('Model inputs'!K9="","",'Model inputs'!K9)) -> 29996 | M78: =IF(IF(IF(ISERROR(DATE(2027,11,1)=DATE(YEAR('Model inputs'!AA123),MONTH('Model inputs'!AA123),1)),DATE(2027,11,1)=DATE(YEAR('Model inputs'!AA123),MONTH('Model inputs'!AA123),1),IF(DATE(YEAR('Model inputs'!AA123),MONTH('Model inputs'!AA123),1)="","",DATE(2027,11,1)=DATE(YEAR('Model inputs'!AA123),MONTH('Model inputs'!AA123),1)))="",FALSE,IF(ISERROR(DATE(2027,11,1)=DATE(YEAR('Model inputs'!AA123),MONTH('Model inputs'!AA123),1)),DATE(2027,11,1)=DATE(YEAR('Model inputs'!AA123),MONTH('Model inputs'!AA123),1),IF(DATE(YEAR('Model inputs'!AA123),MONTH('Model inputs'!AA123),1)="","",DATE(2027,11,1)=DATE(YEAR('Model inputs'!AA123),MONTH('Model inputs'!AA123),1)))),IF('Model inputs'!AA108="","",'Model inputs'!AA108),IF('Model inputs'!L9="","",'Model inputs'!L9)) -> 32456 | N78: =IF(IF(IF(ISERROR(DATE(2027,12,1)=DATE(YEAR('Model inputs'!AA123),MONTH('Model inputs'!AA123),1)),DATE(2027,12,1)=DATE(YEAR('Model inputs'!AA123),MONTH('Model inputs'!AA123),1),IF(DATE(YEAR('Model inputs'!AA123),MONTH('Model inputs'!AA123),1)="","",DATE(2027,12,1)=DATE(YEAR('Model inputs'!AA123),MONTH('Model inputs'!AA123),1)))="",FALSE,IF(ISERROR(DATE(2027,12,1)=DATE(YEAR('Model inputs'!AA123),MONTH('Model inputs'!AA123),1)),DATE(2027,12,1)=DATE(YEAR('Model inputs'!AA123),MONTH('Model inputs'!AA123),1),IF(DATE(YEAR('Model inputs'!AA123),MONTH('Model inputs'!AA123),1)="","",DATE(2027,12,1)=DATE(YEAR('Model inputs'!AA123),MONTH('Model inputs'!AA123),1)))),IF('Model inputs'!AA108="","",'Model inputs'!AA108),IF('Model inputs'!M9="","",'Model inputs'!M9)) -> 34916 | O78: 0 | P78: 0 | Q78: 0 | R78: 0 | S78: 0 | T78: 0 | U78: 0 | V78: 0 | W78: 0 | X78: =IF(IF(IF(ISERROR(DATE(2026,10,1)=DATE(YEAR('Model inputs'!AA123),MONTH('Model inputs'!AA123),1)),DATE(2026,10,1)=DATE(YEAR('Model inputs'!AA123),MONTH('Model inputs'!AA123),1),IF(DATE(YEAR('Model inputs'!AA123),MONTH('Model inputs'!AA123),1)="","",DATE(2026,10,1)=DATE(YEAR('Model inputs'!AA123),MONTH('Model inputs'!AA123),1)))="",FALSE,IF(ISERROR(DATE(2026,10,1)=DATE(YEAR('Model inputs'!AA123),MONTH('Model inputs'!AA123),1)),DATE(2026,10,1)=DATE(YEAR('Model inputs'!AA123),MONTH('Model inputs'!AA123),1),IF(DATE(YEAR('Model inputs'!AA123),MONTH('Model inputs'!AA123),1)="","",DATE(2026,10,1)=DATE(YEAR('Model inputs'!AA123),MONTH('Model inputs'!AA123),1)))),IF('Model inputs'!AA108="","",'Model inputs'!AA108),IF('Model inputs'!W9="","",'Model inputs'!W9)) -> 0 | Y78: =IF(IF(IF(ISERROR(DATE(2026,11,1)=DATE(YEAR('Model inputs'!AA123),MONTH('Model inputs'!AA123),1)),DATE(2026,11,1)=DATE(YEAR('Model inputs'!AA123),MONTH('Model inputs'!AA123),1),IF(DATE(YEAR('Model inputs'!AA123),MONTH('Model inputs'!AA123),1)="","",DATE(2026,11,1)=DATE(YEAR('Model inputs'!AA123),MONTH('Model inputs'!AA123),1)))="",FALSE,IF(ISERROR(DATE(2026,11,1)=DATE(YEAR('Model inputs'!AA123),MONTH('Model inputs'!AA123),1)),DATE(2026,11,1)=DATE(YEAR('Model inputs'!AA123),MONTH('Model inputs'!AA123),1),IF(DATE(YEAR('Model inputs'!AA123),MONTH('Model inputs'!AA123),1)="","",DATE(2026,11,1)=DATE(YEAR('Model inputs'!AA123),MONTH('Model inputs'!AA123),1)))),IF('Model inputs'!AA108="","",'Model inputs'!AA108),IF('Model inputs'!X9="","",'Model inputs'!X9)) -> -300
A79: Caixa inicial do mês — projeção Base (EUR) · Caixa final — projeção Base (EUR) · Base — fixos 500 €/mês · Base — fixos 500 €/mês | B79: =IF(IF(IF(ISERROR(DATE(2026,12,1)=DATE(YEAR('Model inputs'!AA124),MONTH('Model inputs'!AA124),1)),DATE(2026,12,1)=DATE(YEAR('Model inputs'!AA124),MONTH('Model inputs'!AA124),1),IF(DATE(YEAR('Model inputs'!AA124),MONTH('Model inputs'!AA124),1)="","",DATE(2026,12,1)=DATE(YEAR('Model inputs'!AA124),MONTH('Model inputs'!AA124),1)))="",FALSE,IF(ISERROR(DATE(2026,12,1)=DATE(YEAR('Model inputs'!AA124),MONTH('Model inputs'!AA124),1)),DATE(2026,12,1)=DATE(YEAR('Model inputs'!AA124),MONTH('Model inputs'!AA124),1),IF(DATE(YEAR('Model inputs'!AA124),MONTH('Model inputs'!AA124),1)="","",DATE(2026,12,1)=DATE(YEAR('Model inputs'!AA124),MONTH('Model inputs'!AA124),1)))),IF('Model inputs'!AA109="","",'Model inputs'!AA109),IF('Model inputs'!Y10="","",'Model inputs'!Y10)) -> -1000 | C79: =IF(IF(IF(ISERROR(DATE(2027,1,1)=DATE(YEAR('Model inputs'!AA124),MONTH('Model inputs'!AA124),1)),DATE(2027,1,1)=DATE(YEAR('Model inputs'!AA124),MONTH('Model inputs'!AA124),1),IF(DATE(YEAR('Model inputs'!AA124),MONTH('Model inputs'!AA124),1)="","",DATE(2027,1,1)=DATE(YEAR('Model inputs'!AA124),MONTH('Model inputs'!AA124),1)))="",FALSE,IF(ISERROR(DATE(2027,1,1)=DATE(YEAR('Model inputs'!AA124),MONTH('Model inputs'!AA124),1)),DATE(2027,1,1)=DATE(YEAR('Model inputs'!AA124),MONTH('Model inputs'!AA124),1),IF(DATE(YEAR('Model inputs'!AA124),MONTH('Model inputs'!AA124),1)="","",DATE(2027,1,1)=DATE(YEAR('Model inputs'!AA124),MONTH('Model inputs'!AA124),1)))),IF('Model inputs'!AA109="","",'Model inputs'!AA109),IF('Model inputs'!B10="","",'Model inputs'!B10)) -> 20000 | D79: =IF(IF(IF(ISERROR(DATE(2027,2,1)=DATE(YEAR('Model inputs'!AA124),MONTH('Model inputs'!AA124),1)),DATE(2027,2,1)=DATE(YEAR('Model inputs'!AA124),MONTH('Model inputs'!AA124),1),IF(DATE(YEAR('Model inputs'!AA124),MONTH('Model inputs'!AA124),1)="","",DATE(2027,2,1)=DATE(YEAR('Model inputs'!AA124),MONTH('Model inputs'!AA124),1)))="",FALSE,IF(ISERROR(DATE(2027,2,1)=DATE(YEAR('Model inputs'!AA124),MONTH('Model inputs'!AA124),1)),DATE(2027,2,1)=DATE(YEAR('Model inputs'!AA124),MONTH('Model inputs'!AA124),1),IF(DATE(YEAR('Model inputs'!AA124),MONTH('Model inputs'!AA124),1)="","",DATE(2027,2,1)=DATE(YEAR('Model inputs'!AA124),MONTH('Model inputs'!AA124),1)))),IF('Model inputs'!AA109="","",'Model inputs'!AA109),IF('Model inputs'!C10="","",'Model inputs'!C10)) -> 19569 | E79: =IF(IF(IF(ISERROR(DATE(2027,3,1)=DATE(YEAR('Model inputs'!AA124),MONTH('Model inputs'!AA124),1)),DATE(2027,3,1)=DATE(YEAR('Model inputs'!AA124),MONTH('Model inputs'!AA124),1),IF(DATE(YEAR('Model inputs'!AA124),MONTH('Model inputs'!AA124),1)="","",DATE(2027,3,1)=DATE(YEAR('Model inputs'!AA124),MONTH('Model inputs'!AA124),1)))="",FALSE,IF(ISERROR(DATE(2027,3,1)=DATE(YEAR('Model inputs'!AA124),MONTH('Model inputs'!AA124),1)),DATE(2027,3,1)=DATE(YEAR('Model inputs'!AA124),MONTH('Model inputs'!AA124),1),IF(DATE(YEAR('Model inputs'!AA124),MONTH('Model inputs'!AA124),1)="","",DATE(2027,3,1)=DATE(YEAR('Model inputs'!AA124),MONTH('Model inputs'!AA124),1)))),IF('Model inputs'!AA109="","",'Model inputs'!AA109),IF('Model inputs'!D10="","",'Model inputs'!D10)) -> 19345 | F79: =IF(IF(IF(ISERROR(DATE(2027,4,1)=DATE(YEAR('Model inputs'!AA124),MONTH('Model inputs'!AA124),1)),DATE(2027,4,1)=DATE(YEAR('Model inputs'!AA124),MONTH('Model inputs'!AA124),1),IF(DATE(YEAR('Model inputs'!AA124),MONTH('Model inputs'!AA124),1)="","",DATE(2027,4,1)=DATE(YEAR('Model inputs'!AA124),MONTH('Model inputs'!AA124),1)))="",FALSE,IF(ISERROR(DATE(2027,4,1)=DATE(YEAR('Model inputs'!AA124),MONTH('Model inputs'!AA124),1)),DATE(2027,4,1)=DATE(YEAR('Model inputs'!AA124),MONTH('Model inputs'!AA124),1),IF(DATE(YEAR('Model inputs'!AA124),MONTH('Model inputs'!AA124),1)="","",DATE(2027,4,1)=DATE(YEAR('Model inputs'!AA124),MONTH('Model inputs'!AA124),1)))),IF('Model inputs'!AA109="","",'Model inputs'!AA109),IF('Model inputs'!E10="","",'Model inputs'!E10)) -> 19466 | G79: =IF(IF(IF(ISERROR(DATE(2027,5,1)=DATE(YEAR('Model inputs'!AA124),MONTH('Model inputs'!AA124),1)),DATE(2027,5,1)=DATE(YEAR('Model inputs'!AA124),MONTH('Model inputs'!AA124),1),IF(DATE(YEAR('Model inputs'!AA124),MONTH('Model inputs'!AA124),1)="","",DATE(2027,5,1)=DATE(YEAR('Model inputs'!AA124),MONTH('Model inputs'!AA124),1)))="",FALSE,IF(ISERROR(DATE(2027,5,1)=DATE(YEAR('Model inputs'!AA124),MONTH('Model inputs'!AA124),1)),DATE(2027,5,1)=DATE(YEAR('Model inputs'!AA124),MONTH('Model inputs'!AA124),1),IF(DATE(YEAR('Model inputs'!AA124),MONTH('Model inputs'!AA124),1)="","",DATE(2027,5,1)=DATE(YEAR('Model inputs'!AA124),MONTH('Model inputs'!AA124),1)))),IF('Model inputs'!AA109="","",'Model inputs'!AA109),IF('Model inputs'!F10="","",'Model inputs'!F10)) -> 19932 | H79: =IF(IF(IF(ISERROR(DATE(2027,6,1)=DATE(YEAR('Model inputs'!AA124),MONTH('Model inputs'!AA124),1)),DATE(2027,6,1)=DATE(YEAR('Model inputs'!AA124),MONTH('Model inputs'!AA124),1),IF(DATE(YEAR('Model inputs'!AA124),MONTH('Model inputs'!AA124),1)="","",DATE(2027,6,1)=DATE(YEAR('Model inputs'!AA124),MONTH('Model inputs'!AA124),1)))="",FALSE,IF(ISERROR(DATE(2027,6,1)=DATE(YEAR('Model inputs'!AA124),MONTH('Model inputs'!AA124),1)),DATE(2027,6,1)=DATE(YEAR('Model inputs'!AA124),MONTH('Model inputs'!AA124),1),IF(DATE(YEAR('Model inputs'!AA124),MONTH('Model inputs'!AA124),1)="","",DATE(2027,6,1)=DATE(YEAR('Model inputs'!AA124),MONTH('Model inputs'!AA124),1)))),IF('Model inputs'!AA109="","",'Model inputs'!AA109),IF('Model inputs'!G10="","",'Model inputs'!G10)) -> 20812 | I79: =IF(IF(IF(ISERROR(DATE(2027,7,1)=DATE(YEAR('Model inputs'!AA124),MONTH('Model inputs'!AA124),1)),DATE(2027,7,1)=DATE(YEAR('Model inputs'!AA124),MONTH('Model inputs'!AA124),1),IF(DATE(YEAR('Model inputs'!AA124),MONTH('Model inputs'!AA124),1)="","",DATE(2027,7,1)=DATE(YEAR('Model inputs'!AA124),MONTH('Model inputs'!AA124),1)))="",FALSE,IF(ISERROR(DATE(2027,7,1)=DATE(YEAR('Model inputs'!AA124),MONTH('Model inputs'!AA124),1)),DATE(2027,7,1)=DATE(YEAR('Model inputs'!AA124),MONTH('Model inputs'!AA124),1),IF(DATE(YEAR('Model inputs'!AA124),MONTH('Model inputs'!AA124),1)="","",DATE(2027,7,1)=DATE(YEAR('Model inputs'!AA124),MONTH('Model inputs'!AA124),1)))),IF('Model inputs'!AA109="","",'Model inputs'!AA109),IF('Model inputs'!H10="","",'Model inputs'!H10)) -> 22106 | J79: =IF(IF(IF(ISERROR(DATE(2027,8,1)=DATE(YEAR('Model inputs'!AA124),MONTH('Model inputs'!AA124),1)),DATE(2027,8,1)=DATE(YEAR('Model inputs'!AA124),MONTH('Model inputs'!AA124),1),IF(DATE(YEAR('Model inputs'!AA124),MONTH('Model inputs'!AA124),1)="","",DATE(2027,8,1)=DATE(YEAR('Model inputs'!AA124),MONTH('Model inputs'!AA124),1)))="",FALSE,IF(ISERROR(DATE(2027,8,1)=DATE(YEAR('Model inputs'!AA124),MONTH('Model inputs'!AA124),1)),DATE(2027,8,1)=DATE(YEAR('Model inputs'!AA124),MONTH('Model inputs'!AA124),1),IF(DATE(YEAR('Model inputs'!AA124),MONTH('Model inputs'!AA124),1)="","",DATE(2027,8,1)=DATE(YEAR('Model inputs'!AA124),MONTH('Model inputs'!AA124),1)))),IF('Model inputs'!AA109="","",'Model inputs'!AA109),IF('Model inputs'!I10="","",'Model inputs'!I10)) -> 23814 | K79: =IF(IF(IF(ISERROR(DATE(2027,9,1)=DATE(YEAR('Model inputs'!AA124),MONTH('Model inputs'!AA124),1)),DATE(2027,9,1)=DATE(YEAR('Model inputs'!AA124),MONTH('Model inputs'!AA124),1),IF(DATE(YEAR('Model inputs'!AA124),MONTH('Model inputs'!AA124),1)="","",DATE(2027,9,1)=DATE(YEAR('Model inputs'!AA124),MONTH('Model inputs'!AA124),1)))="",FALSE,IF(ISERROR(DATE(2027,9,1)=DATE(YEAR('Model inputs'!AA124),MONTH('Model inputs'!AA124),1)),DATE(2027,9,1)=DATE(YEAR('Model inputs'!AA124),MONTH('Model inputs'!AA124),1),IF(DATE(YEAR('Model inputs'!AA124),MONTH('Model inputs'!AA124),1)="","",DATE(2027,9,1)=DATE(YEAR('Model inputs'!AA124),MONTH('Model inputs'!AA124),1)))),IF('Model inputs'!AA109="","",'Model inputs'!AA109),IF('Model inputs'!J10="","",'Model inputs'!J10)) -> 25936 | L79: =IF(IF(IF(ISERROR(DATE(2027,10,1)=DATE(YEAR('Model inputs'!AA124),MONTH('Model inputs'!AA124),1)),DATE(2027,10,1)=DATE(YEAR('Model inputs'!AA124),MONTH('Model inputs'!AA124),1),IF(DATE(YEAR('Model inputs'!AA124),MONTH('Model inputs'!AA124),1)="","",DATE(2027,10,1)=DATE(YEAR('Model inputs'!AA124),MONTH('Model inputs'!AA124),1)))="",FALSE,IF(ISERROR(DATE(2027,10,1)=DATE(YEAR('Model inputs'!AA124),MONTH('Model inputs'!AA124),1)),DATE(2027,10,1)=DATE(YEAR('Model inputs'!AA124),MONTH('Model inputs'!AA124),1),IF(DATE(YEAR('Model inputs'!AA124),MONTH('Model inputs'!AA124),1)="","",DATE(2027,10,1)=DATE(YEAR('Model inputs'!AA124),MONTH('Model inputs'!AA124),1)))),IF('Model inputs'!AA109="","",'Model inputs'!AA109),IF('Model inputs'!K10="","",'Model inputs'!K10)) -> 28196 | M79: =IF(IF(IF(ISERROR(DATE(2027,11,1)=DATE(YEAR('Model inputs'!AA124),MONTH('Model inputs'!AA124),1)),DATE(2027,11,1)=DATE(YEAR('Model inputs'!AA124),MONTH('Model inputs'!AA124),1),IF(DATE(YEAR('Model inputs'!AA124),MONTH('Model inputs'!AA124),1)="","",DATE(2027,11,1)=DATE(YEAR('Model inputs'!AA124),MONTH('Model inputs'!AA124),1)))="",FALSE,IF(ISERROR(DATE(2027,11,1)=DATE(YEAR('Model inputs'!AA124),MONTH('Model inputs'!AA124),1)),DATE(2027,11,1)=DATE(YEAR('Model inputs'!AA124),MONTH('Model inputs'!AA124),1),IF(DATE(YEAR('Model inputs'!AA124),MONTH('Model inputs'!AA124),1)="","",DATE(2027,11,1)=DATE(YEAR('Model inputs'!AA124),MONTH('Model inputs'!AA124),1)))),IF('Model inputs'!AA109="","",'Model inputs'!AA109),IF('Model inputs'!L10="","",'Model inputs'!L10)) -> 30456 | N79: =IF(IF(IF(ISERROR(DATE(2027,12,1)=DATE(YEAR('Model inputs'!AA124),MONTH('Model inputs'!AA124),1)),DATE(2027,12,1)=DATE(YEAR('Model inputs'!AA124),MONTH('Model inputs'!AA124),1),IF(DATE(YEAR('Model inputs'!AA124),MONTH('Model inputs'!AA124),1)="","",DATE(2027,12,1)=DATE(YEAR('Model inputs'!AA124),MONTH('Model inputs'!AA124),1)))="",FALSE,IF(ISERROR(DATE(2027,12,1)=DATE(YEAR('Model inputs'!AA124),MONTH('Model inputs'!AA124),1)),DATE(2027,12,1)=DATE(YEAR('Model inputs'!AA124),MONTH('Model inputs'!AA124),1),IF(DATE(YEAR('Model inputs'!AA124),MONTH('Model inputs'!AA124),1)="","",DATE(2027,12,1)=DATE(YEAR('Model inputs'!AA124),MONTH('Model inputs'!AA124),1)))),IF('Model inputs'!AA109="","",'Model inputs'!AA109),IF('Model inputs'!M10="","",'Model inputs'!M10)) -> 32716 | O79: 0 | P79: 0 | Q79: 0 | R79: 0 | S79: 0 | T79: 0 | U79: 0 | V79: 0 | W79: 0 | X79: =IF(IF(IF(ISERROR(DATE(2026,10,1)=DATE(YEAR('Model inputs'!AA124),MONTH('Model inputs'!AA124),1)),DATE(2026,10,1)=DATE(YEAR('Model inputs'!AA124),MONTH('Model inputs'!AA124),1),IF(DATE(YEAR('Model inputs'!AA124),MONTH('Model inputs'!AA124),1)="","",DATE(2026,10,1)=DATE(YEAR('Model inputs'!AA124),MONTH('Model inputs'!AA124),1)))="",FALSE,IF(ISERROR(DATE(2026,10,1)=DATE(YEAR('Model inputs'!AA124),MONTH('Model inputs'!AA124),1)),DATE(2026,10,1)=DATE(YEAR('Model inputs'!AA124),MONTH('Model inputs'!AA124),1),IF(DATE(YEAR('Model inputs'!AA124),MONTH('Model inputs'!AA124),1)="","",DATE(2026,10,1)=DATE(YEAR('Model inputs'!AA124),MONTH('Model inputs'!AA124),1)))),IF('Model inputs'!AA109="","",'Model inputs'!AA109),IF('Model inputs'!W10="","",'Model inputs'!W10)) -> 0 | Y79: =IF(IF(IF(ISERROR(DATE(2026,11,1)=DATE(YEAR('Model inputs'!AA124),MONTH('Model inputs'!AA124),1)),DATE(2026,11,1)=DATE(YEAR('Model inputs'!AA124),MONTH('Model inputs'!AA124),1),IF(DATE(YEAR('Model inputs'!AA124),MONTH('Model inputs'!AA124),1)="","",DATE(2026,11,1)=DATE(YEAR('Model inputs'!AA124),MONTH('Model inputs'!AA124),1)))="",FALSE,IF(ISERROR(DATE(2026,11,1)=DATE(YEAR('Model inputs'!AA124),MONTH('Model inputs'!AA124),1)),DATE(2026,11,1)=DATE(YEAR('Model inputs'!AA124),MONTH('Model inputs'!AA124),1),IF(DATE(YEAR('Model inputs'!AA124),MONTH('Model inputs'!AA124),1)="","",DATE(2026,11,1)=DATE(YEAR('Model inputs'!AA124),MONTH('Model inputs'!AA124),1)))),IF('Model inputs'!AA109="","",'Model inputs'!AA109),IF('Model inputs'!X10="","",'Model inputs'!X10)) -> -500
A80: Custo variável por domínio por mês — estimativa (EUR) · Entrega mensal — projeção Base (EUR) · Teste Pro 109 € — fixos 500 €/mês · Teste Pro 109 € — fixos 500 €/mês | AA80: =3 -> 3
A81: Custo variável por domínio por mês — estimativa (EUR) · Entrega mensal — projeção Base (EUR) · Base — fixos 400 €/mês · Base — fixos 400 €/mês | AA81: =3 -> 3
A82: Custo variável por domínio por mês — estimativa (EUR) · Entrega mensal — projeção Base (EUR) · Teste Pro 109 € — fixos 400 €/mês · Teste Pro 109 € — fixos 400 €/mês | AA82: =3 -> 3
A83: Custo variável por domínio por mês — estimativa (EUR) · Entrega mensal — projeção Base (EUR) · Base — fixos 300 €/mês · Base — fixos 300 €/mês | AA83: =3 -> 3
A84: Custo variável por domínio por mês — estimativa (EUR) · Entrega mensal — projeção Base (EUR) · Teste Pro 119 € — fixos 500 €/mês · Teste Pro 119 € — fixos 500 €/mês | AA84: =3 -> 3
A85: Custo variável por domínio por mês — estimativa (EUR) · Entrega mensal — projeção Base (EUR) · Teste Pro 119 € — fixos 400 €/mês · Teste Pro 119 € — fixos 400 €/mês | AA85: =3 -> 3
A86: Custo variável por domínio por mês — estimativa (EUR) · Entrega mensal — projeção Base (EUR) · Teste Pro 109 € — fixos 300 €/mês · Teste Pro 109 € — fixos 300 €/mês | AA86: =3 -> 3
A87: Custo variável por domínio por mês — estimativa (EUR) · Entrega mensal — projeção Base (EUR) · Teste Pro 119 € — fixos 300 €/mês · Teste Pro 119 € — fixos 300 €/mês | AA87: =3 -> 3
A88: Custos totais mensais — projeção Base (EUR) · EBITDA mensal — projeção Base (EUR) · Teste Pro 109 € — fixos 500 €/mês · Teste Pro 109 € — fixos 500 €/mês | B88: ='Model inputs'!B52+'Model inputs'!B116 -> 500 | C88: ='Model inputs'!C52+'Model inputs'!C116 -> 530 | D88: ='Model inputs'!D52+'Model inputs'!D116 -> 620 | E88: ='Model inputs'!E52+'Model inputs'!E116 -> 770 | F88: ='Model inputs'!F52+'Model inputs'!F116 -> 920 | G88: ='Model inputs'!G52+'Model inputs'!G116 -> 1100 | H88: ='Model inputs'!H52+'Model inputs'!H116 -> 1280 | I88: ='Model inputs'!I52+'Model inputs'!I116 -> 1460 | ... N88: ='Model inputs'!N52+'Model inputs'!N116 -> 1700 | O88: 0 | P88: 0 | Q88: 0 | R88: 0 | S88: 0 | T88: 0 | U88: 0 | V88: 0 | W88: 0 | X88: ='Model inputs'!X52+'Model inputs'!X116 -> 500 | Y88: ='Model inputs'!Y52+'Model inputs'!Y116 -> 500
A89: Custos totais mensais — projeção Base (EUR) · EBITDA mensal — projeção Base (EUR) · Teste Pro 109 € — fixos 400 €/mês · Teste Pro 109 € — fixos 400 €/mês | B89: ='Model inputs'!B54+'Model inputs'!B117 -> 400 | C89: ='Model inputs'!C54+'Model inputs'!C117 -> 430 | D89: ='Model inputs'!D54+'Model inputs'!D117 -> 520 | E89: ='Model inputs'!E54+'Model inputs'!E117 -> 670 | F89: ='Model inputs'!F54+'Model inputs'!F117 -> 820 | G89: ='Model inputs'!G54+'Model inputs'!G117 -> 1000 | H89: ='Model inputs'!H54+'Model inputs'!H117 -> 1180 | I89: ='Model inputs'!I54+'Model inputs'!I117 -> 1360 | ... N89: ='Model inputs'!N54+'Model inputs'!N117 -> 1600 | O89: 0 | P89: 0 | Q89: 0 | R89: 0 | S89: 0 | T89: 0 | U89: 0 | V89: 0 | W89: 0 | X89: ='Model inputs'!X54+'Model inputs'!X117 -> 400 | Y89: ='Model inputs'!Y54+'Model inputs'!Y117 -> 400
A90: Custos totais mensais — projeção Base (EUR) · EBITDA mensal — projeção Base (EUR) · Teste Pro 119 € — fixos 500 €/mês · Teste Pro 119 € — fixos 500 €/mês | B90: ='Model inputs'!B56+'Model inputs'!B118 -> 500 | C90: ='Model inputs'!C56+'Model inputs'!C118 -> 530 | D90: ='Model inputs'!D56+'Model inputs'!D118 -> 620 | E90: ='Model inputs'!E56+'Model inputs'!E118 -> 770 | F90: ='Model inputs'!F56+'Model inputs'!F118 -> 920 | G90: ='Model inputs'!G56+'Model inputs'!G118 -> 1100 | H90: ='Model inputs'!H56+'Model inputs'!H118 -> 1280 | I90: ='Model inputs'!I56+'Model inputs'!I118 -> 1460 | ... N90: ='Model inputs'!N56+'Model inputs'!N118 -> 1700 | O90: 0 | P90: 0 | Q90: 0 | R90: 0 | S90: 0 | T90: 0 | U90: 0 | V90: 0 | W90: 0 | X90: ='Model inputs'!X56+'Model inputs'!X118 -> 500 | Y90: ='Model inputs'!Y56+'Model inputs'!Y118 -> 500
A91: Custos totais mensais — projeção Base (EUR) · EBITDA mensal — projeção Base (EUR) · Teste Pro 119 € — fixos 400 €/mês · Teste Pro 119 € — fixos 400 €/mês | B91: ='Model inputs'!B57+'Model inputs'!B119 -> 400 | C91: ='Model inputs'!C57+'Model inputs'!C119 -> 430 | D91: ='Model inputs'!D57+'Model inputs'!D119 -> 520 | E91: ='Model inputs'!E57+'Model inputs'!E119 -> 670 | F91: ='Model inputs'!F57+'Model inputs'!F119 -> 820 | G91: ='Model inputs'!G57+'Model inputs'!G119 -> 1000 | H91: ='Model inputs'!H57+'Model inputs'!H119 -> 1180 | I91: ='Model inputs'!I57+'Model inputs'!I119 -> 1360 | ... N91: ='Model inputs'!N57+'Model inputs'!N119 -> 1600 | O91: 0 | P91: 0 | Q91: 0 | R91: 0 | S91: 0 | T91: 0 | U91: 0 | V91: 0 | W91: 0 | X91: ='Model inputs'!X57+'Model inputs'!X119 -> 400 | Y91: ='Model inputs'!Y57+'Model inputs'!Y119 -> 400
A92: Custos totais mensais — projeção Base (EUR) · EBITDA mensal — projeção Base (EUR) · Teste Pro 109 € — fixos 300 €/mês · Teste Pro 109 € — fixos 300 €/mês | B92: ='Model inputs'!B58+'Model inputs'!B120 -> 300 | C92: ='Model inputs'!C58+'Model inputs'!C120 -> 330 | D92: ='Model inputs'!D58+'Model inputs'!D120 -> 420 | E92: ='Model inputs'!E58+'Model inputs'!E120 -> 570 | F92: ='Model inputs'!F58+'Model inputs'!F120 -> 720 | G92: ='Model inputs'!G58+'Model inputs'!G120 -> 900 | H92: ='Model inputs'!H58+'Model inputs'!H120 -> 1080 | I92: ='Model inputs'!I58+'Model inputs'!I120 -> 1260 | ... N92: ='Model inputs'!N58+'Model inputs'!N120 -> 1500 | O92: 0 | P92: 0 | Q92: 0 | R92: 0 | S92: 0 | T92: 0 | U92: 0 | V92: 0 | W92: 0 | X92: ='Model inputs'!X58+'Model inputs'!X120 -> 300 | Y92: ='Model inputs'!Y58+'Model inputs'!Y120 -> 300
A93: Custos totais mensais — projeção Base (EUR) · EBITDA mensal — projeção Base (EUR) · Teste Pro 119 € — fixos 300 €/mês · Teste Pro 119 € — fixos 300 €/mês | B93: ='Model inputs'!B59+'Model inputs'!B121 -> 300 | C93: ='Model inputs'!C59+'Model inputs'!C121 -> 330 | D93: ='Model inputs'!D59+'Model inputs'!D121 -> 420 | E93: ='Model inputs'!E59+'Model inputs'!E121 -> 570 | F93: ='Model inputs'!F59+'Model inputs'!F121 -> 720 | G93: ='Model inputs'!G59+'Model inputs'!G121 -> 900 | H93: ='Model inputs'!H59+'Model inputs'!H121 -> 1080 | I93: ='Model inputs'!I59+'Model inputs'!I121 -> 1260 | ... N93: ='Model inputs'!N59+'Model inputs'!N121 -> 1500 | O93: 0 | P93: 0 | Q93: 0 | R93: 0 | S93: 0 | T93: 0 | U93: 0 | V93: 0 | W93: 0 | X93: ='Model inputs'!X59+'Model inputs'!X121 -> 300 | Y93: ='Model inputs'!Y59+'Model inputs'!Y121 -> 300
A94: Domínios médios por cliente Pro — hipótese · Entrega mensal — projeção Base (EUR) · Teste Pro 109 € — fixos 500 €/mês · Teste Pro 109 € — fixos 500 €/mês | AA94: =10 -> 10
A95: Domínios médios por cliente Pro — hipótese · Entrega mensal — projeção Base (EUR) · Base — fixos 400 €/mês · Base — fixos 400 €/mês | AA95: =10 -> 10
A96: Domínios médios por cliente Pro — hipótese · Entrega mensal — projeção Base (EUR) · Teste Pro 109 € — fixos 400 €/mês · Teste Pro 109 € — fixos 400 €/mês | AA96: =10 -> 10
A97: Domínios médios por cliente Pro — hipótese · Entrega mensal — projeção Base (EUR) · Base — fixos 300 €/mês · Base — fixos 300 €/mês | AA97: =10 -> 10
A98: Domínios médios por cliente Pro — hipótese · Entrega mensal — projeção Base (EUR) · Teste Pro 119 € — fixos 500 €/mês · Teste Pro 119 € — fixos 500 €/mês | AA98: =10 -> 10
A99: Domínios médios por cliente Pro — hipótese · Entrega mensal — projeção Base (EUR) · Teste Pro 119 € — fixos 400 €/mês · Teste Pro 119 € — fixos 400 €/mês | AA99: =10 -> 10
A100: Domínios médios por cliente Pro — hipótese · Entrega mensal — projeção Base (EUR) · Teste Pro 109 € — fixos 300 €/mês · Teste Pro 109 € — fixos 300 €/mês | AA100: =10 -> 10
A101: Domínios médios por cliente Pro — hipótese · Entrega mensal — projeção Base (EUR) · Teste Pro 119 € — fixos 300 €/mês · Teste Pro 119 € — fixos 300 €/mês | AA101: =10 -> 10
...
